Workbook

Sheet Work Queue
A1: Work Queue - counts update automatically from All Claims - Draft
A3: Follow-up Status | B3: Claims | D3: How to use
A4: OVERDUE | B4: =COUNTIF('All Claims - Draft'!$BF:$BF,A4) -> 132 | D4: • Orange headers on All Claims = columns you type in. Navy = report data. Grey = helper formulas (don't type there).
A5: Due within 7 days | B5: =COUNTIF('All Claims - Draft'!$BF:$BF,A5) -> 27 | D5: • Filter "Follow-up Status" = OVERDUE to get today's worklist.
A6: No review date set | B6: =COUNTIF('All Claims - Draft'!$BF:$BF,A6) -> 62 | D6: • Filter "Missing Info" (non-blank) to see what each claim still needs.
A7: Scheduled | B7: =COUNTIF('All Claims - Draft'!$BF:$BF,A7) -> 77 | D7: • "Suggested Denial Reason" reads the Denial Code; "Suggested Next Step" reads the Denial Reason.
A8: Closed | B8: =COUNTIF('All Claims - Draft'!$BF:$BF,A8) -> 195 | D8: • Dropdowns are on Claim Status, Last Action, Denial Reason, Denial Code and both Adjustment Code columns; you can still type a value not on the list.
D9: • See the Change Log tab for every cell changed when this copy was made.
A10: Claim Status | B10: Claims
A11: Finalized | B11: =COUNTIF('All Claims - Draft'!$A:$A,A11) -> 195
A12: Denied | B12: =COUNTIF('All Claims - Draft'!$A:$A,A12) -> 163
A13: Under Review | B13: =COUNTIF('All Claims - Draft'!$A:$A,A13) -> 51
A14: Pending | B14: =COUNTIF('All Claims - Draft'!$A:$A,A14) -> 39
A15: PAID | B15: =COUNTIF('All Claims - Draft'!$A:$A,A15) -> 23
A16: Rejected | B16: =COUNTIF('All Claims - Draft'!$A:$A,A16) -> 15
A17: Received | B17: =COUNTIF('All Claims - Draft'!$A:$A,A17) -> 4
A18: Not found | B18: =COUNTIF('All Claims - Draft'!$A:$A,A18) -> 3
A20: Claims missing this field | B20: Claims
A21: Notes | B21: =COUNTIF('All Claims - Draft'!$BH:$BH,"*"&A21&"*") -> 31
A22: Latest Date Worked | B22: =COUNTIF('All Claims - Draft'!$BH:$BH,"*"&A22&"*") -> 61
A23: Last Action | B23: =COUNTIF('All Claims - Draft'!$BH:$BH,"*"&A23&"*") -> 53
A24: Denial Reason | B24: =COUNTIF('All Claims - Draft'!$BH:$BH,"*"&A24&"*") -> 8
A25: Denial Code | B25: =COUNTIF('All Claims - Draft'!$BH:$BH,"*"&A25&"*") -> 69
A26: Next Review Date | B26: =COUNTIF('All Claims - Draft'!$BH:$BH,"*"&A26&"*") -> 62
A27: Next Step | B27: =COUNTIF('All Claims - Draft'!$BH:$BH,"*"&A27&"*") -> 198
A28: CPT outcome | B28: =COUNTIF('All Claims - Draft'!$BH:$BH,"*"&A28&"*") -> 7
A30: Open claims by Denial Reason (not Finalized) | B30: Claims
A31: No authorization | B31: =COUNTIFS('All Claims - Draft'!$BA:$BA,A31&"*",'All Claims - Draft'!$A:$A,"<>Finalized") -> 19
A32: Timely filing | B32: =COUNTIFS('All Claims - Draft'!$BA:$BA,A32&"*",'All Claims - Draft'!$A:$A,"<>Finalized") -> 3
A33: Medical records needed | B33: =COUNTIFS('All Claims - Draft'!$BA:$BA,A33&"*",'All Claims - Draft'!$A:$A,"<>Finalized") -> 45
A34: Bundled / NCCI edit | B34: =COUNTIFS('All Claims - Draft'!$BA:$BA,A34&"*",'All Claims - Draft'!$A:$A,"<>Finalized") -> 21
A35: Modifier issue | B35: =COUNTIFS('All Claims - Draft'!$BA:$BA,A35&"*",'All Claims - Draft'!$A:$A,"<>Finalized") -> 10
A36: Diagnosis issue | B36: =COUNTIFS('All Claims - Draft'!$BA:$BA,A36&"*",'All Claims - Draft'!$A:$A,"<>Finalized") -> 4
A37: Coding / billing error | B37: =COUNTIFS('All Claims - Draft'!$BA:$BA,A37&"*",'All Claims - Draft'!$A:$A,"<>Finalized") -> 16
A38: Not covered by plan | B38: =COUNTIFS('All Claims - Draft'!$BA:$BA,A38&"*",'All Claims - Draft'!$A:$A,"<>Finalized") -> 3
A39: Not covered by secondary | B39: =COUNTIFS('All Claims - Draft'!$BA:$BA,A39&"*",'All Claims - Draft'!$A:$A,"<>Finalized") -> 0
A40: Medical necessity / frequency | B40: =COUNTIFS('All Claims - Draft'!$BA:$BA,A40&"*",'All Claims - Draft'!$A:$A,"<>Finalized") -> 8
A41: Wrong payer / vendor | B41: =COUNTIFS('All Claims - Draft'!$BA:$BA,A41&"*",'All Claims - Draft'!$A:$A,"<>Finalized") -> 22
A42: Other insurance / COB | B42: =COUNTIFS('All Claims - Draft'!$BA:$BA,A42&"*",'All Claims - Draft'!$A:$A,"<>Finalized") -> 11
... A52: Other | B52: =COUNTIFS('All Claims - Draft'!$BA:$BA,A52&"*",'All Claims - Draft'!$A:$A,"<>Finalized") -> 13

Sheet All Claims - Draft
A1: Claim Status | B1: Notes | C1: Primary Claim ID | D1: Processed Date | E1: Chart Number | F1: Date of Service | G1: Responsible Payer | H1: Primary Payer Name | I1: Secondary Payer Name | J1: Procedure Code | K1: Latest Date Worked | L1: Days Until Deadline | M1: Days Until Corrected Claim Deadline | N1: Days Until Appeal Deadline | O1: Filing Deadline | P1: Filing Limit | Q1: Limit Carrier | R1: Corrected Claim Limit | S1: Corrected Claim From | T1: Appeal Limit | U1: Appeal From | V1: Service Month | W1: Specialty | X1: Modifier 1 | Y1: Modifier 2 | Z1: Modifier 3 | AA1: Units | AB1: AR Age by Service Date | AC1: Procedure Code 1 | AD1: Procedure Code 2 | AE1: Procedure Code 3 | AF1: Procedure Code 4 | AG1: Procedure Code 5 | AH1: Procedure Code 6 | AI1: Procedure Code 7 | AJ1: Diagnosis Code 1 | AK1: Diagnosis Code 2 | AL1: Diagnosis Code 3 | AM1: Diagnosis Code 4 | AN1: Secondary Claim ID | AO1: Rendering Provider | AP1: Location Name | AQ1: Created Date | AR1: CPT Codes Adjusted (not payable) | AS1: Adjustment Code | AT1: CPT Codes Adjusted (payable) | AU1: Adjustment Code (payable) | AV1: CPT Codes Paid | AW1: CPT Codes Worked - Adjusted | AX1: CPT Codes Worked | AY1: Last Action | AZ1: Prior Actions | BA1: Denial Reason | BB1: Denial Code | BC1: Reference # | BD1: Next Review Date | BE1: Next Step | BF1: Follow-up Status | BG1: Days Since Worked | BH1: Missing Info | BI1: Suggested Denial Reason (from code) | BJ1: Suggested Next Step (from reason)
A2: PAID | B2: OP | C2: 546185672 | D2: 46252 | E2: HF514237620 | F2: 46035 | G2: Aetna Legacy | H2: DME Region D | I2: Aetna Legacy | J2: A6023+A1 x10 | L2: =IF($O2="","",$O2-TODAY()) -> 89 | M2: =IF(AND(TRIM($A2)="Finalized",$K2<>""),"",IF($D2="","",$D2+365-TODAY())) -> 306 | N2: =IF(AND(TRIM($A2)="Finalized",$K2<>""),"",IF($D2="","",$D2+120-TODAY())) -> 61 | O2: =IF(AND(TRIM($A2)="Finalized",$K2<>""),"",DATE(2027,1,13)) -> 46400 | P2: 365 days | Q2: MEDICARE | R2: 365 days | S2: Processed date | T2: 120 days | U2: Processed date | V2: 2026-01 January | W2: DME | X2: A1 | AA2: 10 | AB2: =IF($F2="","",TODAY()-$F2) -> 276 | AC2: A6023 | AJ2: G894 | AK2: M48062 | AN2: 552888745 | AO2: Advanced Spine and Pain LLC DME SUR | AP2: Advanced Spine and Pain LLC DME - Surprise Reems | AQ2: 46036 | BF2: =IF(TRIM($A2)="Finalized","Closed",IF($BD2="","No review date set",IF($BD2<TODAY(),"OVERDUE",IF($BD2-TODAY()<=7,"Due within 7 days","Scheduled")))) -> No review date set | BG2: =IF($K2="","",TODAY()-$K2) | BH2: =IFERROR(LEFT(IF($B2="","Notes, ","")&IF($K2="","Latest Date Worked, ","")&IF($AY2="","Last Action, ","")&IF(AND(OR(TRIM($A2)="Denied",TRIM($A2)="Rejected"),$BA2=""),"Denial Reason, ","")&IF(AND(TRIM($A2)="Denied",$BB2="",TRIM($BA2)<>"NO DENIAL"),"Denial Code, ","")&IF(AND(TRIM($A2)<>"Finalized",$BD2=""),"Next Review Date, ","")&IF(AND(TRIM($A2)<>"Finalized",$BE2=""),"Next Step, ","")&IF(AND(TRIM($A2)="Finalized",$AV2="",$AR2="",$AT2="",$AX2="",$AW2=""),"CPT outcome, ",""),LEN(IF($B2="","Notes, ","")&IF($K2="","Latest Date Worked, ","")&IF($AY2="","Last Action, ","")&IF(AND(OR(TRIM($A2)="Denied",TRIM($A2)="Rejected"),$BA2=""),"Denial Reason, ","")&IF(AND(TRIM($A2)="Denied",$BB2="",TRIM($BA2)<>"NO DENIAL"),"Denial Code, ","")&IF(AND(TRIM($A2)<>"Finalized",$BD2=""),"Next Review Date, ","")&IF(AND(TRIM($A2)<>"Finalized",$BE2=""),"Next Step, ","")&IF(AND(TRIM($A2)="Finalized",$AV2="",$AR2="",$AT2="",$AX2="",$AW2=""),"CPT outcome, ",""))-2),"") -> Latest Date Worked, Last Action, Next Review Date, Next Step | BI2: =IF($BB2="","",IFERROR(INDEX('Denial Codes'!$C:$C,MATCH(LEFT($BB2,FIND(" - ",$BB2&" - ")+2)&"*",'Denial Codes'!$A:$A,0)),"")) | BJ2: =IF($BA2="","",IFERROR(INDEX(Lists!$B:$B,MATCH(TRIM($BA2),Lists!$A:$A,0))&"",""))
A3: Under Review | C3: 569224437 | E3: HF450934372 | F3: 46044 | G3: Gold Kidney Health Plan | H3: Gold Kidney Health Plan | I3: No Payer | J3: 22845+58+59 x1; 22853+58+59 x1; 22853+58 x1; 22845+58+59 x1 | L3: =IF($O3="","",$O3-TODAY()) | Q3: Not on reference list | V3: 2026-01 January | W3: ORTHO | X3: 58 | Y3: 59 | AA3: 4 | AB3: =IF($F3="","",TODAY()-$F3) -> 267 | AC3: 22845 | AD3: 22853 | AE3: 22853 | AF3: 22845 | AJ3: M4316 | AK3: M5416 | AO3: MAYURAN, VIKRAM | AP3: Banner Desert Medical Center | AQ3: 46254 | BE3: Check Gold Kidney portal once the account is reactivated | BF3: =IF(TRIM($A3)="Finalized","Closed",IF($BD3="","No review date set",IF($BD3<TODAY(),"OVERDUE",IF($BD3-TODAY()<=7,"Due within 7 days","Scheduled")))) -> No review date set | BG3: =IF($K3="","",TODAY()-$K3) | BH3: =IFERROR(LEFT(IF($B3="","Notes, ","")&IF($K3="","Latest Date Worked, ","")&IF($AY3="","Last Action, ","")&IF(AND(OR(TRIM($A3)="Denied",TRIM($A3)="Rejected"),$BA3=""),"Denial Reason, ","")&IF(AND(TRIM($A3)="Denied",$BB3="",TRIM($BA3)<>"NO DENIAL"),"Denial Code, ","")&IF(AND(TRIM($A3)<>"Finalized",$BD3=""),"Next Review Date, ","")&IF(AND(TRIM($A3)<>"Finalized",$BE3=""),"Next Step, ","")&IF(AND(TRIM($A3)="Finalized",$AV3="",$AR3="",$AT3="",$AX3="",$AW3=""),"CPT outcome, ",""),LEN(IF($B3="","Notes, ","")&IF($K3="","Latest Date Worked, ","")&IF($AY3="","Last Action, ","")&IF(AND(OR(TRIM($A3)="Denied",TRIM($A3)="Rejected"),$BA3=""),"Denial Reason, ","")&IF(AND(TRIM($A3)="Denied",$BB3="",TRIM($BA3)<>"NO DENIAL"),"Denial Code, ","")&IF(AND(TRIM($A3)<>"Finalized",$BD3=""),"Next Review Date, ","")&IF(AND(TRIM($A3)<>"Finalized",$BE3=""),"Next Step, ","")&IF(AND(TRIM($A3)="Finalized",$AV3="",$AR3="",$AT3="",$AX3="",$AW3=""),"CPT outcome, ",""))-2),"") -> Notes, Latest Date Worked, Last Action, Next Review Date | BI3: =IF($BB3="","",IFERROR(INDEX('Denial Codes'!$C:$C,MATCH(LEFT($BB3,FIND(" - ",$BB3&" - ")+2)&"*",'Denial Codes'!$A:$A,0)),"")) | BJ3: =IF($BA3="","",IFERROR(INDEX(Lists!$B:$B,MATCH(TRIM($BA3),Lists!$A:$A,0))&"",""))
A4: Denied | B4: Added anatomical modifiers, and resubmitted | C4: 555920273 | D4: 46247 | E4: HF548529635 | F4: 46079 | G4: Mercy Care Plan (AHCCCS) - Complete Care & Long Term Care (LTC) | H4: Mercy Care Plan (AHCCCS) - Complete Care & Long Term Care (LTC) | I4: No Payer | J4: L3916+NU x1; L3916+NU x1 | K4: 46310 | L4: =IF($O4="","",$O4-TODAY()) -> -52 | M4: =IF(AND(TRIM($A4)="Finalized",$K4<>""),"",IF($F4="","",$F4+365-TODAY())) -> 133 | N4: =IF(AND(TRIM($A4)="Finalized",$K4<>""),"",IF($F4="","",$F4+365-TODAY())) -> 133 | O4: =IF(AND(TRIM($A4)="Finalized",$K4<>""),"",DATE(2026,8,25)) -> 46259 | P4: 180 days | Q4: MERCY CARE MEDICAID | R4: 365 days | S4: Date of service | T4: 365 days | U4: Date of service | V4: 2026-02 February | W4: DME | X4: NU | AA4: 2 | AB4: =IF($F4="","",TODAY()-$F4) -> 232 | AC4: L3916 | AD4: L3916 | AJ4: M19031, M19032 | AO4: Arshad, Jawad | AP4: ASAP - Mesa | AQ4: 46084 | AV4: L3916+RT | AX4: L3916+LT | AY4: Resubmitted | AZ4: Resubmitted | BA4: Modifier issue | BB4: CO_18 - Exact duplicate claim/service | BF4: =IF(TRIM($A4)="Finalized","Closed",IF($BD4="","No review date set",IF($BD4<TODAY(),"OVERDUE",IF($BD4-TODAY()<=7,"Due within 7 days","Scheduled")))) -> No review date set | BG4: =IF($K4="","",TODAY()-$K4) -> 1 | BH4: =IFERROR(LEFT(IF($B4="","Notes, ","")&IF($K4="","Latest Date Worked, ","")&IF($AY4="","Last Action, ","")&IF(AND(OR(TRIM($A4)="Denied",TRIM($A4)="Rejected"),$BA4=""),"Denial Reason, ","")&IF(AND(TRIM($A4)="Denied",$BB4="",TRIM($BA4)<>"NO DENIAL"),"Denial Code, ","")&IF(AND(TRIM($A4)<>"Finalized",$BD4=""),"Next Review Date, ","")&IF(AND(TRIM($A4)<>"Finalized",$BE4=""),"Next Step, ","")&IF(AND(TRIM($A4)="Finalized",$AV4="",$AR4="",$AT4="",$AX4="",$AW4=""),"CPT outcome, ",""),LEN(IF($B4="","Notes, ","")&IF($K4="","Latest Date Worked, ","")&IF($AY4="","Last Action, ","")&IF(AND(OR(TRIM($A4)="Denied",TRIM($A4)="Rejected"),$BA4=""),"Denial Reason, ","")&IF(AND(TRIM($A4)="Denied",$BB4="",TRIM($BA4)<>"NO DENIAL"),"Denial Code, ","")&IF(AND(TRIM($A4)<>"Finalized",$BD4=""),"Next Review Date, ","")&IF(AND(TRIM($A4)<>"Finalized",$BE4=""),"Next Step, ","")&IF(AND(TRIM($A4)="Finalized",$AV4="",$AR4="",$AT4="",$AX4="",$AW4=""),"CPT outcome, ",""))-2),"") -> Next Review Date, Next Step | BI4: =IF($BB4="","",IFERROR(INDEX('Denial Codes'!$C:$C,MATCH(LEFT($BB4,FIND(" - ",$BB4&" - ")+2)&"*",'Denial Codes'!$A:$A,0)),"")) -> Duplicate claim | BJ4: =IF($BA4="","",IFERROR(INDEX(Lists!$B:$B,MATCH(TRIM($BA4),Lists!$A:$A,0))&"","")) -> Correct or add the modifier (e.g. NU/RR, KX, RT/LT, 25) and resubmit.
A5: Rejected | B5: Provider TAX ID/NPI Combination is not on file with BCBS AZ | C5: 552282138 | E5: HF527802572 | F5: 46085 | G5: Blue Cross Blue Shield of Arizona (BCBS AZ) | H5: Blue Cross Blue Shield of Arizona (BCBS AZ) | I5: No Payer | J5: 63045 x1; 63048 x1 | K5: 46310 | L5: =IF($O5="","",$O5-TODAY()) -> -136 | M5: =IF(AND(TRIM($A5)="Finalized",$K5<>""),"",IF($F5="","",$F5+90-TODAY())) -> -136 | N5: =IF(AND(TRIM($A5)="Finalized",$K5<>""),"",IF($D5="","",$D5+365-TODAY())) | O5: =IF(AND(TRIM($A5)="Finalized",$K5<>""),"",DATE(2026,6,2)) -> 46175 | P5: 90 days | Q5: BCBS | R5: 90 days | S5: Date of service | T5: 365 days | U5: Processed date | V5: 2026-03 March | W5: ORTHO | AA5: 2 | AB5: =IF($F5="","",TODAY()-$F5) -> 226 | AC5: 63045 | AD5: 63048 | AJ5: M5412 | AK5: M5010 | AL5: M4722 | AM5: M960 | AO5: MCCUNNIFF, PETER | AP5: ASAP Surgery Centers North Valley LLC | AQ5: 46273 | AX5: 63045, 63048 | AY5: Resubmitted | BA5: Credentialing / out of network | BB5: N290 - Missing/incomplete/invalid rendering provider primary identifier | BD5: 46314 | BF5: =IF(TRIM($A5)="Finalized","Closed",IF($BD5="","No review date set",IF($BD5<TODAY(),"OVERDUE",IF($BD5-TODAY()<=7,"Due within 7 days","Scheduled")))) -> Due within 7 days | BG5: =IF($K5="","",TODAY()-$K5) -> 1 | BH5: =IFERROR(LEFT(IF($B5="","Notes, ","")&IF($K5="","Latest Date Worked, ","")&IF($AY5="","Last Action, ","")&IF(AND(OR(TRIM($A5)="Denied",TRIM($A5)="Rejected"),$BA5=""),"Denial Reason, ","")&IF(AND(TRIM($A5)="Denied",$BB5="",TRIM($BA5)<>"NO DENIAL"),"Denial Code, ","")&IF(AND(TRIM($A5)<>"Finalized",$BD5=""),"Next Review Date, ","")&IF(AND(TRIM($A5)<>"Finalized",$BE5=""),"Next Step, ","")&IF(AND(TRIM($A5)="Finalized",$AV5="",$AR5="",$AT5="",$AX5="",$AW5=""),"CPT outcome, ",""),LEN(IF($B5="","Notes, ","")&IF($K5="","Latest Date Worked, ","")&IF($AY5="","Last Action, ","")&IF(AND(OR(TRIM($A5)="Denied",TRIM($A5)="Rejected"),$BA5=""),"Denial Reason, ","")&IF(AND(TRIM($A5)="Denied",$BB5="",TRIM($BA5)<>"NO DENIAL"),"Denial Code, ","")&IF(AND(TRIM($A5)<>"Finalized",$BD5=""),"Next Review Date, ","")&IF(AND(TRIM($A5)<>"Finalized",$BE5=""),"Next Step, ","")&IF(AND(TRIM($A5)="Finalized",$AV5="",$AR5="",$AT5="",$AX5="",$AW5=""),"CPT outcome, ",""))-2),"") -> Next Step | BI5: =IF($BB5="","",IFERROR(INDEX('Denial Codes'!$C:$C,MATCH(LEFT($BB5,FIND(" - ",$BB5&" - ")+2)&"*",'Denial Codes'!$A:$A,0)),"")) -> Credentialing / out of network | BJ5: =IF($BA5="","",IFERROR(INDEX(Lists!$B:$B,MATCH(TRIM($BA5),Lists!$A:$A,0))&"","")) -> Check provider enrollment, NPI/TIN and network status; appeal once credentialing is confirmed.
A6: Denied | B6: Resubmitted to primary plan Arizona Ufcw Employers Health | C6: 552709009 | D6: 46261 | E6: HF507623401 | F6: 46093 | G6: United Healthcare | H6: United Healthcare | I6: No Payer | J6: 99494 x1; 99492 x1 | K6: 46310 | L6: =IF($O6="","",$O6-TODAY()) -> -128 | M6: =IF(AND(TRIM($A6)="Finalized",$K6<>""),"",IF($D6="","",$D6+180-TODAY())) -> 130 | N6: =IF(AND(TRIM($A6)="Finalized",$K6<>""),"",IF($D6="","",$D6+365-TODAY())) -> 315 | O6: =IF(AND(TRIM($A6)="Finalized",$K6<>""),"",DATE(2026,6,10)) -> 46183 | P6: 90 days | Q6: UHC COMMERCIAL | R6: 180 days | S6: Processed date | T6: 365 days | U6: Processed date | V6: 2026-03 March | W6: BH | AA6: 2 | AB6: =IF($F6="","",TODAY()-$F6) -> 218 | AC6: 99494 | AD6: 99492 | AJ6: F1190 | AO6: MORALES, DAVID | AP6: ASAP - DEER VALLEY | AQ6: 46119 | AX6: 99492, 99494 | AY6: Resubmitted | BA6: Other insurance / COB | BB6: OA_22 - This care may be covered by another payer per coordination of benefits | BD6: 46341 | BF6: =IF(TRIM($A6)="Finalized","Closed",IF($BD6="","No review date set",IF($BD6<TODAY(),"OVERDUE",IF($BD6-TODAY()<=7,"Due within 7 days","Scheduled")))) -> Scheduled | BG6: =IF($K6="","",TODAY()-$K6) -> 1 | BH6: =IFERROR(LEFT(IF($B6="","Notes, ","")&IF($K6="","Latest Date Worked, ","")&IF($AY6="","Last Action, ","")&IF(AND(OR(TRIM($A6)="Denied",TRIM($A6)="Rejected"),$BA6=""),"Denial Reason, ","")&IF(AND(TRIM($A6)="Denied",$BB6="",TRIM($BA6)<>"NO DENIAL"),"Denial Code, ","")&IF(AND(TRIM($A6)<>"Finalized",$BD6=""),"Next Review Date, ","")&IF(AND(TRIM($A6)<>"Finalized",$BE6=""),"Next Step, ","")&IF(AND(TRIM($A6)="Finalized",$AV6="",$AR6="",$AT6="",$AX6="",$AW6=""),"CPT outcome, ",""),LEN(IF($B6="","Notes, ","")&IF($K6="","Latest Date Worked, ","")&IF($AY6="","Last Action, ","")&IF(AND(OR(TRIM($A6)="Denied",TRIM($A6)="Rejected"),$BA6=""),"Denial Reason, ","")&IF(AND(TRIM($A6)="Denied",$BB6="",TRIM($BA6)<>"NO DENIAL"),"Denial Code, ","")&IF(AND(TRIM($A6)<>"Finalized",$BD6=""),"Next Review Date, ","")&IF(AND(TRIM($A6)<>"Finalized",$BE6=""),"Next Step, ","")&IF(AND(TRIM($A6)="Finalized",$AV6="",$AR6="",$AT6="",$AX6="",$AW6=""),"CPT outcome, ",""))-2),"") -> Next Step | BI6: =IF($BB6="","",IFERROR(INDEX('Denial Codes'!$C:$C,MATCH(LEFT($BB6,FIND(" - ",$BB6&" - ")+2)&"*",'Denial Codes'!$A:$A,0)),"")) -> Other insurance / COB | BJ6: =IF($BA6="","",IFERROR(INDEX(Lists!$B:$B,MATCH(TRIM($BA6),Lists!$A:$A,0))&"","")) -> Get the other insurance and primary EOB, update COB with the payer and bill primary first.
A7: Denied | B7: Uploaded MR - Transaction Submission Confirmation Case ID# 18151 | C7: 568271516 | D7: 46261 | E7: HF532203609 | F7: 46105 | G7: UMR Wausau / UHIS | H7: UMR Wausau / UHIS | I7: No Payer | J7: 93970 x1 | K7: 46310 | L7: =IF($O7="","",$O7-TODAY()) | N7: =IF(AND(TRIM($A7)="Finalized",$K7<>""),"",IF($D7="","",$D7+180-TODAY())) -> 130 | Q7: UMR / WAUSAU | T7: 180 days | U7: Processed date | V7: 2026-03 March | W7: US | AA7: 1 | AB7: =IF($F7="","",TODAY()-$F7) -> 206 | AC7: 93970 | AJ7: I10 | AK7: R2243 | AO7: LEATHEM, JARRETT | AP7: ASAP - Gilbert | AQ7: 46245 | AX7: 93970 | AY7: Uploaded MR | BA7: Medical records needed | BB7: CO_252 - An attachment/other documentation is required to adjudicate this claim/service | BC7: Case ID# 18151 | BD7: 46341 | BF7: =IF(TRIM($A7)="Finalized","Closed",IF($BD7="","No review date set",IF($BD7<TODAY(),"OVERDUE",IF($BD7-TODAY()<=7,"Due within 7 days","Scheduled")))) -> Scheduled | BG7: =IF($K7="","",TODAY()-$K7) -> 1 | BH7: =IFERROR(LEFT(IF($B7="","Notes, ","")&IF($K7="","Latest Date Worked, ","")&IF($AY7="","Last Action, ","")&IF(AND(OR(TRIM($A7)="Denied",TRIM($A7)="Rejected"),$BA7=""),"Denial Reason, ","")&IF(AND(TRIM($A7)="Denied",$BB7="",TRIM($BA7)<>"NO DENIAL"),"Denial Code, ","")&IF(AND(TRIM($A7)<>"Finalized",$BD7=""),"Next Review Date, ","")&IF(AND(TRIM($A7)<>"Finalized",$BE7=""),"Next Step, ","")&IF(AND(TRIM($A7)="Finalized",$AV7="",$AR7="",$AT7="",$AX7="",$AW7=""),"CPT outcome, ",""),LEN(IF($B7="","Notes, ","")&IF($K7="","Latest Date Worked, ","")&IF($AY7="","Last Action, ","")&IF(AND(OR(TRIM($A7)="Denied",TRIM($A7)="Rejected"),$BA7=""),"Denial Reason, ","")&IF(AND(TRIM($A7)="Denied",$BB7="",TRIM($BA7)<>"NO DENIAL"),"Denial Code, ","")&IF(AND(TRIM($A7)<>"Finalized",$BD7=""),"Next Review Date, ","")&IF(AND(TRIM($A7)<>"Finalized",$BE7=""),"Next Step, ","")&IF(AND(TRIM($A7)="Finalized",$AV7="",$AR7="",$AT7="",$AX7="",$AW7=""),"CPT outcome, ",""))-2),"") -> Next Step | BI7: =IF($BB7="","",IFERROR(INDEX('Denial Codes'!$C:$C,MATCH(LEFT($BB7,FIND(" - ",$BB7&" - ")+2)&"*",'Denial Codes'!$A:$A,0)),"")) -> Medical records needed | BJ7: =IF($BA7="","",IFERROR(INDEX(Lists!$B:$B,MATCH(TRIM($BA7),Lists!$A:$A,0))&"","")) -> Upload the MR on the payer portal, note the PIQ/reference number and set a review date.
A8: Denied | B8: Added mod 24, and resubmitted - DND Proc 99493 is included in the global period of HxProc 64635 on Claim ID RC2772466500 Line ID 1 on date of service 03/24/2026. | C8: 554160244 | D8: 46266 | E8: HF523425107 | F8: 46106 | G8: UnitedHealthcare Community Plan / Arizona Long Term Care | H8: UnitedHealthcare Community Plan / Arizona Long Term Care | I8: No Payer | J8: 99494 x1; 99493 x1 | K8: 46310 | L8: =IF($O8="","",$O8-TODAY()) -> -115 | M8: =IF(AND(TRIM($A8)="Finalized",$K8<>""),"",IF($D8="","",$D8+180-TODAY())) -> 135 | N8: =IF(AND(TRIM($A8)="Finalized",$K8<>""),"",IF($D8="","",$D8+365-TODAY())) -> 320 | O8: =IF(AND(TRIM($A8)="Finalized",$K8<>""),"",DATE(2026,6,23)) -> 46196 | P8: 90 days | Q8: UHC COMMUNITY | R8: 180 days | S8: Processed date | T8: 365 days | U8: Processed date | V8: 2026-03 March | W8: BH | AA8: 2 | AB8: =IF($F8="","",TODAY()-$F8) -> 205 | AC8: 99494 | AD8: 99493 | AJ8: F4323 | AO8: TURLEY, TODD | AP8: ASAP - DEER VALLEY | AQ8: 46119 | AX8: 99493, 99494 | AY8: Resubmitted | BA8: Bundled / NCCI edit | BB8: CO_97 - The benefit for this service is included in the payment/allowance for another service/procedure already adjudicated | BD8: 46341 | BF8: =IF(TRIM($A8)="Finalized","Closed",IF($BD8="","No review date set",IF($BD8<TODAY(),"OVERDUE",IF($BD8-TODAY()<=7,"Due within 7 days","Scheduled")))) -> Scheduled | BG8: =IF($K8="","",TODAY()-$K8) -> 1 | BH8: =IFERROR(LEFT(IF($B8="","Notes, ","")&IF($K8="","Latest Date Worked, ","")&IF($AY8="","Last Action, ","")&IF(AND(OR(TRIM($A8)="Denied",TRIM($A8)="Rejected"),$BA8=""),"Denial Reason, ","")&IF(AND(TRIM($A8)="Denied",$BB8="",TRIM($BA8)<>"NO DENIAL"),"Denial Code, ","")&IF(AND(TRIM($A8)<>"Finalized",$BD8=""),"Next Review Date, ","")&IF(AND(TRIM($A8)<>"Finalized",$BE8=""),"Next Step, ","")&IF(AND(TRIM($A8)="Finalized",$AV8="",$AR8="",$AT8="",$AX8="",$AW8=""),"CPT outcome, ",""),LEN(IF($B8="","Notes, ","")&IF($K8="","Latest Date Worked, ","")&IF($AY8="","Last Action, ","")&IF(AND(OR(TRIM($A8)="Denied",TRIM($A8)="Rejected"),$BA8=""),"Denial Reason, ","")&IF(AND(TRIM($A8)="Denied",$BB8="",TRIM($BA8)<>"NO DENIAL"),"Denial Code, ","")&IF(AND(TRIM($A8)<>"Finalized",$BD8=""),"Next Review Date, ","")&IF(AND(TRIM($A8)<>"Finalized",$BE8=""),"Next Step, ","")&IF(AND(TRIM($A8)="Finalized",$AV8="",$AR8="",$AT8="",$AX8="",$AW8=""),"CPT outcome, ",""))-2),"") -> Next Step | BI8: =IF($BB8="","",IFERROR(INDEX('Denial Codes'!$C:$C,MATCH(LEFT($BB8,FIND(" - ",$BB8&" - ")+2)&"*",'Denial Codes'!$A:$A,0)),"")) -> Bundled / NCCI edit | BJ8: =IF($BA8="","",IFERROR(INDEX(Lists!$B:$B,MATCH(TRIM($BA8),Lists!$A:$A,0))&"","")) -> Check the NCCI pair; if the service was distinct, add 59/XU (or XS) and resubmit; otherwise adjust.
A9: Under Review | B9: I need to ask Juan for MR | C9: 568316185 | D9: 46254 | E9: HF452729341 | F9: 46114 | G9: HealthSpring Medicare Advantage | H9: HealthSpring Medicare Advantage | I9: No Payer | J9: 93925 x1 | L9: =IF($O9="","",$O9-TODAY()) -> -107 | M9: =IF(AND(TRIM($A9)="Finalized",$K9<>""),"",IF($F9="","",$F9+90-TODAY())) -> -107 | N9: =IF(AND(TRIM($A9)="Finalized",$K9<>""),"",IF($D9="","",$D9+180-TODAY())) -> 123 | O9: =IF(AND(TRIM($A9)="Finalized",$K9<>""),"",DATE(2026,7,1)) -> 46204 | P9: 90 days | Q9: CIGNA / CIGNA MEDICARE | R9: 90 days | S9: Date of service | T9: 180 days | U9: Processed date | V9: 2026-04 April | W9: US | AA9: 1 | AB9: =IF($F9="","",TODAY()-$F9) -> 197 | AC9: 93925 | AJ9: I70213 | AO9: TURLEY, TODD | AP9: ASAP - DEER VALLEY 240 | AQ9: 46245 | AX9: 93925 | BA9: Duplicate claim | BB9: CO_18 - Exact duplicate claim/service | BE9: I need to ask Juan for MR | BF9: =IF(TRIM($A9)="Finalized","Closed",IF($BD9="","No review date set",IF($BD9<TODAY(),"OVERDUE",IF($BD9-TODAY()<=7,"Due within 7 days","Scheduled")))) -> No review date set | BG9: =IF($K9="","",TODAY()-$K9) | BH9: =IFERROR(LEFT(IF($B9="","Notes, ","")&IF($K9="","Latest Date Worked, ","")&IF($AY9="","Last Action, ","")&IF(AND(OR(TRIM($A9)="Denied",TRIM($A9)="Rejected"),$BA9=""),"Denial Reason, ","")&IF(AND(TRIM($A9)="Denied",$BB9="",TRIM($BA9)<>"NO DENIAL"),"Denial Code, ","")&IF(AND(TRIM($A9)<>"Finalized",$BD9=""),"Next Review Date, ","")&IF(AND(TRIM($A9)<>"Finalized",$BE9=""),"Next Step, ","")&IF(AND(TRIM($A9)="Finalized",$AV9="",$AR9="",$AT9="",$AX9="",$AW9=""),"CPT outcome, ",""),LEN(IF($B9="","Notes, ","")&IF($K9="","Latest Date Worked, ","")&IF($AY9="","Last Action, ","")&IF(AND(OR(TRIM($A9)="Denied",TRIM($A9)="Rejected"),$BA9=""),"Denial Reason, ","")&IF(AND(TRIM($A9)="Denied",$BB9="",TRIM($BA9)<>"NO DENIAL"),"Denial Code, ","")&IF(AND(TRIM($A9)<>"Finalized",$BD9=""),"Next Review Date, ","")&IF(AND(TRIM($A9)<>"Finalized",$BE9=""),"Next Step, ","")&IF(AND(TRIM($A9)="Finalized",$AV9="",$AR9="",$AT9="",$AX9="",$AW9=""),"CPT outcome, ",""))-2),"") -> Latest Date Worked, Last Action, Next Review Date | BI9: =IF($BB9="","",IFERROR(INDEX('Denial Codes'!$C:$C,MATCH(LEFT($BB9,FIND(" - ",$BB9&" - ")+2)&"*",'Denial Codes'!$A:$A,0)),"")) -> Duplicate claim | BJ9: =IF($BA9="","",IFERROR(INDEX(Lists!$B:$B,MATCH(TRIM($BA9),Lists!$A:$A,0))&"","")) -> Check the status of the original claim; no resubmission needed if it was processed.
A10: Denied | B10: Waiting on full recoup to bill PT - ABN signed - Bundling with HHA episode on DOS - HOME HEALTH SCOTTSDALE, LLC NPI 1154898542 | C10: 556764523 | D10: 46231 | E10: HF541770771 | F10: 46121 | G10: Tricare for Life (All Regions) | H10: DME Region D | I10: Tricare for Life (All Regions) | J10: A6023+A2 x20 | K10: 46310 | L10: =IF($O10="","",$O10-TODAY()) -> 175 | M10: =IF(AND(TRIM($A10)="Finalized",$K10<>""),"",IF($D10="","",$D10+365-TODAY())) -> 285 | N10: =IF(AND(TRIM($A10)="Finalized",$K10<>""),"",IF($D10="","",$D10+120-TODAY())) -> 40 | O10: =IF(AND(TRIM($A10)="Finalized",$K10<>""),"",DATE(2027,4,9)) -> 46486 | P10: 365 days | Q10: MEDICARE | R10: 365 days | S10: Processed date | T10: 120 days | U10: Processed date | V10: 2026-04 April | W10: DME | X10: A2 | AA10: 20 | AB10: =IF($F10="","",TODAY()-$F10) -> 190 | AC10: A6023 | AJ10: G894 | AN10: 559829888 | AO10: Advanced Spine and Pain LLC DME PEO | AP10: Advanced Spine and Pain LLC DME - Peoria | AQ10: 46133 | AX10: A6023 | AY10: Waiting on payer | BA10: Bundled / NCCI edit | BB10: N88 Alert: This payment is being made conditionally. An HHA episode of care notice has been filed for this patient. When a patient is treated under a HHA episode of care, consolidated billing requires that certain therapy services and supplies, such as this, be included in the HHA's payment. This payment will need to be recouped from you if we establish that the patient is concurrently receiving treatment under a HHA episode of care. | BD10: 46341 | BE10: Waiting on full recoup to bill PT | BF10: =IF(TRIM($A10)="Finalized","Closed",IF($BD10="","No review date set",IF($BD10<TODAY(),"OVERDUE",IF($BD10-TODAY()<=7,"Due within 7 days","Scheduled")))) -> Scheduled | BG10: =IF($K10="","",TODAY()-$K10) -> 1 | BH10: =IFERROR(LEFT(IF($B10="","Notes, ","")&IF($K10="","Latest Date Worked, ","")&IF($AY10="","Last Action, ","")&IF(AND(OR(TRIM($A10)="Denied",TRIM($A10)="Rejected"),$BA10=""),"Denial Reason, ","")&IF(AND(TRIM($A10)="Denied",$BB10="",TRIM($BA10)<>"NO DENIAL"),"Denial Code, ","")&IF(AND(TRIM($A10)<>"Finalized",$BD10=""),"Next Review Date, ","")&IF(AND(TRIM($A10)<>"Finalized",$BE10=""),"Next Step, ","")&IF(AND(TRIM($A10)="Finalized",$AV10="",$AR10="",$AT10="",$AX10="",$AW10=""),"CPT outcome, ",""),LEN(IF($B10="","Notes, ","")&IF($K10="","Latest Date Worked, ","")&IF($AY10="","Last Action, ","")&IF(AND(OR(TRIM($A10)="Denied",TRIM($A10)="Rejected"),$BA10=""),"Denial Reason, ","")&IF(AND(TRIM($A10)="Denied",$BB10="",TRIM($BA10)<>"NO DENIAL"),"Denial Code, ","")&IF(AND(TRIM($A10)<>"Finalized",$BD10=""),"Next Review Date, ","")&IF(AND(TRIM($A10)<>"Finalized",$BE10=""),"Next Step, ","")&IF(AND(TRIM($A10)="Finalized",$AV10="",$AR10="",$AT10="",$AX10="",$AW10=""),"CPT outcome, ",""))-2),"") | BI10: =IF($BB10="","",IFERROR(INDEX('Denial Codes'!$C:$C,MATCH(LEFT($BB10,FIND(" - ",$BB10&" - ")+2)&"*",'Denial Codes'!$A:$A,0)),"")) | BJ10: =IF($BA10="","",IFERROR(INDEX(Lists!$B:$B,MATCH(TRIM($BA10),Lists!$A:$A,0))&"","")) -> Check the NCCI pair; if the service was distinct, add 59/XU (or XS) and resubmit; otherwise adjust.
A11: Denied | B11: Uploaded MR - Transaction Submission Confirmation Case ID# 18149 | C11: 568312031 | D11: 46266 | E11: HF460572363 | F11: 46126 | G11: UMR Wausau / UHIS | H11: UMR Wausau / UHIS | I11: No Payer | J11: 93970 x1 | K11: 46310 | L11: =IF($O11="","",$O11-TODAY()) | N11: =IF(AND(TRIM($A11)="Finalized",$K11<>""),"",IF($D11="","",$D11+180-TODAY())) -> 135 | Q11: UMR / WAUSAU | T11: 180 days | U11: Processed date | V11: 2026-04 April | W11: US | AA11: 1 | AB11: =IF($F11="","",TODAY()-$F11) -> 185 | AC11: 93970 | AJ11: E1142 | AK11: E7849 | AL11: I10 | AO11: LEATHEM, JARRETT | AP11: ASAP - Gilbert | AQ11: 46245 | AX11: 93970 | AY11: Uploaded MR | BA11: Medical records needed | BB11: CO_252 - An attachment/other documentation is required to adjudicate this claim/service | BC11: Case ID# 18149 | BD11: 46341 | BF11: =IF(TRIM($A11)="Finalized","Closed",IF($BD11="","No review date set",IF($BD11<TODAY(),"OVERDUE",IF($BD11-TODAY()<=7,"Due within 7 days","Scheduled")))) -> Scheduled | BG11: =IF($K11="","",TODAY()-$K11) -> 1 | BH11: =IFERROR(LEFT(IF($B11="","Notes, ","")&IF($K11="","Latest Date Worked, ","")&IF($AY11="","Last Action, ","")&IF(AND(OR(TRIM($A11)="Denied",TRIM($A11)="Rejected"),$BA11=""),"Denial Reason, ","")&IF(AND(TRIM($A11)="Denied",$BB11="",TRIM($BA11)<>"NO DENIAL"),"Denial Code, ","")&IF(AND(TRIM($A11)<>"Finalized",$BD11=""),"Next Review Date, ","")&IF(AND(TRIM($A11)<>"Finalized",$BE11=""),"Next Step, ","")&IF(AND(TRIM($A11)="Finalized",$AV11="",$AR11="",$AT11="",$AX11="",$AW11=""),"CPT outcome, ",""),LEN(IF($B11="","Notes, ","")&IF($K11="","Latest Date Worked, ","")&IF($AY11="","Last Action, ","")&IF(AND(OR(TRIM($A11)="Denied",TRIM($A11)="Rejected"),$BA11=""),"Denial Reason, ","")&IF(AND(TRIM($A11)="Denied",$BB11="",TRIM($BA11)<>"NO DENIAL"),"Denial Code, ","")&IF(AND(TRIM($A11)<>"Finalized",$BD11=""),"Next Review Date, ","")&IF(AND(TRIM($A11)<>"Finalized",$BE11=""),"Next Step, ","")&IF(AND(TRIM($A11)="Finalized",$AV11="",$AR11="",$AT11="",$AX11="",$AW11=""),"CPT outcome, ",""))-2),"") -> Next Step | BI11: =IF($BB11="","",IFERROR(INDEX('Denial Codes'!$C:$C,MATCH(LEFT($BB11,FIND(" - ",$BB11&" - ")+2)&"*",'Denial Codes'!$A:$A,0)),"")) -> Medical records needed | BJ11: =IF($BA11="","",IFERROR(INDEX(Lists!$B:$B,MATCH(TRIM($BA11),Lists!$A:$A,0))&"","")) -> Upload the MR on the payer portal, note the PIQ/reference number and set a review date.
A12: Denied | B12: Uploaded MR on portal | C12: 556730319 | D12: 46279 | E12: HF530285792 | F12: 46127 | G12: Tricare West | H12: Tricare West | I12: No Payer | J12: 63047 x1 | K12: 46311 | L12: =IF($O12="","",$O12-TODAY()) -> 181 | M12: =IF(AND(TRIM($A12)="Finalized",$K12<>""),"",IF($F12="","",$F12+365-TODAY())) -> 181 | N12: =IF(AND(TRIM($A12)="Finalized",$K12<>""),"",IF($D12="","",$D12+90-TODAY())) -> 58 | O12: =IF(AND(TRIM($A12)="Finalized",$K12<>""),"",DATE(2027,4,15)) -> 46492 | P12: 365 days | Q12: TRICARE WEST | R12: 365 days | S12: Date of service | T12: 90 days | U12: Processed date | V12: 2026-04 April | W12: ORTHO | AA12: 1 | AB12: =IF($F12="","",TODAY()-$F12) -> 184 | AC12: 63047 | AJ12: M5416 | AK12: M5450 | AO12: MCCUNNIFF, PETER | AP12: ASAP Surgery Centers North Valley LLC | AQ12: 46246 | AV12: 63048 | AX12: 63047 | AY12: Uploaded MR | BA12: Medical records needed | BB12: CO_252 - An attachment/other documentation is required to adjudicate this claim/service | BD12: 46311 | BF12: =IF(TRIM($A12)="Finalized","Closed",IF($BD12="","No review date set",IF($BD12<TODAY(),"OVERDUE",IF($BD12-TODAY()<=7,"Due within 7 days","Scheduled")))) -> Due within 7 days | BG12: =IF($K12="","",TODAY()-$K12) -> 0 | BH12: =IFERROR(LEFT(IF($B12="","Notes, ","")&IF($K12="","Latest Date Worked, ","")&IF($AY12="","Last Action, ","")&IF(AND(OR(TRIM($A12)="Denied",TRIM($A12)="Rejected"),$BA12=""),"Denial Reason, ","")&IF(AND(TRIM($A12)="Denied",$BB12="",TRIM($BA12)<>"NO DENIAL"),"Denial Code, ","")&IF(AND(TRIM($A12)<>"Finalized",$BD12=""),"Next Review Date, ","")&IF(AND(TRIM($A12)<>"Finalized",$BE12=""),"Next Step, ","")&IF(AND(TRIM($A12)="Finalized",$AV12="",$AR12="",$AT12="",$AX12="",$AW12=""),"CPT outcome, ",""),LEN(IF($B12="","Notes, ","")&IF($K12="","Latest Date Worked, ","")&IF($AY12="","Last Action, ","")&IF(AND(OR(TRIM($A12)="Denied",TRIM($A12)="Rejected"),$BA12=""),"Denial Reason, ","")&IF(AND(TRIM($A12)="Denied",$BB12="",TRIM($BA12)<>"NO DENIAL"),"Denial Code, ","")&IF(AND(TRIM($A12)<>"Finalized",$BD12=""),"Next Review Date, ","")&IF(AND(TRIM($A12)<>"Finalized",$BE12=""),"Next Step, ","")&IF(AND(TRIM($A12)="Finalized",$AV12="",$AR12="",$AT12="",$AX12="",$AW12=""),"CPT outcome, ",""))-2),"") -> Next Step | BI12: =IF($BB12="","",IFERROR(INDEX('Denial Codes'!$C:$C,MATCH(LEFT($BB12,FIND(" - ",$BB12&" - ")+2)&"*",'Denial Codes'!$A:$A,0)),"")) -> Medical records needed | BJ12: =IF($BA12="","",IFERROR(INDEX(Lists!$B:$B,MATCH(TRIM($BA12),Lists!$A:$A,0))&"","")) -> Upload the MR on the payer portal, note the PIQ/reference number and set a review date.
A13: Denied | B13: TFierro30 corrected claim and resubmitted - Filed reconsideration with MR - PIQ-89945925 | C13: 573339755 | D13: 46289 | E13: HF331720981 | F13: 46132 | G13: United Healthcare | H13: United Healthcare | I13: No Payer | J13: 63685 x1 | K13: 46295 | L13: =IF($O13="","",$O13-TODAY()) -> -89 | M13: =IF(AND(TRIM($A13)="Finalized",$K13<>""),"",IF($D13="","",$D13+180-TODAY())) -> 158 | N13: =IF(AND(TRIM($A13)="Finalized",$K13<>""),"",IF($D13="","",$D13+365-TODAY())) -> 343 | O13: =IF(AND(TRIM($A13)="Finalized",$K13<>""),"",DATE(2026,7,19)) -> 46222 | P13: 90 days | Q13: UHC COMMERCIAL | R13: 180 days | S13: Processed date | T13: 365 days | U13: Processed date | V13: 2026-04 April | W13: ORTHO | AA13: 1 | AB13: =IF($F13="","",TODAY()-$F13) -> 179 | AC13: 63685 | AJ13: T85122A | AK13: Z4542 | AL13: M961 | AO13: BURGHER, ABRAM | AP13: ASAP Surgery Centers North Valley LLC | AQ13: 46149 | AX13: 63663, 63685 | AY13: Resubmitted | AZ13: Uploaded MR | BA13: Medical records needed | BB13: CO_50 - Non-covered services because this is not deemed a 'medical necessity' by the payer | BF13: =IF(TRIM($A13)="Finalized","Closed",IF($BD13="","No review date set",IF($BD13<TODAY(),"OVERDUE",IF($BD13-TODAY()<=7,"Due within 7 days","Scheduled")))) -> No review date set | BG13: =IF($K13="","",TODAY()-$K13) -> 16 | BH13: =IFERROR(LEFT(IF($B13="","Notes, ","")&IF($K13="","Latest Date Worked, ","")&IF($AY13="","Last Action, ","")&IF(AND(OR(TRIM($A13)="Denied",TRIM($A13)="Rejected"),$BA13=""),"Denial Reason, ","")&IF(AND(TRIM($A13)="Denied",$BB13="",TRIM($BA13)<>"NO DENIAL"),"Denial Code, ","")&IF(AND(TRIM($A13)<>"Finalized",$BD13=""),"Next Review Date, ","")&IF(AND(TRIM($A13)<>"Finalized",$BE13=""),"Next Step, ","")&IF(AND(TRIM($A13)="Finalized",$AV13="",$AR13="",$AT13="",$AX13="",$AW13=""),"CPT outcome, ",""),LEN(IF($B13="","Notes, ","")&IF($K13="","Latest Date Worked, ","")&IF($AY13="","Last Action, ","")&IF(AND(OR(TRIM($A13)="Denied",TRIM($A13)="Rejected"),$BA13=""),"Denial Reason, ","")&IF(AND(TRIM($A13)="Denied",$BB13="",TRIM($BA13)<>"NO DENIAL"),"Denial Code, ","")&IF(AND(TRIM($A13)<>"Finalized",$BD13=""),"Next Review Date, ","")&IF(AND(TRIM($A13)<>"Finalized",$BE13=""),"Next Step, ","")&IF(AND(TRIM($A13)="Finalized",$AV13="",$AR13="",$AT13="",$AX13="",$AW13=""),"CPT outcome, ",""))-2),"") -> Next Review Date, Next Step | BI13: =IF($BB13="","",IFERROR(INDEX('Denial Codes'!$C:$C,MATCH(LEFT($BB13,FIND(" - ",$BB13&" - ")+2)&"*",'Denial Codes'!$A:$A,0)),"")) -> Medical necessity / frequency | BJ13: =IF($BA13="","",IFERROR(INDEX(Lists!$B:$B,MATCH(TRIM($BA13),Lists!$A:$A,0))&"","")) -> Upload the MR on the payer portal, note the PIQ/reference number and set a review date.
A14: Denied | B14: Resubmitted - RENEE OROC credentialing issue - Denied Remark MA130 Multiple submission/billing errors unable to adjudicate claim as submitted | C14: 557506616 | D14: 46258 | E14: HF508283049 | F14: 46136 | G14: Blue Cross Blue Shield of Arizona (BCBS AZ) | H14: Blue Cross Blue Shield of Arizona (BCBS AZ) | I14: Medicare Part B Arizona * | J14: A6023+A1 x20 | K14: 46310 | L14: =IF($O14="","",$O14-TODAY()) -> -85 | M14: =IF(AND(TRIM($A14)="Finalized",$K14<>""),"",IF($F14="","",$F14+90-TODAY())) -> -85 | N14: =IF(AND(TRIM($A14)="Finalized",$K14<>""),"",IF($D14="","",$D14+365-TODAY())) -> 312 | O14: =IF(AND(TRIM($A14)="Finalized",$K14<>""),"",DATE(2026,7,23)) -> 46226 | P14: 90 days | Q14: BCBS | R14: 90 days | S14: Date of service | T14: 365 days | U14: Processed date | V14: 2026-04 April | W14: DME | X14: A1 | AA14: 20 | AB14: =IF($F14="","",TODAY()-$F14) -> 175 | AC14: A6023 | AJ14: G894 | AK14: M48062 | AO14: OROC, RENEE | AP14: ASAP - Mesa | AQ14: 46254 | AX14: A6023 | AY14: Resubmitted | BA14: Credentialing / out of network | BB14: PR_96 - Non-covered charge(s) | BD14: 46341 | BF14: =IF(TRIM($A14)="Finalized","Closed",IF($BD14="","No review date set",IF($BD14<TODAY(),"OVERDUE",IF($BD14-TODAY()<=7,"Due within 7 days","Scheduled")))) -> Scheduled | BG14: =IF($K14="","",TODAY()-$K14) -> 1 | BH14: =IFERROR(LEFT(IF($B14="","Notes, ","")&IF($K14="","Latest Date Worked, ","")&IF($AY14="","Last Action, ","")&IF(AND(OR(TRIM($A14)="Denied",TRIM($A14)="Rejected"),$BA14=""),"Denial Reason, ","")&IF(AND(TRIM($A14)="Denied",$BB14="",TRIM($BA14)<>"NO DENIAL"),"Denial Code, ","")&IF(AND(TRIM($A14)<>"Finalized",$BD14=""),"Next Review Date, ","")&IF(AND(TRIM($A14)<>"Finalized",$BE14=""),"Next Step, ","")&IF(AND(TRIM($A14)="Finalized",$AV14="",$AR14="",$AT14="",$AX14="",$AW14=""),"CPT outcome, ",""),LEN(IF($B14="","Notes, ","")&IF($K14="","Latest Date Worked, ","")&IF($AY14="","Last Action, ","")&IF(AND(OR(TRIM($A14)="Denied",TRIM($A14)="Rejected"),$BA14=""),"Denial Reason, ","")&IF(AND(TRIM($A14)="Denied",$BB14="",TRIM($BA14)<>"NO DENIAL"),"Denial Code, ","")&IF(AND(TRIM($A14)<>"Finalized",$BD14=""),"Next Review Date, ","")&IF(AND(TRIM($A14)<>"Finalized",$BE14=""),"Next Step, ","")&IF(AND(TRIM($A14)="Finalized",$AV14="",$AR14="",$AT14="",$AX14="",$AW14=""),"CPT outcome, ",""))-2),"") -> Next Step | BI14: =IF($BB14="","",IFERROR(INDEX('Denial Codes'!$C:$C,MATCH(LEFT($BB14,FIND(" - ",$BB14&" - ")+2)&"*",'Denial Codes'!$A:$A,0)),"")) -> Not covered by plan | BJ14: =IF($BA14="","",IFERROR(INDEX(Lists!$B:$B,MATCH(TRIM($BA14),Lists!$A:$A,0))&"","")) -> Check provider enrollment, NPI/TIN and network status; appeal once credentialing is confirmed.
A15: Denied | B15: Edited referring provider, and resubmitted | C15: 568470154 | D15: 46253 | E15: HF474490292 | F15: 46148 | G15: Medicare Part B Arizona * | H15: Medicare Part B Arizona * | I15: Tricare for Life (All Regions) | J15: 93970 x1 | K15: 46310 | L15: =IF($O15="","",$O15-TODAY()) -> 202 | M15: =IF(AND(TRIM($A15)="Finalized",$K15<>""),"",IF($D15="","",$D15+365-TODAY())) -> 307 | N15: =IF(AND(TRIM($A15)="Finalized",$K15<>""),"",IF($D15="","",$D15+120-TODAY())) -> 62 | O15: =IF(AND(TRIM($A15)="Finalized",$K15<>""),"",DATE(2027,5,6)) -> 46513 | P15: 365 days | Q15: MEDICARE | R15: 365 days | S15: Processed date | T15: 120 days | U15: Processed date | V15: 2026-05 May | W15: US | AA15: 1 | AB15: =IF($F15="","",TODAY()-$F15) -> 163 | AC15: 93970 | AJ15: I872 | AO15: BURGHER, ABRAM | AP15: ASAP - Surprise - Reems | AQ15: 46246 | AX15: 93970 | AY15: Resubmitted | BA15: Referral / referring provider | BB15: CO_183 - The referring provider is not eligible to refer the service billed | BD15: 46341 | BF15: =IF(TRIM($A15)="Finalized","Closed",IF($BD15="","No review date set",IF($BD15<TODAY(),"OVERDUE",IF($BD15-TODAY()<=7,"Due within 7 days","Scheduled")))) -> Scheduled | BG15: =IF($K15="","",TODAY()-$K15) -> 1 | BH15: =IFERROR(LEFT(IF($B15="","Notes, ","")&IF($K15="","Latest Date Worked, ","")&IF($AY15="","Last Action, ","")&IF(AND(OR(TRIM($A15)="Denied",TRIM($A15)="Rejected"),$BA15=""),"Denial Reason, ","")&IF(AND(TRIM($A15)="Denied",$BB15="",TRIM($BA15)<>"NO DENIAL"),"Denial Code, ","")&IF(AND(TRIM($A15)<>"Finalized",$BD15=""),"Next Review Date, ","")&IF(AND(TRIM($A15)<>"Finalized",$BE15=""),"Next Step, ","")&IF(AND(TRIM($A15)="Finalized",$AV15="",$AR15="",$AT15="",$AX15="",$AW15=""),"CPT outcome, ",""),LEN(IF($B15="","Notes, ","")&IF($K15="","Latest Date Worked, ","")&IF($AY15="","Last Action, ","")&IF(AND(OR(TRIM($A15)="Denied",TRIM($A15)="Rejected"),$BA15=""),"Denial Reason, ","")&IF(AND(TRIM($A15)="Denied",$BB15="",TRIM($BA15)<>"NO DENIAL"),"Denial Code, ","")&IF(AND(TRIM($A15)<>"Finalized",$BD15=""),"Next Review Date, ","")&IF(AND(TRIM($A15)<>"Finalized",$BE15=""),"Next Step, ","")&IF(AND(TRIM($A15)="Finalized",$AV15="",$AR15="",$AT15="",$AX15="",$AW15=""),"CPT outcome, ",""))-2),"") -> Next Step | BI15: =IF($BB15="","",IFERROR(INDEX('Denial Codes'!$C:$C,MATCH(LEFT($BB15,FIND(" - ",$BB15&" - ")+2)&"*",'Denial Codes'!$A:$A,0)),"")) -> Referral / referring provider | BJ15: =IF($BA15="","",IFERROR(INDEX(Lists!$B:$B,MATCH(TRIM($BA15),Lists!$A:$A,0))&"","")) -> Get a valid referral or correct the referring provider, then resubmit.
A16: Denied | B16: Waiting on full recoup to bill PT - ABN signed - Bundling with HHA episode on DOS - HOME HEALTH SCOTTSDALE, LLC NPI 1154898542 | C16: 559112760 | D16: 46218 | E16: HF550801271 | F16: 46149 | G16: AARP United Healthcare | H16: DME Region D | I16: AARP United Healthcare | J16: A6010+A1 x10 | L16: =IF($O16="","",$O16-TODAY()) -> 203 | M16: =IF(AND(TRIM($A16)="Finalized",$K16<>""),"",IF($D16="","",$D16+365-TODAY())) -> 272 | N16: =IF(AND(TRIM($A16)="Finalized",$K16<>""),"",IF($D16="","",$D16+120-TODAY())) -> 27 | O16: =IF(AND(TRIM($A16)="Finalized",$K16<>""),"",DATE(2027,5,7)) -> 46514 | P16: 365 days | Q16: MEDICARE | R16: 365 days | S16: Processed date | T16: 120 days | U16: Processed date | V16: 2026-05 May | W16: DME | X16: A1 | AA16: 10 | AB16: =IF($F16="","",TODAY()-$F16) -> 162 | AC16: A6010 | AJ16: G894 | AK16: M5416 | AL16: M48062 | AN16: 561539073 | AO16: Advanced Spine and Pain LLC DME GWY | AP16: Advanced Spine and Pain LLC DME - Greenway | AQ16: 46155 | AX16: A6010 | BA16: Bundled / NCCI edit | BB16: N88 Alert: This payment is being made conditionally. An HHA episode of care notice has been filed for this patient. When a patient is treated under a HHA episode of care, consolidated billing requires that certain therapy services and supplies, such as this, be included in the HHA's payment. This payment will need to be recouped from you if we establish that the patient is concurrently receiving treatment under a HHA episode of care | BE16: Waiting on full recoup to bill PT | BF16: =IF(TRIM($A16)="Finalized","Closed",IF($BD16="","No review date set",IF($BD16<TODAY(),"OVERDUE",IF($BD16-TODAY()<=7,"Due within 7 days","Scheduled")))) -> No review date set | BG16: =IF($K16="","",TODAY()-$K16) | BH16: =IFERROR(LEFT(IF($B16="","Notes, ","")&IF($K16="","Latest Date Worked, ","")&IF($AY16="","Last Action, ","")&IF(AND(OR(TRIM($A16)="Denied",TRIM($A16)="Rejected"),$BA16=""),"Denial Reason, ","")&IF(AND(TRIM($A16)="Denied",$BB16="",TRIM($BA16)<>"NO DENIAL"),"Denial Code, ","")&IF(AND(TRIM($A16)<>"Finalized",$BD16=""),"Next Review Date, ","")&IF(AND(TRIM($A16)<>"Finalized",$BE16=""),"Next Step, ","")&IF(AND(TRIM($A16)="Finalized",$AV16="",$AR16="",$AT16="",$AX16="",$AW16=""),"CPT outcome, ",""),LEN(IF($B16="","Notes, ","")&IF($K16="","Latest Date Worked, ","")&IF($AY16="","Last Action, ","")&IF(AND(OR(TRIM($A16)="Denied",TRIM($A16)="Rejected"),$BA16=""),"Denial Reason, ","")&IF(AND(TRIM($A16)="Denied",$BB16="",TRIM($BA16)<>"NO DENIAL"),"Denial Code, ","")&IF(AND(TRIM($A16)<>"Finalized",$BD16=""),"Next Review Date, ","")&IF(AND(TRIM($A16)<>"Finalized",$BE16=""),"Next Step, ","")&IF(AND(TRIM($A16)="Finalized",$AV16="",$AR16="",$AT16="",$AX16="",$AW16=""),"CPT outcome, ",""))-2),"") -> Latest Date Worked, Last Action, Next Review Date | BI16: =IF($BB16="","",IFERROR(INDEX('Denial Codes'!$C:$C,MATCH(LEFT($BB16,FIND(" - ",$BB16&" - ")+2)&"*",'Denial Codes'!$A:$A,0)),"")) | BJ16: =IF($BA16="","",IFERROR(INDEX(Lists!$B:$B,MATCH(TRIM($BA16),Lists!$A:$A,0))&"","")) -> Check the NCCI pair; if the service was distinct, add 59/XU (or XS) and resubmit; otherwise adjust.
A17: Rejected | B17: Rejected due to invalid/missing modifier | C17: 560559053 | E17: WC-559349596 | F17: 46168 | G17: Arizona Complete Health (Centene) | H17: Arizona Complete Health (Centene) | I17: No Payer | J17: 99484+95 x1 | L17: =IF($O17="","",$O17-TODAY()) -> -23 | M17: =IF(AND(TRIM($A17)="Finalized",$K17<>""),"",IF($F17="","",$F17+365-TODAY())) -> 222 | N17: =IF(AND(TRIM($A17)="Finalized",$K17<>""),"",IF($F17="","",$F17+365-TODAY())) -> 222 | O17: =IF(AND(TRIM($A17)="Finalized",$K17<>""),"",DATE(2026,9,23)) -> 46288 | P17: 120 days | Q17: AZ COMPLETE | R17: 365 days | S17: Date of service | T17: 365 days | U17: Date of service | V17: 2026-05 May | W17: BH | X17: 95 | AA17: 1 | AB17: =IF($F17="","",TODAY()-$F17) -> 143 | AC17: 99484 | AJ17: M5412 | AK17: M5416 | AL17: Z79891 | AM17: Z1331 | AO17: WILSON, JARED | AP17: ASAP - Gilbert | AQ17: 46275 | AX17: 99204, 99484 | BA17: Modifier issue | BE17: Waiting for D's reply | BF17: =IF(TRIM($A17)="Finalized","Closed",IF($BD17="","No review date set",IF($BD17<TODAY(),"OVERDUE",IF($BD17-TODAY()<=7,"Due within 7 days","Scheduled")))) -> No review date set | BG17: =IF($K17="","",TODAY()-$K17) | BH17: =IFERROR(LEFT(IF($B17="","Notes, ","")&IF($K17="","Latest Date Worked, ","")&IF($AY17="","Last Action, ","")&IF(AND(OR(TRIM($A17)="Denied",TRIM($A17)="Rejected"),$BA17=""),"Denial Reason, ","")&IF(AND(TRIM($A17)="Denied",$BB17="",TRIM($BA17)<>"NO DENIAL"),"Denial Code, ","")&IF(AND(TRIM($A17)<>"Finalized",$BD17=""),"Next Review Date, ","")&IF(AND(TRIM($A17)<>"Finalized",$BE17=""),"Next Step, ","")&IF(AND(TRIM($A17)="Finalized",$AV17="",$AR17="",$AT17="",$AX17="",$AW17=""),"CPT outcome, ",""),LEN(IF($B17="","Notes, ","")&IF($K17="","Latest Date Worked, ","")&IF($AY17="","Last Action, ","")&IF(AND(OR(TRIM($A17)="Denied",TRIM($A17)="Rejected"),$BA17=""),"Denial Reason, ","")&IF(AND(TRIM($A17)="Denied",$BB17="",TRIM($BA17)<>"NO DENIAL"),"Denial Code, ","")&IF(AND(TRIM($A17)<>"Finalized",$BD17=""),"Next Review Date, ","")&IF(AND(TRIM($A17)<>"Finalized",$BE17=""),"Next Step, ","")&IF(AND(TRIM($A17)="Finalized",$AV17="",$AR17="",$AT17="",$AX17="",$AW17=""),"CPT outcome, ",""))-2),"") -> Latest Date Worked, Last Action, Next Review Date | BI17: =IF($BB17="","",IFERROR(INDEX('Denial Codes'!$C:$C,MATCH(LEFT($BB17,FIND(" - ",$BB17&" - ")+2)&"*",'Denial Codes'!$A:$A,0)),"")) | BJ17: =IF($BA17="","",IFERROR(INDEX(Lists!$B:$B,MATCH(TRIM($BA17),Lists!$A:$A,0))&"","")) -> Correct or add the modifier (e.g. NU/RR, KX, RT/LT, 25) and resubmit.
A18: Rejected | B18: Rejected due to invalid/missing modifier | C18: 560607909 | E18: HF559630348 | F18: 46169 | G18: Arizona Complete Health (Centene) | H18: Arizona Complete Health (Centene) | I18: No Payer | J18: 99484+95 x1 | L18: =IF($O18="","",$O18-TODAY()) -> -22 | M18: =IF(AND(TRIM($A18)="Finalized",$K18<>""),"",IF($F18="","",$F18+365-TODAY())) -> 223 | N18: =IF(AND(TRIM($A18)="Finalized",$K18<>""),"",IF($F18="","",$F18+365-TODAY())) -> 223 | O18: =IF(AND(TRIM($A18)="Finalized",$K18<>""),"",DATE(2026,9,24)) -> 46289 | P18: 120 days | Q18: AZ COMPLETE | R18: 365 days | S18: Date of service | T18: 365 days | U18: Date of service | V18: 2026-05 May | W18: BH | X18: 95 | AA18: 1 | AB18: =IF($F18="","",TODAY()-$F18) -> 142 | AC18: 99484 | AJ18: M546 | AK18: M542 | AL18: Z79891 | AM18: Z1331 | AO18: WILSON, JARED | AP18: ASAP - Gilbert | AQ18: 46275 | AX18: 99204, 99484 | BA18: Modifier issue | BE18: Waiting for D's reply | BF18: =IF(TRIM($A18)="Finalized","Closed",IF($BD18="","No review date set",IF($BD18<TODAY(),"OVERDUE",IF($BD18-TODAY()<=7,"Due within 7 days","Scheduled")))) -> No review date set | BG18: =IF($K18="","",TODAY()-$K18) | BH18: =IFERROR(LEFT(IF($B18="","Notes, ","")&IF($K18="","Latest Date Worked, ","")&IF($AY18="","Last Action, ","")&IF(AND(OR(TRIM($A18)="Denied",TRIM($A18)="Rejected"),$BA18=""),"Denial Reason, ","")&IF(AND(TRIM($A18)="Denied",$BB18="",TRIM($BA18)<>"NO DENIAL"),"Denial Code, ","")&IF(AND(TRIM($A18)<>"Finalized",$BD18=""),"Next Review Date, ","")&IF(AND(TRIM($A18)<>"Finalized",$BE18=""),"Next Step, ","")&IF(AND(TRIM($A18)="Finalized",$AV18="",$AR18="",$AT18="",$AX18="",$AW18=""),"CPT outcome, ",""),LEN(IF($B18="","Notes, ","")&IF($K18="","Latest Date Worked, ","")&IF($AY18="","Last Action, ","")&IF(AND(OR(TRIM($A18)="Denied",TRIM($A18)="Rejected"),$BA18=""),"Denial Reason, ","")&IF(AND(TRIM($A18)="Denied",$BB18="",TRIM($BA18)<>"NO DENIAL"),"Denial Code, ","")&IF(AND(TRIM($A18)<>"Finalized",$BD18=""),"Next Review Date, ","")&IF(AND(TRIM($A18)<>"Finalized",$BE18=""),"Next Step, ","")&IF(AND(TRIM($A18)="Finalized",$AV18="",$AR18="",$AT18="",$AX18="",$AW18=""),"CPT outcome, ",""))-2),"") -> Latest Date Worked, Last Action, Next Review Date | BI18: =IF($BB18="","",IFERROR(INDEX('Denial Codes'!$C:$C,MATCH(LEFT($BB18,FIND(" - ",$BB18&" - ")+2)&"*",'Denial Codes'!$A:$A,0)),"")) | BJ18: =IF($BA18="","",IFERROR(INDEX(Lists!$B:$B,MATCH(TRIM($BA18),Lists!$A:$A,0))&"","")) -> Correct or add the modifier (e.g. NU/RR, KX, RT/LT, 25) and resubmit.
A19: Denied | B19: Checking with D to see if I adjust or ask scriber to adjust | C19: 570821252 | D19: 46279 | E19: HF559271506 | F19: 46169 | G19: Medicare Part B Arizona * | H19: Medicare Part B Arizona * | I19: No Payer | J19: 99484+95 x1 | L19: =IF($O19="","",$O19-TODAY()) -> 223 | M19: =IF(AND(TRIM($A19)="Finalized",$K19<>""),"",IF($D19="","",$D19+365-TODAY())) -> 333 | N19: =IF(AND(TRIM($A19)="Finalized",$K19<>""),"",IF($D19="","",$D19+120-TODAY())) -> 88 | O19: =IF(AND(TRIM($A19)="Finalized",$K19<>""),"",DATE(2027,5,27)) -> 46534 | P19: 365 days | Q19: MEDICARE | R19: 365 days | S19: Processed date | T19: 120 days | U19: Processed date | V19: 2026-05 May | W19: BH | X19: 95 | AA19: 1 | AB19: =IF($F19="","",TODAY()-$F19) -> 142 | AC19: 99484 | AJ19: G894 | AK19: M961 | AL19: Z79891 | AM19: Z1331 | AO19: WILSON, JARED | AP19: ASAP - Gilbert | AQ19: 46268 | AX19: 99204, 99484 | BA19: Medical necessity / frequency | BB19: N776 - This service is not a covered Telehealth service | BE19: Waiting for D's reply | BF19: =IF(TRIM($A19)="Finalized","Closed",IF($BD19="","No review date set",IF($BD19<TODAY(),"OVERDUE",IF($BD19-TODAY()<=7,"Due within 7 days","Scheduled")))) -> No review date set | BG19: =IF($K19="","",TODAY()-$K19) | BH19: =IFERROR(LEFT(IF($B19="","Notes, ","")&IF($K19="","Latest Date Worked, ","")&IF($AY19="","Last Action, ","")&IF(AND(OR(TRIM($A19)="Denied",TRIM($A19)="Rejected"),$BA19=""),"Denial Reason, ","")&IF(AND(TRIM($A19)="Denied",$BB19="",TRIM($BA19)<>"NO DENIAL"),"Denial Code, ","")&IF(AND(TRIM($A19)<>"Finalized",$BD19=""),"Next Review Date, ","")&IF(AND(TRIM($A19)<>"Finalized",$BE19=""),"Next Step, ","")&IF(AND(TRIM($A19)="Finalized",$AV19="",$AR19="",$AT19="",$AX19="",$AW19=""),"CPT outcome, ",""),LEN(IF($B19="","Notes, ","")&IF($K19="","Latest Date Worked, ","")&IF($AY19="","Last Action, ","")&IF(AND(OR(TRIM($A19)="Denied",TRIM($A19)="Rejected"),$BA19=""),"Denial Reason, ","")&IF(AND(TRIM($A19)="Denied",$BB19="",TRIM($BA19)<>"NO DENIAL"),"Denial Code, ","")&IF(AND(TRIM($A19)<>"Finalized",$BD19=""),"Next Review Date, ","")&IF(AND(TRIM($A19)<>"Finalized",$BE19=""),"Next Step, ","")&IF(AND(TRIM($A19)="Finalized",$AV19="",$AR19="",$AT19="",$AX19="",$AW19=""),"CPT outcome, ",""))-2),"") -> Latest Date Worked, Last Action, Next Review Date | BI19: =IF($BB19="","",IFERROR(INDEX('Denial Codes'!$C:$C,MATCH(LEFT($BB19,FIND(" - ",$BB19&" - ")+2)&"*",'Denial Codes'!$A:$A,0)),"")) -> Not covered by plan | BJ19: =IF($BA19="","",IFERROR(INDEX(Lists!$B:$B,MATCH(TRIM($BA19),Lists!$A:$A,0))&"","")) -> Appeal with medical records and a letter of medical necessity; check LCD/MUE limits.
A20: Under Review | B20: I need to confirm with D if 99204 would be adjusted or we can change the encounter notes | C20: 560610028 | D20: 46283 | E20: HF559317309 | F20: 46169 | G20: Medicare Part B Arizona * | H20: Medicare Part B Arizona * | I20: Blue Cross Blue Shield of Arizona (BCBS AZ) | J20: 99484+95 x1 | L20: =IF($O20="","",$O20-TODAY()) -> 223 | M20: =IF(AND(TRIM($A20)="Finalized",$K20<>""),"",IF($D20="","",$D20+365-TODAY())) -> 337 | N20: =IF(AND(TRIM($A20)="Finalized",$K20<>""),"",IF($D20="","",$D20+120-TODAY())) -> 92 | O20: =IF(AND(TRIM($A20)="Finalized",$K20<>""),"",DATE(2027,5,27)) -> 46534 | P20: 365 days | Q20: MEDICARE | R20: 365 days | S20: Processed date | T20: 120 days | U20: Processed date | V20: 2026-05 May | W20: BH | X20: 95 | AA20: 1 | AB20: =IF($F20="","",TODAY()-$F20) -> 142 | AC20: 99484 | AJ20: G894 | AK20: M4804 | AL20: M961 | AM20: K5903 | AO20: WILSON, JARED | AP20: ASAP - Gilbert | AQ20: 46275 | AT20: 99204 | AU20: CO_151 - Payer deems the information submitted does not support this many/frequency of services | AX20: 99204, 99484 | BA20: Medical necessity / frequency | BB20: CO_151 - Payer deems the information submitted does not support this many/frequency of services | BD20: 46310 | BE20: I need to confirm with D if 99204 would be adjusted or we can change the encounter notes - if I can resubmit with 99214 I need to bill with POS 11 and remove mod 95 | BF20: =IF(TRIM($A20)="Finalized","Closed",IF($BD20="","No review date set",IF($BD20<TODAY(),"OVERDUE",IF($BD20-TODAY()<=7,"Due within 7 days","Scheduled")))) -> OVERDUE | BG20: =IF($K20="","",TODAY()-$K20) | BH20: =IFERROR(LEFT(IF($B20="","Notes, ","")&IF($K20="","Latest Date Worked, ","")&IF($AY20="","Last Action, ","")&IF(AND(OR(TRIM($A20)="Denied",TRIM($A20)="Rejected"),$BA20=""),"Denial Reason, ","")&IF(AND(TRIM($A20)="Denied",$BB20="",TRIM($BA20)<>"NO DENIAL"),"Denial Code, ","")&IF(AND(TRIM($A20)<>"Finalized",$BD20=""),"Next Review Date, ","")&IF(AND(TRIM($A20)<>"Finalized",$BE20=""),"Next Step, ","")&IF(AND(TRIM($A20)="Finalized",$AV20="",$AR20="",$AT20="",$AX20="",$AW20=""),"CPT outcome, ",""),LEN(IF($B20="","Notes, ","")&IF($K20="","Latest Date Worked, ","")&IF($AY20="","Last Action, ","")&IF(AND(OR(TRIM($A20)="Denied",TRIM($A20)="Rejected"),$BA20=""),"Denial Reason, ","")&IF(AND(TRIM($A20)="Denied",$BB20="",TRIM($BA20)<>"NO DENIAL"),"Denial Code, ","")&IF(AND(TRIM($A20)<>"Finalized",$BD20=""),"Next Review Date, ","")&IF(AND(TRIM($A20)<>"Finalized",$BE20=""),"Next Step, ","")&IF(AND(TRIM($A20)="Finalized",$AV20="",$AR20="",$AT20="",$AX20="",$AW20=""),"CPT outcome, ",""))-2),"") -> Latest Date Worked, Last Action | BI20: =IF($BB20="","",IFERROR(INDEX('Denial Codes'!$C:$C,MATCH(LEFT($BB20,FIND(" - ",$BB20&" - ")+2)&"*",'Denial Codes'!$A:$A,0)),"")) -> Medical necessity / frequency | BJ20: =IF($BA20="","",IFERROR(INDEX(Lists!$B:$B,MATCH(TRIM($BA20),Lists!$A:$A,0))&"","")) -> Appeal with medical records and a letter of medical necessity; check LCD/MUE limits.
A21: PAID | B21: OP | C21: 562125174 | D21: 46280 | E21: HF480446510 | F21: 46175 | G21: Blue Cross Blue Shield of Arizona (BCBS AZ) | H21: Blue Cross Blue Shield of Arizona (BCBS AZ) | I21: No Payer | J21: L0637+KX x1 | L21: =IF($O21="","",$O21-TODAY()) -> -46 | M21: =IF(AND(TRIM($A21)="Finalized",$K21<>""),"",IF($F21="","",$F21+90-TODAY())) -> -46 | N21: =IF(AND(TRIM($A21)="Finalized",$K21<>""),"",IF($D21="","",$D21+365-TODAY())) -> 334 | O21: =IF(AND(TRIM($A21)="Finalized",$K21<>""),"",DATE(2026,8,31)) -> 46265 | P21: 90 days | Q21: BCBS | R21: 90 days | S21: Date of service | T21: 365 days | U21: Processed date | V21: 2026-06 June | W21: DME | X21: KX | AA21: 1 | AB21: =IF($F21="","",TODAY()-$F21) -> 136 | AC21: L0637 | AJ21: M47816 | AO21: BARCOME, MARYBETH | AP21: ASAP Peoria | AQ21: 46185 | AV21: L0637 | BE21: We need to renfund BCBS | BF21: =IF(TRIM($A21)="Finalized","Closed",IF($BD21="","No review date set",IF($BD21<TODAY(),"OVERDUE",IF($BD21-TODAY()<=7,"Due within 7 days","Scheduled")))) -> No review date set | BG21: =IF($K21="","",TODAY()-$K21) | BH21: =IFERROR(LEFT(IF($B21="","Notes, ","")&IF($K21="","Latest Date Worked, ","")&IF($AY21="","Last Action, ","")&IF(AND(OR(TRIM($A21)="Denied",TRIM($A21)="Rejected"),$BA21=""),"Denial Reason, ","")&IF(AND(TRIM($A21)="Denied",$BB21="",TRIM($BA21)<>"NO DENIAL"),"Denial Code, ","")&IF(AND(TRIM($A21)<>"Finalized",$BD21=""),"Next Review Date, ","")&IF(AND(TRIM($A21)<>"Finalized",$BE21=""),"Next Step, ","")&IF(AND(TRIM($A21)="Finalized",$AV21="",$AR21="",$AT21="",$AX21="",$AW21=""),"CPT outcome, ",""),LEN(IF($B21="","Notes, ","")&IF($K21="","Latest Date Worked, ","")&IF($AY21="","Last Action, ","")&IF(AND(OR(TRIM($A21)="Denied",TRIM($A21)="Rejected"),$BA21=""),"Denial Reason, ","")&IF(AND(TRIM($A21)="Denied",$BB21="",TRIM($BA21)<>"NO DENIAL"),"Denial Code, ","")&IF(AND(TRIM($A21)<>"Finalized",$BD21=""),"Next Review Date, ","")&IF(AND(TRIM($A21)<>"Finalized",$BE21=""),"Next Step, ","")&IF(AND(TRIM($A21)="Finalized",$AV21="",$AR21="",$AT21="",$AX21="",$AW21=""),"CPT outcome, ",""))-2),"") -> Latest Date Worked, Last Action, Next Review Date | BI21: =IF($BB21="","",IFERROR(INDEX('Denial Codes'!$C:$C,MATCH(LEFT($BB21,FIND(" - ",$BB21&" - ")+2)&"*",'Denial Codes'!$A:$A,0)),"")) | BJ21: =IF($BA21="","",IFERROR(INDEX(Lists!$B:$B,MATCH(TRIM($BA21),Lists!$A:$A,0))&"",""))
A22: PAID | B22: OP | C22: 563181415 | D22: 46258 | E22: HF537547660 | F22: 46195 | G22: Blue Cross Blue Shield of Arizona (BCBS AZ) | H22: Blue Cross Blue Shield of Arizona (BCBS AZ) | I22: No Payer | J22: L0637+KX x1 | L22: =IF($O22="","",$O22-TODAY()) -> -26 | M22: =IF(AND(TRIM($A22)="Finalized",$K22<>""),"",IF($F22="","",$F22+90-TODAY())) -> -26 | N22: =IF(AND(TRIM($A22)="Finalized",$K22<>""),"",IF($D22="","",$D22+365-TODAY())) -> 312 | O22: =IF(AND(TRIM($A22)="Finalized",$K22<>""),"",DATE(2026,9,20)) -> 46285 | P22: 90 days | Q22: BCBS | R22: 90 days | S22: Date of service | T22: 365 days | U22: Processed date | V22: 2026-06 June | W22: DME | X22: KX | AA22: 1 | AB22: =IF($F22="","",TODAY()-$F22) -> 116 | AC22: L0637 | AJ22: M5416 | AK22: M5116 | AL22: M48061 | AO22: TURLEY, TODD | AP22: ASAP - DEER VALLEY | AQ22: 46196 | AV22: L0637 | BE22: We need to renfund BCBS | BF22: =IF(TRIM($A22)="Finalized","Closed",IF($BD22="","No review date set",IF($BD22<TODAY(),"OVERDUE",IF($BD22-TODAY()<=7,"Due within 7 days","Scheduled")))) -> No review date set | BG22: =IF($K22="","",TODAY()-$K22) | BH22: =IFERROR(LEFT(IF($B22="","Notes, ","")&IF($K22="","Latest Date Worked, ","")&IF($AY22="","Last Action, ","")&IF(AND(OR(TRIM($A22)="Denied",TRIM($A22)="Rejected"),$BA22=""),"Denial Reason, ","")&IF(AND(TRIM($A22)="Denied",$BB22="",TRIM($BA22)<>"NO DENIAL"),"Denial Code, ","")&IF(AND(TRIM($A22)<>"Finalized",$BD22=""),"Next Review Date, ","")&IF(AND(TRIM($A22)<>"Finalized",$BE22=""),"Next Step, ","")&IF(AND(TRIM($A22)="Finalized",$AV22="",$AR22="",$AT22="",$AX22="",$AW22=""),"CPT outcome, ",""),LEN(IF($B22="","Notes, ","")&IF($K22="","Latest Date Worked, ","")&IF($AY22="","Last Action, ","")&IF(AND(OR(TRIM($A22)="Denied",TRIM($A22)="Rejected"),$BA22=""),"Denial Reason, ","")&IF(AND(TRIM($A22)="Denied",$BB22="",TRIM($BA22)<>"NO DENIAL"),"Denial Code, ","")&IF(AND(TRIM($A22)<>"Finalized",$BD22=""),"Next Review Date, ","")&IF(AND(TRIM($A22)<>"Finalized",$BE22=""),"Next Step, ","")&IF(AND(TRIM($A22)="Finalized",$AV22="",$AR22="",$AT22="",$AX22="",$AW22=""),"CPT outcome, ",""))-2),"") -> Latest Date Worked, Last Action, Next Review Date | BI22: =IF($BB22="","",IFERROR(INDEX('Denial Codes'!$C:$C,MATCH(LEFT($BB22,FIND(" - ",$BB22&" - ")+2)&"*",'Denial Codes'!$A:$A,0)),"")) | BJ22: =IF($BA22="","",IFERROR(INDEX(Lists!$B:$B,MATCH(TRIM($BA22),Lists!$A:$A,0))&"",""))
A23: Denied | B23: Remove 25 from 62323 and add it to 99204, and resubmitted | C23: 563596494 | E23: HF563557943 | F23: 46199 | G23: Medicare Part B Arizona * | H23: Medicare Part B Arizona * | I23: No Payer | J23: 62323+25 x1 | K23: 46309 | L23: =IF($O23="","",$O23-TODAY()) -> 253 | M23: =IF(AND(TRIM($A23)="Finalized",$K23<>""),"",IF($D23="","",$D23+365-TODAY())) | N23: =IF(AND(TRIM($A23)="Finalized",$K23<>""),"",IF($D23="","",$D23+120-TODAY())) | O23: =IF(AND(TRIM($A23)="Finalized",$K23<>""),"",DATE(2027,6,26)) -> 46564 | P23: 365 days | Q23: MEDICARE | R23: 365 days | S23: Processed date | T23: 120 days | U23: Processed date | V23: 2026-06 June | W23: ORTHO | X23: 25 | AA23: 1 | AB23: =IF($F23="","",TODAY()-$F23) -> 112 | AC23: 62323 | AJ23: Z79891 | AO23: WILSON, JARED | AP23: ASAP - Tucson | AQ23: 46289 | AV23: 99204, G3002, 99484 | AX23: 62323 | AY23: Resubmitted | BA23: Modifier issue | BB23: CO_4 - The procedure code is inconsistent with the modifier used, or a required modifier is missing | BF23: =IF(TRIM($A23)="Finalized","Closed",IF($BD23="","No review date set",IF($BD23<TODAY(),"OVERDUE",IF($BD23-TODAY()<=7,"Due within 7 days","Scheduled")))) -> No review date set | BG23: =IF($K23="","",TODAY()-$K23) -> 2 | BH23: =IFERROR(LEFT(IF($B23="","Notes, ","")&IF($K23="","Latest Date Worked, ","")&IF($AY23="","Last Action, ","")&IF(AND(OR(TRIM($A23)="Denied",TRIM($A23)="Rejected"),$BA23=""),"Denial Reason, ","")&IF(AND(TRIM($A23)="Denied",$BB23="",TRIM($BA23)<>"NO DENIAL"),"Denial Code, ","")&IF(AND(TRIM($A23)<>"Finalized",$BD23=""),"Next Review Date, ","")&IF(AND(TRIM($A23)<>"Finalized",$BE23=""),"Next Step, ","")&IF(AND(TRIM($A23)="Finalized",$AV23="",$AR23="",$AT23="",$AX23="",$AW23=""),"CPT outcome, ",""),LEN(IF($B23="","Notes, ","")&IF($K23="","Latest Date Worked, ","")&IF($AY23="","Last Action, ","")&IF(AND(OR(TRIM($A23)="Denied",TRIM($A23)="Rejected"),$BA23=""),"Denial Reason, ","")&IF(AND(TRIM($A23)="Denied",$BB23="",TRIM($BA23)<>"NO DENIAL"),"Denial Code, ","")&IF(AND(TRIM($A23)<>"Finalized",$BD23=""),"Next Review Date, ","")&IF(AND(TRIM($A23)<>"Finalized",$BE23=""),"Next Step, ","")&IF(AND(TRIM($A23)="Finalized",$AV23="",$AR23="",$AT23="",$AX23="",$AW23=""),"CPT outcome, ",""))-2),"") -> Next Review Date, Next Step | BI23: =IF($BB23="","",IFERROR(INDEX('Denial Codes'!$C:$C,MATCH(LEFT($BB23,FIND(" - ",$BB23&" - ")+2)&"*",'Denial Codes'!$A:$A,0)),"")) -> Modifier issue | BJ23: =IF($BA23="","",IFERROR(INDEX(Lists!$B:$B,MATCH(TRIM($BA23),Lists!$A:$A,0))&"","")) -> Correct or add the modifier (e.g. NU/RR, KX, RT/LT, 25) and resubmit.
A24: Rejected | B24: TFierro30 Called Az priority care and BCBS HAve a claifiction requested escalated to see who the payer was Call ref# 12696890 rep MousamK - Resubmitted to APCP - Rep Heather - The member is assigned to an affiliated network - Arizona Priority Care | C24: 569646388 | D24: 46259 | E24: HF527306886 | F24: 46037 | G24: Arizona Priority Care Plus | H24: Arizona Priority Care Plus | I24: No Payer | J24: 63685 x1 | K24: 46279 | L24: =IF($O24="","",$O24-TODAY()) -> -214 | M24: =IF(AND(TRIM($A24)="Finalized",$K24<>""),"",IF($D24="","",$D24+365-TODAY())) -> 313 | N24: =IF(AND(TRIM($A24)="Finalized",$K24<>""),"",IF($D24="","",$D24+365-TODAY())) -> 313 | O24: =IF(AND(TRIM($A24)="Finalized",$K24<>""),"",DATE(2026,3,16)) -> 46097 | P24: 60 days | Q24: AZ PRIORITY CARE | R24: 365 days | S24: Processed date | T24: 365 days | U24: Processed date | V24: 2026-01 January | W24: ORTHO | AA24: 1 | AB24: =IF($F24="","",TODAY()-$F24) -> 274 | AC24: 63685 | AJ24: M961 | AK24: M5416 | AO24: KALLGREN, MARK | AP24: Premier Endoscopy Center, LLC | AQ24: 46048 | AX24: 63047 | AY24: Contacted payer | AZ24: Resubmitted; Contacted payer | BA24: Wrong payer / vendor | BC24: Call ref # 12696890; Call ref # 10627708 | BD24: 46309 | BF24: =IF(TRIM($A24)="Finalized","Closed",IF($BD24="","No review date set",IF($BD24<TODAY(),"OVERDUE",IF($BD24-TODAY()<=7,"Due within 7 days","Scheduled")))) -> OVERDUE | BG24: =IF($K24="","",TODAY()-$K24) -> 32 | BH24: =IFERROR(LEFT(IF($B24="","Notes, ","")&IF($K24="","Latest Date Worked, ","")&IF($AY24="","Last Action, ","")&IF(AND(OR(TRIM($A24)="Denied",TRIM($A24)="Rejected"),$BA24=""),"Denial Reason, ","")&IF(AND(TRIM($A24)="Denied",$BB24="",TRIM($BA24)<>"NO DENIAL"),"Denial Code, ","")&IF(AND(TRIM($A24)<>"Finalized",$BD24=""),"Next Review Date, ","")&IF(AND(TRIM($A24)<>"Finalized",$BE24=""),"Next Step, ","")&IF(AND(TRIM($A24)="Finalized",$AV24="",$AR24="",$AT24="",$AX24="",$AW24=""),"CPT outcome, ",""),LEN(IF($B24="","Notes, ","")&IF($K24="","Latest Date Worked, ","")&IF($AY24="","Last Action, ","")&IF(AND(OR(TRIM($A24)="Denied",TRIM($A24)="Rejected"),$BA24=""),"Denial Reason, ","")&IF(AND(TRIM($A24)="Denied",$BB24="",TRIM($BA24)<>"NO DENIAL"),"Denial Code, ","")&IF(AND(TRIM($A24)<>"Finalized",$BD24=""),"Next Review Date, ","")&IF(AND(TRIM($A24)<>"Finalized",$BE24=""),"Next Step, ","")&IF(AND(TRIM($A24)="Finalized",$AV24="",$AR24="",$AT24="",$AX24="",$AW24=""),"CPT outcome, ",""))-2),"") -> Next Step | BI24: =IF($BB24="","",IFERROR(INDEX('Denial Codes'!$C:$C,MATCH(LEFT($BB24,FIND(" - ",$BB24&" - ")+2)&"*",'Denial Codes'!$A:$A,0)),"")) | BJ24: =IF($BA24="","",IFERROR(INDEX(Lists!$B:$B,MATCH(TRIM($BA24),Lists!$A:$A,0))&"","")) -> Bill the correct payer, delegated vendor or capitated group/IPA (e.g. Optum Behavioral, Preferred Homecare).
A25: Pending | B25: secondary - Corrected adjustments, and resubmitted | C25: 546184427 | D25: 46089 | E25: HF503610126 | F25: 46027 | G25: Tricare for Life (All Regions) | H25: Humana | I25: Tricare for Life (All Regions) | J25: A6023+A2 x20 | K25: 46141 | L25: =IF($O25="","",$O25-TODAY()) -> -194 | M25: =IF(AND(TRIM($A25)="Finalized",$K25<>""),"",IF($F25="","",$F25+90-TODAY())) -> -194 | N25: =IF(AND(TRIM($A25)="Finalized",$K25<>""),"",IF($D25="","",$D25+60-TODAY())) -> -162 | O25: =IF(AND(TRIM($A25)="Finalized",$K25<>""),"",DATE(2026,4,5)) -> 46117 | P25: 90 days | Q25: HUMANA COMMERCIAL | R25: 90 days | S25: Date of service | T25: 60 days | U25: Processed date | V25: 2026-01 January | W25: DME | X25: A2 | AA25: 20 | AB25: =IF($F25="","",TODAY()-$F25) -> 284 | AC25: A6023 | AJ25: G894 | AK25: G90513 | AL25: M961 | AN25: 557644876 | AO25: MCMURDIE, TODD | AP25: ASAP - Surprise - Reems | AQ25: 46036 | AV25: A6023 | AX25: A6023 | AY25: Resubmitted | BA25: Other insurance / COB | BD25: 46171 | BE25: Cross over claim to secondary | BF25: =IF(TRIM($A25)="Finalized","Closed",IF($BD25="","No review date set",IF($BD25<TODAY(),"OVERDUE",IF($BD25-TODAY()<=7,"Due within 7 days","Scheduled")))) -> OVERDUE | BG25: =IF($K25="","",TODAY()-$K25) -> 170 | BH25: =IFERROR(LEFT(IF($B25="","Notes, ","")&IF($K25="","Latest Date Worked, ","")&IF($AY25="","Last Action, ","")&IF(AND(OR(TRIM($A25)="Denied",TRIM($A25)="Rejected"),$BA25=""),"Denial Reason, ","")&IF(AND(TRIM($A25)="Denied",$BB25="",TRIM($BA25)<>"NO DENIAL"),"Denial Code, ","")&IF(AND(TRIM($A25)<>"Finalized",$BD25=""),"Next Review Date, ","")&IF(AND(TRIM($A25)<>"Finalized",$BE25=""),"Next Step, ","")&IF(AND(TRIM($A25)="Finalized",$AV25="",$AR25="",$AT25="",$AX25="",$AW25=""),"CPT outcome, ",""),LEN(IF($B25="","Notes, ","")&IF($K25="","Latest Date Worked, ","")&IF($AY25="","Last Action, ","")&IF(AND(OR(TRIM($A25)="Denied",TRIM($A25)="Rejected"),$BA25=""),"Denial Reason, ","")&IF(AND(TRIM($A25)="Denied",$BB25="",TRIM($BA25)<>"NO DENIAL"),"Denial Code, ","")&IF(AND(TRIM($A25)<>"Finalized",$BD25=""),"Next Review Date, ","")&IF(AND(TRIM($A25)<>"Finalized",$BE25=""),"Next Step, ","")&IF(AND(TRIM($A25)="Finalized",$AV25="",$AR25="",$AT25="",$AX25="",$AW25=""),"CPT outcome, ",""))-2),"") | BI25: =IF($BB25="","",IFERROR(INDEX('Denial Codes'!$C:$C,MATCH(LEFT($BB25,FIND(" - ",$BB25&" - ")+2)&"*",'Denial Codes'!$A:$A,0)),"")) | BJ25: =IF($BA25="","",IFERROR(INDEX(Lists!$B:$B,MATCH(TRIM($BA25),Lists!$A:$A,0))&"","")) -> Get the other insurance and primary EOB, update COB with the payer and bill primary first.
A26: Denied | B26: Uploaded MR | C26: 545332485 | D26: 46142 | E26: HF532613047 | F26: 46028 | G26: United Healthcare | H26: United Healthcare | I26: No Payer | J26: 99494 x1 | K26: 46122 | L26: =IF($O26="","",$O26-TODAY()) -> -193 | M26: =IF(AND(TRIM($A26)="Finalized",$K26<>""),"",IF($D26="","",$D26+180-TODAY())) -> 11 | N26: =IF(AND(TRIM($A26)="Finalized",$K26<>""),"",IF($D26="","",$D26+365-TODAY())) -> 196 | O26: =IF(AND(TRIM($A26)="Finalized",$K26<>""),"",DATE(2026,4,6)) -> 46118 | P26: 90 days | Q26: UHC COMMERCIAL | R26: 180 days | S26: Processed date | T26: 365 days | U26: Processed date | V26: 2026-01 January | W26: BH | AA26: 1 | AB26: =IF($F26="","",TODAY()-$F26) -> 283 | AC26: 99494 | AJ26: F4320 | AO26: MEARS, CHAD | AP26: ASAP Peoria | AQ26: 46057 | AX26: 99494 | AY26: Uploaded MR | BA26: Medical records needed | BB26: CO_252 - An attachment/other documentation is required to adjudicate this claim/service | BC26: PIQ-82135368 | BD26: 46152 | BF26: =IF(TRIM($A26)="Finalized","Closed",IF($BD26="","No review date set",IF($BD26<TODAY(),"OVERDUE",IF($BD26-TODAY()<=7,"Due within 7 days","Scheduled")))) -> OVERDUE | BG26: =IF($K26="","",TODAY()-$K26) -> 189 | BH26: =IFERROR(LEFT(IF($B26="","Notes, ","")&IF($K26="","Latest Date Worked, ","")&IF($AY26="","Last Action, ","")&IF(AND(OR(TRIM($A26)="Denied",TRIM($A26)="Rejected"),$BA26=""),"Denial Reason, ","")&IF(AND(TRIM($A26)="Denied",$BB26="",TRIM($BA26)<>"NO DENIAL"),"Denial Code, ","")&IF(AND(TRIM($A26)<>"Finalized",$BD26=""),"Next Review Date, ","")&IF(AND(TRIM($A26)<>"Finalized",$BE26=""),"Next Step, ","")&IF(AND(TRIM($A26)="Finalized",$AV26="",$AR26="",$AT26="",$AX26="",$AW26=""),"CPT outcome, ",""),LEN(IF($B26="","Notes, ","")&IF($K26="","Latest Date Worked, ","")&IF($AY26="","Last Action, ","")&IF(AND(OR(TRIM($A26)="Denied",TRIM($A26)="Rejected"),$BA26=""),"Denial Reason, ","")&IF(AND(TRIM($A26)="Denied",$BB26="",TRIM($BA26)<>"NO DENIAL"),"Denial Code, ","")&IF(AND(TRIM($A26)<>"Finalized",$BD26=""),"Next Review Date, ","")&IF(AND(TRIM($A26)<>"Finalized",$BE26=""),"Next Step, ","")&IF(AND(TRIM($A26)="Finalized",$AV26="",$AR26="",$AT26="",$AX26="",$AW26=""),"CPT outcome, ",""))-2),"") -> Next Step | BI26: =IF($BB26="","",IFERROR(INDEX('Denial Codes'!$C:$C,MATCH(LEFT($BB26,FIND(" - ",$BB26&" - ")+2)&"*",'Denial Codes'!$A:$A,0)),"")) -> Medical records needed | BJ26: =IF($BA26="","",IFERROR(INDEX(Lists!$B:$B,MATCH(TRIM($BA26),Lists!$A:$A,0))&"","")) -> Upload the MR on the payer portal, note the PIQ/reference number and set a review date.
A27: Under Review | C27: 545484752 | D27: 46063 | E27: HF331360774 | F27: 46029 | G27: Blue Cross Blue Shield of Arizona (BCBS AZ) | H27: Blue Cross Blue Shield of Arizona (BCBS AZ) | I27: No Payer | J27: 99494 x1; 99492 x1 | L27: =IF($O27="","",$O27-TODAY()) -> -192 | M27: =IF(AND(TRIM($A27)="Finalized",$K27<>""),"",IF($F27="","",$F27+90-TODAY())) -> -192 | N27: =IF(AND(TRIM($A27)="Finalized",$K27<>""),"",IF($D27="","",$D27+365-TODAY())) -> 117 | O27: =IF(AND(TRIM($A27)="Finalized",$K27<>""),"",DATE(2026,4,7)) -> 46119 | P27: 90 days | Q27: BCBS | R27: 90 days | S27: Date of service | T27: 365 days | U27: Processed date | V27: 2026-01 January | W27: BH | AA27: 1 | AB27: =IF($F27="","",TODAY()-$F27) -> 282 | AC27: 99494 | AD27: 99492 | AJ27: F4320 | AO27: SARKAR, AWNIK | AP27: ASAP Peoria | AQ27: 46057 | BA27: Eligibility / member ID | BE27: Locate active plan on DOS (checking with Tricare) | BF27: =IF(TRIM($A27)="Finalized","Closed",IF($BD27="","No review date set",IF($BD27<TODAY(),"OVERDUE",IF($BD27-TODAY()<=7,"Due within 7 days","Scheduled")))) -> No review date set | BG27: =IF($K27="","",TODAY()-$K27) | BH27: =IFERROR(LEFT(IF($B27="","Notes, ","")&IF($K27="","Latest Date Worked, ","")&IF($AY27="","Last Action, ","")&IF(AND(OR(TRIM($A27)="Denied",TRIM($A27)="Rejected"),$BA27=""),"Denial Reason, ","")&IF(AND(TRIM($A27)="Denied",$BB27="",TRIM($BA27)<>"NO DENIAL"),"Denial Code, ","")&IF(AND(TRIM($A27)<>"Finalized",$BD27=""),"Next Review Date, ","")&IF(AND(TRIM($A27)<>"Finalized",$BE27=""),"Next Step, ","")&IF(AND(TRIM($A27)="Finalized",$AV27="",$AR27="",$AT27="",$AX27="",$AW27=""),"CPT outcome, ",""),LEN(IF($B27="","Notes, ","")&IF($K27="","Latest Date Worked, ","")&IF($AY27="","Last Action, ","")&IF(AND(OR(TRIM($A27)="Denied",TRIM($A27)="Rejected"),$BA27=""),"Denial Reason, ","")&IF(AND(TRIM($A27)="Denied",$BB27="",TRIM($BA27)<>"NO DENIAL"),"Denial Code, ","")&IF(AND(TRIM($A27)<>"Finalized",$BD27=""),"Next Review Date, ","")&IF(AND(TRIM($A27)<>"Finalized",$BE27=""),"Next Step, ","")&IF(AND(TRIM($A27)="Finalized",$AV27="",$AR27="",$AT27="",$AX27="",$AW27=""),"CPT outcome, ",""))-2),"") -> Notes, Latest Date Worked, Last Action, Next Review Date | BI27: =IF($BB27="","",IFERROR(INDEX('Denial Codes'!$C:$C,MATCH(LEFT($BB27,FIND(" - ",$BB27&" - ")+2)&"*",'Denial Codes'!$A:$A,0)),"")) | BJ27: =IF($BA27="","",IFERROR(INDEX(Lists!$B:$B,MATCH(TRIM($BA27),Lists!$A:$A,0))&"","")) -> Verify eligibility; correct the member ID/MBI, name or DOB and resubmit.
A28: PAID | B28: OP | C28: 555109108 | D28: 46199 | E28: HF537320032 | F28: 46030 | G28: Humana Gold Plus HMO | H28: Humana Gold Plus HMO | I28: No Payer | J28: 93925 x1 | K28: 46212 | L28: =IF($O28="","",$O28-TODAY()) -> -191 | M28: =IF(AND(TRIM($A28)="Finalized",$K28<>""),"",IF($F28="","",$F28+90-TODAY())) -> -191 | N28: =IF(AND(TRIM($A28)="Finalized",$K28<>""),"",IF($D28="","",$D28+540-TODAY())) -> 428 | O28: =IF(AND(TRIM($A28)="Finalized",$K28<>""),"",DATE(2026,4,8)) -> 46120 | P28: 90 days | Q28: HUMANA MA | R28: 90 days | S28: Date of service | T28: 540 days | U28: Processed date | V28: 2026-01 January | W28: US | AA28: 1 | AB28: =IF($F28="","",TODAY()-$F28) -> 281 | AC28: 93925 | AJ28: I739 | AO28: TURLEY, TODD | AP28: ASAP - DEER VALLEY | AQ28: 46048 | AV28: 93925 | AX28: 93925 | BD28: 46243 | BE28: Void original claim 547459229 (overpayment) | BF28: =IF(TRIM($A28)="Finalized","Closed",IF($BD28="","No review date set",IF($BD28<TODAY(),"OVERDUE",IF($BD28-TODAY()<=7,"Due within 7 days","Scheduled")))) -> OVERDUE | BG28: =IF($K28="","",TODAY()-$K28) -> 99 | BH28: =IFERROR(LEFT(IF($B28="","Notes, ","")&IF($K28="","Latest Date Worked, ","")&IF($AY28="","Last Action, ","")&IF(AND(OR(TRIM($A28)="Denied",TRIM($A28)="Rejected"),$BA28=""),"Denial Reason, ","")&IF(AND(TRIM($A28)="Denied",$BB28="",TRIM($BA28)<>"NO DENIAL"),"Denial Code, ","")&IF(AND(TRIM($A28)<>"Finalized",$BD28=""),"Next Review Date, ","")&IF(AND(TRIM($A28)<>"Finalized",$BE28=""),"Next Step, ","")&IF(AND(TRIM($A28)="Finalized",$AV28="",$AR28="",$AT28="",$AX28="",$AW28=""),"CPT outcome, ",""),LEN(IF($B28="","Notes, ","")&IF($K28="","Latest Date Worked, ","")&IF($AY28="","Last Action, ","")&IF(AND(OR(TRIM($A28)="Denied",TRIM($A28)="Rejected"),$BA28=""),"Denial Reason, ","")&IF(AND(TRIM($A28)="Denied",$BB28="",TRIM($BA28)<>"NO DENIAL"),"Denial Code, ","")&IF(AND(TRIM($A28)<>"Finalized",$BD28=""),"Next Review Date, ","")&IF(AND(TRIM($A28)<>"Finalized",$BE28=""),"Next Step, ","")&IF(AND(TRIM($A28)="Finalized",$AV28="",$AR28="",$AT28="",$AX28="",$AW28=""),"CPT outcome, ",""))-2),"") -> Last Action | BI28: =IF($BB28="","",IFERROR(INDEX('Denial Codes'!$C:$C,MATCH(LEFT($BB28,FIND(" - ",$BB28&" - ")+2)&"*",'Denial Codes'!$A:$A,0)),"")) | BJ28: =IF($BA28="","",IFERROR(INDEX(Lists!$B:$B,MATCH(TRIM($BA28),Lists!$A:$A,0))&"",""))
A29: Denied | B29: Filed reconsideration - Optum letter reference # 70293624 said cpt 99492 denied because: The medical records submitted indicate this procedure was performed in office (place of service code 11). However, the claim form indicates a different place of service, specifically telehealth provided in patients home(place of service code 10). This discrepancy means we can't verify the validity and accuracy of the claim - Jess uploaded MR | C29: 545748574 | D29: 46141 | E29: HF537684538 | F29: 46031 | G29: United Healthcare | H29: United Healthcare | I29: No Payer | J29: 99494 x1; 99492 x1 | K29: 46304 | L29: =IF($O29="","",$O29-TODAY()) -> -190 | M29: =IF(AND(TRIM($A29)="Finalized",$K29<>""),"",IF($D29="","",$D29+180-TODAY())) -> 10 | N29: =IF(AND(TRIM($A29)="Finalized",$K29<>""),"",IF($D29="","",$D29+365-TODAY())) -> 195 | O29: =IF(AND(TRIM($A29)="Finalized",$K29<>""),"",DATE(2026,4,9)) -> 46121 | P29: 90 days | Q29: UHC COMMERCIAL | R29: 180 days | S29: Processed date | T29: 365 days | U29: Processed date | V29: 2026-01 January | W29: BH | AA29: 1 | AB29: =IF($F29="","",TODAY()-$F29) -> 280 | AC29: 99494 | AD29: 99492 | AJ29: F4320 | AO29: TURLEY, TODD | AP29: ASAP Peoria | AQ29: 46057 | AX29: 99492 | AY29: Recon filed | AZ29: Uploaded MR | BA29: Place of service | BC29: PIQ-92429715; Optum letter ref # 70293624 | BD29: 46335 | BF29: =IF(TRIM($A29)="Finalized","Closed",IF($BD29="","No review date set",IF($BD29<TODAY(),"OVERDUE",IF($BD29-TODAY()<=7,"Due within 7 days","Scheduled")))) -> Scheduled | BG29: =IF($K29="","",TODAY()-$K29) -> 7 | BH29: =IFERROR(LEFT(IF($B29="","Notes, ","")&IF($K29="","Latest Date Worked, ","")&IF($AY29="","Last Action, ","")&IF(AND(OR(TRIM($A29)="Denied",TRIM($A29)="Rejected"),$BA29=""),"Denial Reason, ","")&IF(AND(TRIM($A29)="Denied",$BB29="",TRIM($BA29)<>"NO DENIAL"),"Denial Code, ","")&IF(AND(TRIM($A29)<>"Finalized",$BD29=""),"Next Review Date, ","")&IF(AND(TRIM($A29)<>"Finalized",$BE29=""),"Next Step, ","")&IF(AND(TRIM($A29)="Finalized",$AV29="",$AR29="",$AT29="",$AX29="",$AW29=""),"CPT outcome, ",""),LEN(IF($B29="","Notes, ","")&IF($K29="","Latest Date Worked, ","")&IF($AY29="","Last Action, ","")&IF(AND(OR(TRIM($A29)="Denied",TRIM($A29)="Rejected"),$BA29=""),"Denial Reason, ","")&IF(AND(TRIM($A29)="Denied",$BB29="",TRIM($BA29)<>"NO DENIAL"),"Denial Code, ","")&IF(AND(TRIM($A29)<>"Finalized",$BD29=""),"Next Review Date, ","")&IF(AND(TRIM($A29)<>"Finalized",$BE29=""),"Next Step, ","")&IF(AND(TRIM($A29)="Finalized",$AV29="",$AR29="",$AT29="",$AX29="",$AW29=""),"CPT outcome, ",""))-2),"") -> Denial Code, Next Step | BI29: =IF($BB29="","",IFERROR(INDEX('Denial Codes'!$C:$C,MATCH(LEFT($BB29,FIND(" - ",$BB29&" - ")+2)&"*",'Denial Codes'!$A:$A,0)),"")) | BJ29: =IF($BA29="","",IFERROR(INDEX(Lists!$B:$B,MATCH(TRIM($BA29),Lists!$A:$A,0))&"","")) -> Verify the place of service (inpatient/outpatient) and correct the claim.
A30: Denied | B30: No waiver for 63047 - Recon BOT3951067 sent with MR: A0 Carrum exclusion lists fusion; 63047 is decompression, no fusion billed. Asked to reprocess or to provide denial the plan language | C30: 545934422 | D30: 46112 | E30: HF533641085 | F30: 46031 | G30: CIGNA | H30: CIGNA | I30: No Payer | J30: 63047 x1 | K30: 46305 | L30: =IF($O30="","",$O30-TODAY()) -> -190 | M30: =IF(AND(TRIM($A30)="Finalized",$K30<>""),"",IF($F30="","",$F30+90-TODAY())) -> -190 | N30: =IF(AND(TRIM($A30)="Finalized",$K30<>""),"",IF($D30="","",$D30+180-TODAY())) -> -19 | O30: =IF(AND(TRIM($A30)="Finalized",$K30<>""),"",DATE(2026,4,9)) -> 46121 | P30: 90 days | Q30: CIGNA / CIGNA MEDICARE | R30: 90 days | S30: Date of service | T30: 180 days | U30: Processed date | V30: 2026-01 January | W30: ORTHO | AA30: 1 | AB30: =IF($F30="","",TODAY()-$F30) -> 280 | AC30: 63047 | AJ30: M48062 | AO30: O'NEIL, ROY | AP30: ASAP Surgery Centers North Valley LLC | AQ30: 46037 | AX30: 63047 | AY30: Recon filed | BA30: Wrong payer / vendor | BC30: Recon # BOT3951067 | BD30: 46336 | BF30: =IF(TRIM($A30)="Finalized","Closed",IF($BD30="","No review date set",IF($BD30<TODAY(),"OVERDUE",IF($BD30-TODAY()<=7,"Due within 7 days","Scheduled")))) -> Scheduled | BG30: =IF($K30="","",TODAY()-$K30) -> 6 | BH30: =IFERROR(LEFT(IF($B30="","Notes, ","")&IF($K30="","Latest Date Worked, ","")&IF($AY30="","Last Action, ","")&IF(AND(OR(TRIM($A30)="Denied",TRIM($A30)="Rejected"),$BA30=""),"Denial Reason, ","")&IF(AND(TRIM($A30)="Denied",$BB30="",TRIM($BA30)<>"NO DENIAL"),"Denial Code, ","")&IF(AND(TRIM($A30)<>"Finalized",$BD30=""),"Next Review Date, ","")&IF(AND(TRIM($A30)<>"Finalized",$BE30=""),"Next Step, ","")&IF(AND(TRIM($A30)="Finalized",$AV30="",$AR30="",$AT30="",$AX30="",$AW30=""),"CPT outcome, ",""),LEN(IF($B30="","Notes, ","")&IF($K30="","Latest Date Worked, ","")&IF($AY30="","Last Action, ","")&IF(AND(OR(TRIM($A30)="Denied",TRIM($A30)="Rejected"),$BA30=""),"Denial Reason, ","")&IF(AND(TRIM($A30)="Denied",$BB30="",TRIM($BA30)<>"NO DENIAL"),"Denial Code, ","")&IF(AND(TRIM($A30)<>"Finalized",$BD30=""),"Next Review Date, ","")&IF(AND(TRIM($A30)<>"Finalized",$BE30=""),"Next Step, ","")&IF(AND(TRIM($A30)="Finalized",$AV30="",$AR30="",$AT30="",$AX30="",$AW30=""),"CPT outcome, ",""))-2),"") -> Denial Code, Next Step | BI30: =IF($BB30="","",IFERROR(INDEX('Denial Codes'!$C:$C,MATCH(LEFT($BB30,FIND(" - ",$BB30&" - ")+2)&"*",'Denial Codes'!$A:$A,0)),"")) | BJ30: =IF($BA30="","",IFERROR(INDEX(Lists!$B:$B,MATCH(TRIM($BA30),Lists!$A:$A,0))&"","")) -> Bill the correct payer, delegated vendor or capitated group/IPA (e.g. Optum Behavioral, Preferred Homecare).
A31: Finalized | B31: PAID | C31: 545934840 | D31: 46156 | E31: HF456567442 | F31: 46031 | G31: UnitedHealthcare Community Plan / Arizona Long Term Care | H31: United Healthcare | I31: UnitedHealthcare Community Plan / Arizona Long Term Care | J31: 63685 x1 | K31: 46134 | L31: =IF($O31="","",$O31-TODAY()) | M31: =IF(AND(TRIM($A31)="Finalized",$K31<>""),"",IF($D31="","",$D31+180-TODAY())) | N31: =IF(AND(TRIM($A31)="Finalized",$K31<>""),"",IF($D31="","",$D31+365-TODAY())) | O31: =IF(AND(TRIM($A31)="Finalized",$K31<>""),"",DATE(2026,4,9)) | P31: 90 days | Q31: UHC COMMERCIAL | R31: 180 days | S31: Processed date | T31: 365 days | U31: Processed date | V31: 2026-01 January | W31: ORTHO | AA31: 1 | AB31: =IF($F31="","",TODAY()-$F31) -> 280 | AC31: 63685 | AJ31: G90523 | AN31: 556916920 | AO31: O'NEIL, ROY | AP31: ASAP Surgery Centers North Valley LLC | AQ31: 46037 | AV31: 63685 | AY31: Payment posted | BF31: =IF(TRIM($A31)="Finalized","Closed",IF($BD31="","No review date set",IF($BD31<TODAY(),"OVERDUE",IF($BD31-TODAY()<=7,"Due within 7 days","Scheduled")))) -> Closed | BG31: =IF($K31="","",TODAY()-$K31) -> 177 | BH31: =IFERROR(LEFT(IF($B31="","Notes, ","")&IF($K31="","Latest Date Worked, ","")&IF($AY31="","Last Action, ","")&IF(AND(OR(TRIM($A31)="Denied",TRIM($A31)="Rejected"),$BA31=""),"Denial Reason, ","")&IF(AND(TRIM($A31)="Denied",$BB31="",TRIM($BA31)<>"NO DENIAL"),"Denial Code, ","")&IF(AND(TRIM($A31)<>"Finalized",$BD31=""),"Next Review Date, ","")&IF(AND(TRIM($A31)<>"Finalized",$BE31=""),"Next Step, ","")&IF(AND(TRIM($A31)="Finalized",$AV31="",$AR31="",$AT31="",$AX31="",$AW31=""),"CPT outcome, ",""),LEN(IF($B31="","Notes, ","")&IF($K31="","Latest Date Worked, ","")&IF($AY31="","Last Action, ","")&IF(AND(OR(TRIM($A31)="Denied",TRIM($A31)="Rejected"),$BA31=""),"Denial Reason, ","")&IF(AND(TRIM($A31)="Denied",$BB31="",TRIM($BA31)<>"NO DENIAL"),"Denial Code, ","")&IF(AND(TRIM($A31)<>"Finalized",$BD31=""),"Next Review Date, ","")&IF(AND(TRIM($A31)<>"Finalized",$BE31=""),"Next Step, ","")&IF(AND(TRIM($A31)="Finalized",$AV31="",$AR31="",$AT31="",$AX31="",$AW31=""),"CPT outcome, ",""))-2),"") | BI31: =IF($BB31="","",IFERROR(INDEX('Denial Codes'!$C:$C,MATCH(LEFT($BB31,FIND(" - ",$BB31&" - ")+2)&"*",'Denial Codes'!$A:$A,0)),"")) | BJ31: =IF($BA31="","",IFERROR(INDEX(Lists!$B:$B,MATCH(TRIM($BA31),Lists!$A:$A,0))&"",""))
A32: PAID | B32: OP | C32: 548717876 | D32: 46069 | E32: HF442148430 | F32: 46035 | G32: Cigna Medicare Advantage | H32: Cigna Medicare Advantage | I32: No Payer | J32: 93925 x1 | K32: 46079 | L32: =IF($O32="","",$O32-TODAY()) -> -186 | M32: =IF(AND(TRIM($A32)="Finalized",$K32<>""),"",IF($F32="","",$F32+90-TODAY())) -> -186 | N32: =IF(AND(TRIM($A32)="Finalized",$K32<>""),"",IF($D32="","",$D32+180-TODAY())) -> -62 | O32: =IF(AND(TRIM($A32)="Finalized",$K32<>""),"",DATE(2026,4,13)) -> 46125 | P32: 90 days | Q32: CIGNA / CIGNA MEDICARE | R32: 90 days | S32: Date of service | T32: 180 days | U32: Processed date | V32: 2026-01 January | W32: US | AA32: 1 | AB32: =IF($F32="","",TODAY()-$F32) -> 276 | AC32: 93925 | AJ32: I739 | AO32: LEATHEM, JARRETT | AP32: ASAP - Gilbert | AQ32: 46051 | AV32: 93925 | AX32: 93925 | BD32: 46107 | BE32: Void original claim 547855520 (overpayment) | BF32: =IF(TRIM($A32)="Finalized","Closed",IF($BD32="","No review date set",IF($BD32<TODAY(),"OVERDUE",IF($BD32-TODAY()<=7,"Due within 7 days","Scheduled")))) -> OVERDUE | BG32: =IF($K32="","",TODAY()-$K32) -> 232 | BH32: =IFERROR(LEFT(IF($B32="","Notes, ","")&IF($K32="","Latest Date Worked, ","")&IF($AY32="","Last Action, ","")&IF(AND(OR(TRIM($A32)="Denied",TRIM($A32)="Rejected"),$BA32=""),"Denial Reason, ","")&IF(AND(TRIM($A32)="Denied",$BB32="",TRIM($BA32)<>"NO DENIAL"),"Denial Code, ","")&IF(AND(TRIM($A32)<>"Finalized",$BD32=""),"Next Review Date, ","")&IF(AND(TRIM($A32)<>"Finalized",$BE32=""),"Next Step, ","")&IF(AND(TRIM($A32)="Finalized",$AV32="",$AR32="",$AT32="",$AX32="",$AW32=""),"CPT outcome, ",""),LEN(IF($B32="","Notes, ","")&IF($K32="","Latest Date Worked, ","")&IF($AY32="","Last Action, ","")&IF(AND(OR(TRIM($A32)="Denied",TRIM($A32)="Rejected"),$BA32=""),"Denial Reason, ","")&IF(AND(TRIM($A32)="Denied",$BB32="",TRIM($BA32)<>"NO DENIAL"),"Denial Code, ","")&IF(AND(TRIM($A32)<>"Finalized",$BD32=""),"Next Review Date, ","")&IF(AND(TRIM($A32)<>"Finalized",$BE32=""),"Next Step, ","")&IF(AND(TRIM($A32)="Finalized",$AV32="",$AR32="",$AT32="",$AX32="",$AW32=""),"CPT outcome, ",""))-2),"") -> Last Action | BI32: =IF($BB32="","",IFERROR(INDEX('Denial Codes'!$C:$C,MATCH(LEFT($BB32,FIND(" - ",$BB32&" - ")+2)&"*",'Denial Codes'!$A:$A,0)),"")) | BJ32: =IF($BA32="","",IFERROR(INDEX(Lists!$B:$B,MATCH(TRIM($BA32),Lists!$A:$A,0))&"",""))
A33: Denied | B33: Added Date of Current Illness, claim note, and resubmitted | C33: 556348109 | D33: 46133 | E33: HF434792716 | F33: 46036 | G33: Optum Care Medical Network of Arizona, Utah, & Washington (LifePrint) | H33: Optum Care Medical Network of Arizona, Utah, & Washington (LifePrint) | I33: No Payer | J33: 99493 x1 | K33: 46129 | L33: =IF($O33="","",$O33-TODAY()) -> -185 | M33: =IF(AND(TRIM($A33)="Finalized",$K33<>""),"",IF($D33="","",$D33+365-TODAY())) -> 187 | N33: =IF(AND(TRIM($A33)="Finalized",$K33<>""),"",IF($D33="","",$D33+365-TODAY())) -> 187 | O33: =IF(AND(TRIM($A33)="Finalized",$K33<>""),"",DATE(2026,4,14)) -> 46126 | P33: 90 days | Q33: OPTUM | R33: 365 days | S33: Processed date | T33: 365 days | U33: Processed date | V33: 2026-01 January | W33: BH | AA33: 1 | AB33: =IF($F33="","",TODAY()-$F33) -> 275 | AC33: 99493 | AJ33: F1190 | AO33: LEATHEM, JARRETT | AP33: ASAP - Gilbert | AQ33: 46057 | AY33: Resubmitted | BA33: Coding / billing error | BB33: OA_246 - This non-payable code is for required reporting only | BD33: 46159 | BF33: =IF(TRIM($A33)="Finalized","Closed",IF($BD33="","No review date set",IF($BD33<TODAY(),"OVERDUE",IF($BD33-TODAY()<=7,"Due within 7 days","Scheduled")))) -> OVERDUE | BG33: =IF($K33="","",TODAY()-$K33) -> 182 | BH33: =IFERROR(LEFT(IF($B33="","Notes, ","")&IF($K33="","Latest Date Worked, ","")&IF($AY33="","Last Action, ","")&IF(AND(OR(TRIM($A33)="Denied",TRIM($A33)="Rejected"),$BA33=""),"Denial Reason, ","")&IF(AND(TRIM($A33)="Denied",$BB33="",TRIM($BA33)<>"NO DENIAL"),"Denial Code, ","")&IF(AND(TRIM($A33)<>"Finalized",$BD33=""),"Next Review Date, ","")&IF(AND(TRIM($A33)<>"Finalized",$BE33=""),"Next Step, ","")&IF(AND(TRIM($A33)="Finalized",$AV33="",$AR33="",$AT33="",$AX33="",$AW33=""),"CPT outcome, ",""),LEN(IF($B33="","Notes, ","")&IF($K33="","Latest Date Worked, ","")&IF($AY33="","Last Action, ","")&IF(AND(OR(TRIM($A33)="Denied",TRIM($A33)="Rejected"),$BA33=""),"Denial Reason, ","")&IF(AND(TRIM($A33)="Denied",$BB33="",TRIM($BA33)<>"NO DENIAL"),"Denial Code, ","")&IF(AND(TRIM($A33)<>"Finalized",$BD33=""),"Next Review Date, ","")&IF(AND(TRIM($A33)<>"Finalized",$BE33=""),"Next Step, ","")&IF(AND(TRIM($A33)="Finalized",$AV33="",$AR33="",$AT33="",$AX33="",$AW33=""),"CPT outcome, ",""))-2),"") -> Next Step | BI33: =IF($BB33="","",IFERROR(INDEX('Denial Codes'!$C:$C,MATCH(LEFT($BB33,FIND(" - ",$BB33&" - ")+2)&"*",'Denial Codes'!$A:$A,0)),"")) -> Coding / billing error | BJ33: =IF($BA33="","",IFERROR(INDEX(Lists!$B:$B,MATCH(TRIM($BA33),Lists!$A:$A,0))&"","")) -> Fix the code, units, charge or other claim data and resubmit as a corrected claim.
A34: Denied | B34: Prof claim, no rev code needed. Recon sent w/ duplex report - Uploaded MR | C34: 547465291 | D34: 46163 | E34: HF526889546 | F34: 46037 | G34: United Healthcare | H34: United Healthcare | I34: No Payer | J34: 93970 x1 | K34: 46305 | L34: =IF($O34="","",$O34-TODAY()) -> -184 | M34: =IF(AND(TRIM($A34)="Finalized",$K34<>""),"",IF($D34="","",$D34+180-TODAY())) -> 32 | N34: =IF(AND(TRIM($A34)="Finalized",$K34<>""),"",IF($D34="","",$D34+365-TODAY())) -> 217 | O34: =IF(AND(TRIM($A34)="Finalized",$K34<>""),"",DATE(2026,4,15)) -> 46127 | P34: 90 days | Q34: UHC COMMERCIAL | R34: 180 days | S34: Processed date | T34: 365 days | U34: Processed date | V34: 2026-01 January | W34: US | AA34: 1 | AB34: =IF($F34="","",TODAY()-$F34) -> 274 | AC34: 93970 | AJ34: R600 | AK34: M5416 | AO34: TURLEY, TODD | AP34: ASAP - DEER VALLEY | AQ34: 46048 | AY34: Recon filed | AZ34: Uploaded MR | BA34: Coding / billing error | BB34: M50 - Missing/incomplete/invalid revenue code(s) | BC34: PIQ-92451354; PIQ-83025067 | BD34: 46336 | BF34: =IF(TRIM($A34)="Finalized","Closed",IF($BD34="","No review date set",IF($BD34<TODAY(),"OVERDUE",IF($BD34-TODAY()<=7,"Due within 7 days","Scheduled")))) -> Scheduled | BG34: =IF($K34="","",TODAY()-$K34) -> 6 | BH34: =IFERROR(LEFT(IF($B34="","Notes, ","")&IF($K34="","Latest Date Worked, ","")&IF($AY34="","Last Action, ","")&IF(AND(OR(TRIM($A34)="Denied",TRIM($A34)="Rejected"),$BA34=""),"Denial Reason, ","")&IF(AND(TRIM($A34)="Denied",$BB34="",TRIM($BA34)<>"NO DENIAL"),"Denial Code, ","")&IF(AND(TRIM($A34)<>"Finalized",$BD34=""),"Next Review Date, ","")&IF(AND(TRIM($A34)<>"Finalized",$BE34=""),"Next Step, ","")&IF(AND(TRIM($A34)="Finalized",$AV34="",$AR34="",$AT34="",$AX34="",$AW34=""),"CPT outcome, ",""),LEN(IF($B34="","Notes, ","")&IF($K34="","Latest Date Worked, ","")&IF($AY34="","Last Action, ","")&IF(AND(OR(TRIM($A34)="Denied",TRIM($A34)="Rejected"),$BA34=""),"Denial Reason, ","")&IF(AND(TRIM($A34)="Denied",$BB34="",TRIM($BA34)<>"NO DENIAL"),"Denial Code, ","")&IF(AND(TRIM($A34)<>"Finalized",$BD34=""),"Next Review Date, ","")&IF(AND(TRIM($A34)<>"Finalized",$BE34=""),"Next Step, ","")&IF(AND(TRIM($A34)="Finalized",$AV34="",$AR34="",$AT34="",$AX34="",$AW34=""),"CPT outcome, ",""))-2),"") -> Next Step | BI34: =IF($BB34="","",IFERROR(INDEX('Denial Codes'!$C:$C,MATCH(LEFT($BB34,FIND(" - ",$BB34&" - ")+2)&"*",'Denial Codes'!$A:$A,0)),"")) -> Coding / billing error | BJ34: =IF($BA34="","",IFERROR(INDEX(Lists!$B:$B,MATCH(TRIM($BA34),Lists!$A:$A,0))&"","")) -> Fix the code, units, charge or other claim data and resubmit as a corrected claim.
A35: Denied | B35: TAT 15 days - Rep Muthamma | C35: 548015539 | D35: 46064 | E35: HF537685966 | F35: 46043 | G35: Blue Cross Blue Shield of Arizona (BCBS AZ) | H35: Blue Cross Blue Shield of Arizona (BCBS AZ) | I35: Medicare Part B Arizona * | J35: 99494 x1; 99492 x1 | K35: 46134 | L35: =IF($O35="","",$O35-TODAY()) -> -178 | M35: =IF(AND(TRIM($A35)="Finalized",$K35<>""),"",IF($F35="","",$F35+90-TODAY())) -> -178 | N35: =IF(AND(TRIM($A35)="Finalized",$K35<>""),"",IF($D35="","",$D35+365-TODAY())) -> 118 | O35: =IF(AND(TRIM($A35)="Finalized",$K35<>""),"",DATE(2026,4,21)) -> 46133 | P35: 90 days | Q35: BCBS | R35: 90 days | S35: Date of service | T35: 365 days | U35: Processed date | V35: 2026-01 January | W35: BH | AA35: 1 | AB35: =IF($F35="","",TODAY()-$F35) -> 268 | AC35: 99494 | AD35: 99492 | AJ35: F330 | AO35: LEATHEM, JARRETT | AP35: ASAP - Gilbert | AQ35: 46057 | AY35: Contacted payer | BC35: Call ref # 10605826 | BD35: 46164 | BF35: =IF(TRIM($A35)="Finalized","Closed",IF($BD35="","No review date set",IF($BD35<TODAY(),"OVERDUE",IF($BD35-TODAY()<=7,"Due within 7 days","Scheduled")))) -> OVERDUE | BG35: =IF($K35="","",TODAY()-$K35) -> 177 | BH35: =IFERROR(LEFT(IF($B35="","Notes, ","")&IF($K35="","Latest Date Worked, ","")&IF($AY35="","Last Action, ","")&IF(AND(OR(TRIM($A35)="Denied",TRIM($A35)="Rejected"),$BA35=""),"Denial Reason, ","")&IF(AND(TRIM($A35)="Denied",$BB35="",TRIM($BA35)<>"NO DENIAL"),"Denial Code, ","")&IF(AND(TRIM($A35)<>"Finalized",$BD35=""),"Next Review Date, ","")&IF(AND(TRIM($A35)<>"Finalized",$BE35=""),"Next Step, ","")&IF(AND(TRIM($A35)="Finalized",$AV35="",$AR35="",$AT35="",$AX35="",$AW35=""),"CPT outcome, ",""),LEN(IF($B35="","Notes, ","")&IF($K35="","Latest Date Worked, ","")&IF($AY35="","Last Action, ","")&IF(AND(OR(TRIM($A35)="Denied",TRIM($A35)="Rejected"),$BA35=""),"Denial Reason, ","")&IF(AND(TRIM($A35)="Denied",$BB35="",TRIM($BA35)<>"NO DENIAL"),"Denial Code, ","")&IF(AND(TRIM($A35)<>"Finalized",$BD35=""),"Next Review Date, ","")&IF(AND(TRIM($A35)<>"Finalized",$BE35=""),"Next Step, ","")&IF(AND(TRIM($A35)="Finalized",$AV35="",$AR35="",$AT35="",$AX35="",$AW35=""),"CPT outcome, ",""))-2),"") -> Denial Reason, Denial Code, Next Step | BI35: =IF($BB35="","",IFERROR(INDEX('Denial Codes'!$C:$C,MATCH(LEFT($BB35,FIND(" - ",$BB35&" - ")+2)&"*",'Denial Codes'!$A:$A,0)),"")) | BJ35: =IF($BA35="","",IFERROR(INDEX(Lists!$B:$B,MATCH(TRIM($BA35),Lists!$A:$A,0))&"",""))
A36: Pending | B36: secondary - Resubmitted to AmeTrust | C36: 547442681 | D36: 46094 | E36: HF359780591 | F36: 46044 | G36: TRIADA GAP BENEFITS | H36: Blue Cross Blue Shield of Arizona (BCBS AZ) | I36: TRIADA GAP BENEFITS | J36: 99493 x1 | K36: 46304 | L36: =IF($O36="","",$O36-TODAY()) -> -177 | M36: =IF(AND(TRIM($A36)="Finalized",$K36<>""),"",IF($F36="","",$F36+90-TODAY())) -> -177 | N36: =IF(AND(TRIM($A36)="Finalized",$K36<>""),"",IF($D36="","",$D36+365-TODAY())) -> 148 | O36: =IF(AND(TRIM($A36)="Finalized",$K36<>""),"",DATE(2026,4,22)) -> 46134 | P36: 90 days | Q36: BCBS | R36: 90 days | S36: Date of service | T36: 365 days | U36: Processed date | V36: 2026-01 January | W36: BH | AA36: 1 | AB36: =IF($F36="","",TODAY()-$F36) -> 267 | AC36: 99493 | AJ36: F411 | AN36: 556556161 | AO36: LEATHEM, JARRETT | AP36: ASAP - DEER VALLEY | AQ36: 46056 | AW36: 99493 | AX36: 99493 | AY36: Resubmitted | BB36: CO_45 - Charge exceeds fee schedule/maximum allowable or contracted/legislated fee arrangement | BD36: 46335 | BF36: =IF(TRIM($A36)="Finalized","Closed",IF($BD36="","No review date set",IF($BD36<TODAY(),"OVERDUE",IF($BD36-TODAY()<=7,"Due within 7 days","Scheduled")))) -> Scheduled | BG36: =IF($K36="","",TODAY()-$K36) -> 7 | BH36: =IFERROR(LEFT(IF($B36="","Notes, ","")&IF($K36="","Latest Date Worked, ","")&IF($AY36="","Last Action, ","")&IF(AND(OR(TRIM($A36)="Denied",TRIM($A36)="Rejected"),$BA36=""),"Denial Reason, ","")&IF(AND(TRIM($A36)="Denied",$BB36="",TRIM($BA36)<>"NO DENIAL"),"Denial Code, ","")&IF(AND(TRIM($A36)<>"Finalized",$BD36=""),"Next Review Date, ","")&IF(AND(TRIM($A36)<>"Finalized",$BE36=""),"Next Step, ","")&IF(AND(TRIM($A36)="Finalized",$AV36="",$AR36="",$AT36="",$AX36="",$AW36=""),"CPT outcome, ",""),LEN(IF($B36="","Notes, ","")&IF($K36="","Latest Date Worked, ","")&IF($AY36="","Last Action, ","")&IF(AND(OR(TRIM($A36)="Denied",TRIM($A36)="Rejected"),$BA36=""),"Denial Reason, ","")&IF(AND(TRIM($A36)="Denied",$BB36="",TRIM($BA36)<>"NO DENIAL"),"Denial Code, ","")&IF(AND(TRIM($A36)<>"Finalized",$BD36=""),"Next Review Date, ","")&IF(AND(TRIM($A36)<>"Finalized",$BE36=""),"Next Step, ","")&IF(AND(TRIM($A36)="Finalized",$AV36="",$AR36="",$AT36="",$AX36="",$AW36=""),"CPT outcome, ",""))-2),"") -> Next Step | BI36: =IF($BB36="","",IFERROR(INDEX('Denial Codes'!$C:$C,MATCH(LEFT($BB36,FIND(" - ",$BB36&" - ")+2)&"*",'Denial Codes'!$A:$A,0)),"")) -> Other | BJ36: =IF($BA36="","",IFERROR(INDEX(Lists!$B:$B,MATCH(TRIM($BA36),Lists!$A:$A,0))&"",""))
A37: Under Review | B37: Handled by Deanne - Rep Heather AZ BCBS - Per the provider's contractual agreement, the allowed amount is $0.00, the contractual adjustment reflects the difference between the billed charges and the non covered/denied allowed amount, rather than a payable allowance - Case #10628911 - Rep Mage E - Ins canceled appeal, claim was forwarded to Anthem with zero price and no allowed amount - Pricing issue with local plan - Filed appeal - Request APP-COMM-6695304 | C37: 547576017 | D37: 46052 | E37: HF524606724 | F37: 46045 | G37: Blue Cross Blue Shield of Arizona (BCBS AZ) | H37: Blue Cross Blue Shield of Arizona (BCBS AZ) | I37: No Payer | J37: 63047 x1 | K37: 46247 | L37: =IF($O37="","",$O37-TODAY()) -> -176 | M37: =IF(AND(TRIM($A37)="Finalized",$K37<>""),"",IF($F37="","",$F37+90-TODAY())) -> -176 | N37: =IF(AND(TRIM($A37)="Finalized",$K37<>""),"",IF($D37="","",$D37+365-TODAY())) -> 106 | O37: =IF(AND(TRIM($A37)="Finalized",$K37<>""),"",DATE(2026,4,23)) -> 46135 | P37: 90 days | Q37: BCBS | R37: 90 days | S37: Date of service | T37: 365 days | U37: Processed date | V37: 2026-01 January | W37: ORTHO | AA37: 1 | AB37: =IF($F37="","",TODAY()-$F37) -> 266 | AC37: 63047 | AJ37: M48062 | AO37: O'NEIL, ROY | AP37: ASAP Surgery Centers North Valley LLC | AQ37: 46049 | AY37: Contacted payer | AZ37: Contacted payer; Appeal filed | BA37: Other | BC37: Case # 10628911; Call ref # I-55636628; Appeal APP-COMM-6695304 | BD37: 46278 | BF37: =IF(TRIM($A37)="Finalized","Closed",IF($BD37="","No review date set",IF($BD37<TODAY(),"OVERDUE",IF($BD37-TODAY()<=7,"Due within 7 days","Scheduled")))) -> OVERDUE | BG37: =IF($K37="","",TODAY()-$K37) -> 64 | BH37: =IFERROR(LEFT(IF($B37="","Notes, ","")&IF($K37="","Latest Date Worked, ","")&IF($AY37="","Last Action, ","")&IF(AND(OR(TRIM($A37)="Denied",TRIM($A37)="Rejected"),$BA37=""),"Denial Reason, ","")&IF(AND(TRIM($A37)="Denied",$BB37="",TRIM($BA37)<>"NO DENIAL"),"Denial Code, ","")&IF(AND(TRIM($A37)<>"Finalized",$BD37=""),"Next Review Date, ","")&IF(AND(TRIM($A37)<>"Finalized",$BE37=""),"Next Step, ","")&IF(AND(TRIM($A37)="Finalized",$AV37="",$AR37="",$AT37="",$AX37="",$AW37=""),"CPT outcome, ",""),LEN(IF($B37="","Notes, ","")&IF($K37="","Latest Date Worked, ","")&IF($AY37="","Last Action, ","")&IF(AND(OR(TRIM($A37)="Denied",TRIM($A37)="Rejected"),$BA37=""),"Denial Reason, ","")&IF(AND(TRIM($A37)="Denied",$BB37="",TRIM($BA37)<>"NO DENIAL"),"Denial Code, ","")&IF(AND(TRIM($A37)<>"Finalized",$BD37=""),"Next Review Date, ","")&IF(AND(TRIM($A37)<>"Finalized",$BE37=""),"Next Step, ","")&IF(AND(TRIM($A37)="Finalized",$AV37="",$AR37="",$AT37="",$AX37="",$AW37=""),"CPT outcome, ",""))-2),"") -> Next Step | BI37: =IF($BB37="","",IFERROR(INDEX('Denial Codes'!$C:$C,MATCH(LEFT($BB37,FIND(" - ",$BB37&" - ")+2)&"*",'Denial Codes'!$A:$A,0)),"")) | BJ37: =IF($BA37="","",IFERROR(INDEX(Lists!$B:$B,MATCH(TRIM($BA37),Lists!$A:$A,0))&"",""))
A38: Pending | B38: secondary - Edited charges for A6219, and resubmitted | C38: 557162806 | D38: 46156 | E38: HF518924824 | F38: 46041 | G38: Mercy Care Plan (AHCCCS) - Complete Care & Long Term Care (LTC) | H38: Allwell - All States (Centene) | I38: Mercy Care Plan (AHCCCS) - Complete Care & Long Term Care (LTC) | J38: A6023+A2 x10 | K38: 46136 | L38: =IF($O38="","",$O38-TODAY()) -> -175 | M38: =IF(AND(TRIM($A38)="Finalized",$K38<>""),"",IF($D38="","",$D38+90-TODAY())) -> -65 | N38: =IF(AND(TRIM($A38)="Finalized",$K38<>""),"",IF($D38="","",$D38+90-TODAY())) -> -65 | O38: =IF(AND(TRIM($A38)="Finalized",$K38<>""),"",DATE(2026,4,24)) -> 46136 | P38: 95 days | Q38: WELLCARE BY ALLWELL | R38: 90 days | S38: Processed date | T38: 90 days | U38: Processed date | V38: 2026-01 January | W38: DME | X38: A2 | AA38: 10 | AB38: =IF($F38="","",TODAY()-$F38) -> 270 | AC38: A6023 | AJ38: G894 | AK38: M961 | AL38: M5416 | AN38: 551367817 | AO38: KALLGREN, MARK | AP38: ASAP - Mesa | AQ38: 46063 | AV38: A6023 | AX38: A6219, A6023 | AY38: Resubmitted | BA38: Coding / billing error | BD38: 46166 | BE38: Cross over claim to secondary | BF38: =IF(TRIM($A38)="Finalized","Closed",IF($BD38="","No review date set",IF($BD38<TODAY(),"OVERDUE",IF($BD38-TODAY()<=7,"Due within 7 days","Scheduled")))) -> OVERDUE | BG38: =IF($K38="","",TODAY()-$K38) -> 175 | BH38: =IFERROR(LEFT(IF($B38="","Notes, ","")&IF($K38="","Latest Date Worked, ","")&IF($AY38="","Last Action, ","")&IF(AND(OR(TRIM($A38)="Denied",TRIM($A38)="Rejected"),$BA38=""),"Denial Reason, ","")&IF(AND(TRIM($A38)="Denied",$BB38="",TRIM($BA38)<>"NO DENIAL"),"Denial Code, ","")&IF(AND(TRIM($A38)<>"Finalized",$BD38=""),"Next Review Date, ","")&IF(AND(TRIM($A38)<>"Finalized",$BE38=""),"Next Step, ","")&IF(AND(TRIM($A38)="Finalized",$AV38="",$AR38="",$AT38="",$AX38="",$AW38=""),"CPT outcome, ",""),LEN(IF($B38="","Notes, ","")&IF($K38="","Latest Date Worked, ","")&IF($AY38="","Last Action, ","")&IF(AND(OR(TRIM($A38)="Denied",TRIM($A38)="Rejected"),$BA38=""),"Denial Reason, ","")&IF(AND(TRIM($A38)="Denied",$BB38="",TRIM($BA38)<>"NO DENIAL"),"Denial Code, ","")&IF(AND(TRIM($A38)<>"Finalized",$BD38=""),"Next Review Date, ","")&IF(AND(TRIM($A38)<>"Finalized",$BE38=""),"Next Step, ","")&IF(AND(TRIM($A38)="Finalized",$AV38="",$AR38="",$AT38="",$AX38="",$AW38=""),"CPT outcome, ",""))-2),"") | BI38: =IF($BB38="","",IFERROR(INDEX('Denial Codes'!$C:$C,MATCH(LEFT($BB38,FIND(" - ",$BB38&" - ")+2)&"*",'Denial Codes'!$A:$A,0)),"")) | BJ38: =IF($BA38="","",IFERROR(INDEX(Lists!$B:$B,MATCH(TRIM($BA38),Lists!$A:$A,0))&"","")) -> Fix the code, units, charge or other claim data and resubmit as a corrected claim.
A39: Received | B39: Resubmitted - no changes | C39: 555599776 | D39: 46128 | E39: HF475536429 | F39: 46049 | G39: Blue Cross Blue Shield of Arizona (BCBS AZ) | H39: Blue Cross Blue Shield of Arizona (BCBS AZ) | I39: No Payer | J39: 99492 x1; 99494 x1 | K39: 46122 | L39: =IF($O39="","",$O39-TODAY()) -> -172 | M39: =IF(AND(TRIM($A39)="Finalized",$K39<>""),"",IF($F39="","",$F39+90-TODAY())) -> -172 | N39: =IF(AND(TRIM($A39)="Finalized",$K39<>""),"",IF($D39="","",$D39+365-TODAY())) -> 182 | O39: =IF(AND(TRIM($A39)="Finalized",$K39<>""),"",DATE(2026,4,27)) -> 46139 | P39: 90 days | Q39: BCBS | R39: 90 days | S39: Date of service | T39: 365 days | U39: Processed date | V39: 2026-01 January | W39: BH | AA39: 1 | AB39: =IF($F39="","",TODAY()-$F39) -> 262 | AC39: 99492 | AD39: 99494 | AJ39: F4320 | AO39: O'NEIL, ROY | AP39: ASAP Peoria | AQ39: 46057 | AY39: Resubmitted | BD39: 46152 | BF39: =IF(TRIM($A39)="Finalized","Closed",IF($BD39="","No review date set",IF($BD39<TODAY(),"OVERDUE",IF($BD39-TODAY()<=7,"Due within 7 days","Scheduled")))) -> OVERDUE | BG39: =IF($K39="","",TODAY()-$K39) -> 189 | BH39: =IFERROR(LEFT(IF($B39="","Notes, ","")&IF($K39="","Latest Date Worked, ","")&IF($AY39="","Last Action, ","")&IF(AND(OR(TRIM($A39)="Denied",TRIM($A39)="Rejected"),$BA39=""),"Denial Reason, ","")&IF(AND(TRIM($A39)="Denied",$BB39="",TRIM($BA39)<>"NO DENIAL"),"Denial Code, ","")&IF(AND(TRIM($A39)<>"Finalized",$BD39=""),"Next Review Date, ","")&IF(AND(TRIM($A39)<>"Finalized",$BE39=""),"Next Step, ","")&IF(AND(TRIM($A39)="Finalized",$AV39="",$AR39="",$AT39="",$AX39="",$AW39=""),"CPT outcome, ",""),LEN(IF($B39="","Notes, ","")&IF($K39="","Latest Date Worked, ","")&IF($AY39="","Last Action, ","")&IF(AND(OR(TRIM($A39)="Denied",TRIM($A39)="Rejected"),$BA39=""),"Denial Reason, ","")&IF(AND(TRIM($A39)="Denied",$BB39="",TRIM($BA39)<>"NO DENIAL"),"Denial Code, ","")&IF(AND(TRIM($A39)<>"Finalized",$BD39=""),"Next Review Date, ","")&IF(AND(TRIM($A39)<>"Finalized",$BE39=""),"Next Step, ","")&IF(AND(TRIM($A39)="Finalized",$AV39="",$AR39="",$AT39="",$AX39="",$AW39=""),"CPT outcome, ",""))-2),"") -> Next Step | BI39: =IF($BB39="","",IFERROR(INDEX('Denial Codes'!$C:$C,MATCH(LEFT($BB39,FIND(" - ",$BB39&" - ")+2)&"*",'Denial Codes'!$A:$A,0)),"")) | BJ39: =IF($BA39="","",IFERROR(INDEX(Lists!$B:$B,MATCH(TRIM($BA39),Lists!$A:$A,0))&"",""))
A40: Denied | B40: Resubmitted with 99492 - Recon filed - Claim 26A635462200 DOS 01/27/26 99493 denied no prior CoCM 6mo. Prior 99493 DOS 12/16/25 paid clm 26A070631100 under old ID 2062477. Req reprocess; PRA attached - Added Date of Current Illness, claim note, and resubmitted | C40: 573875345 | D40: 46287 | E40: HF431164004 | F40: 46049 | G40: Optum Care Medical Network of Arizona, Utah, & Washington (LifePrint) | H40: Optum Care Medical Network of Arizona, Utah, & Washington (LifePrint) | I40: No Payer | J40: 99493 x1 | K40: 46300 | L40: =IF($O40="","",$O40-TODAY()) -> -172 | M40: =IF(AND(TRIM($A40)="Finalized",$K40<>""),"",IF($D40="","",$D40+365-TODAY())) -> 341 | N40: =IF(AND(TRIM($A40)="Finalized",$K40<>""),"",IF($D40="","",$D40+365-TODAY())) -> 341 | O40: =IF(AND(TRIM($A40)="Finalized",$K40<>""),"",DATE(2026,4,27)) -> 46139 | P40: 90 days | Q40: OPTUM | R40: 365 days | S40: Processed date | T40: 365 days | U40: Processed date | V40: 2026-01 January | W40: BH | AA40: 1 | AB40: =IF($F40="","",TODAY()-$F40) -> 262 | AC40: 99493 | AJ40: F331 | AK40: F411 | AO40: O'NEIL, ROY | AP40: ASAP - Goodyear | AQ40: 46056 | AX40: 99493, 99492 | AY40: Resubmitted | AZ40: Recon filed; Resubmitted | BA40: Coding / billing error | BB40: OA_246 - This non-payable code is for required reporting only | BC40: Request ID TT2647830 | BD40: 46331 | BF40: =IF(TRIM($A40)="Finalized","Closed",IF($BD40="","No review date set",IF($BD40<TODAY(),"OVERDUE",IF($BD40-TODAY()<=7,"Due within 7 days","Scheduled")))) -> Scheduled | BG40: =IF($K40="","",TODAY()-$K40) -> 11 | BH40: =IFERROR(LEFT(IF($B40="","Notes, ","")&IF($K40="","Latest Date Worked, ","")&IF($AY40="","Last Action, ","")&IF(AND(OR(TRIM($A40)="Denied",TRIM($A40)="Rejected"),$BA40=""),"Denial Reason, ","")&IF(AND(TRIM($A40)="Denied",$BB40="",TRIM($BA40)<>"NO DENIAL"),"Denial Code, ","")&IF(AND(TRIM($A40)<>"Finalized",$BD40=""),"Next Review Date, ","")&IF(AND(TRIM($A40)<>"Finalized",$BE40=""),"Next Step, ","")&IF(AND(TRIM($A40)="Finalized",$AV40="",$AR40="",$AT40="",$AX40="",$AW40=""),"CPT outcome, ",""),LEN(IF($B40="","Notes, ","")&IF($K40="","Latest Date Worked, ","")&IF($AY40="","Last Action, ","")&IF(AND(OR(TRIM($A40)="Denied",TRIM($A40)="Rejected"),$BA40=""),"Denial Reason, ","")&IF(AND(TRIM($A40)="Denied",$BB40="",TRIM($BA40)<>"NO DENIAL"),"Denial Code, ","")&IF(AND(TRIM($A40)<>"Finalized",$BD40=""),"Next Review Date, ","")&IF(AND(TRIM($A40)<>"Finalized",$BE40=""),"Next Step, ","")&IF(AND(TRIM($A40)="Finalized",$AV40="",$AR40="",$AT40="",$AX40="",$AW40=""),"CPT outcome, ",""))-2),"") -> Next Step | BI40: =IF($BB40="","",IFERROR(INDEX('Denial Codes'!$C:$C,MATCH(LEFT($BB40,FIND(" - ",$BB40&" - ")+2)&"*",'Denial Codes'!$A:$A,0)),"")) -> Coding / billing error | BJ40: =IF($BA40="","",IFERROR(INDEX(Lists!$B:$B,MATCH(TRIM($BA40),Lists!$A:$A,0))&"","")) -> Fix the code, units, charge or other claim data and resubmit as a corrected claim.
A41: Pending | B41: Not shifting - working on it Shifted to PR - Ins didn't receive PT update | C41: 547976909 | D41: 46066 | E41: HF535417942 | F41: 46051 | G41: Blue Cross Blue Shield of Arizona (BCBS AZ) | H41: Blue Cross Blue Shield of Arizona (BCBS AZ) | I41: LIEN 05 | J41: 99493 x1 | K41: 46245 | L41: =IF($O41="","",$O41-TODAY()) -> -170 | M41: =IF(AND(TRIM($A41)="Finalized",$K41<>""),"",IF($F41="","",$F41+90-TODAY())) -> -170 | N41: =IF(AND(TRIM($A41)="Finalized",$K41<>""),"",IF($D41="","",$D41+365-TODAY())) -> 120 | O41: =IF(AND(TRIM($A41)="Finalized",$K41<>""),"",DATE(2026,4,29)) -> 46141 | P41: 90 days | Q41: BCBS | R41: 90 days | S41: Date of service | T41: 365 days | U41: Processed date | V41: 2026-01 January | W41: BH | AA41: 1 | AB41: =IF($F41="","",TODAY()-$F41) -> 260 | AC41: 99493 | AJ41: F4323 | AO41: TURLEY, TODD | AP41: ASAP - DEER VALLEY | AQ41: 46056 | AZ41: Shifted to patient | BA41: Other insurance / COB | BD41: 46276 | BE41: Follow up: PT said she would update the COB questionnaire (IQ) with the insurance - then ask for reprocessing | BF41: =IF(TRIM($A41)="Finalized","Closed",IF($BD41="","No review date set",IF($BD41<TODAY(),"OVERDUE",IF($BD41-TODAY()<=7,"Due within 7 days","Scheduled")))) -> OVERDUE | BG41: =IF($K41="","",TODAY()-$K41) -> 66 | BH41: =IFERROR(LEFT(IF($B41="","Notes, ","")&IF($K41="","Latest Date Worked, ","")&IF($AY41="","Last Action, ","")&IF(AND(OR(TRIM($A41)="Denied",TRIM($A41)="Rejected"),$BA41=""),"Denial Reason, ","")&IF(AND(TRIM($A41)="Denied",$BB41="",TRIM($BA41)<>"NO DENIAL"),"Denial Code, ","")&IF(AND(TRIM($A41)<>"Finalized",$BD41=""),"Next Review Date, ","")&IF(AND(TRIM($A41)<>"Finalized",$BE41=""),"Next Step, ","")&IF(AND(TRIM($A41)="Finalized",$AV41="",$AR41="",$AT41="",$AX41="",$AW41=""),"CPT outcome, ",""),LEN(IF($B41="","Notes, ","")&IF($K41="","Latest Date Worked, ","")&IF($AY41="","Last Action, ","")&IF(AND(OR(TRIM($A41)="Denied",TRIM($A41)="Rejected"),$BA41=""),"Denial Reason, ","")&IF(AND(TRIM($A41)="Denied",$BB41="",TRIM($BA41)<>"NO DENIAL"),"Denial Code, ","")&IF(AND(TRIM($A41)<>"Finalized",$BD41=""),"Next Review Date, ","")&IF(AND(TRIM($A41)<>"Finalized",$BE41=""),"Next Step, ","")&IF(AND(TRIM($A41)="Finalized",$AV41="",$AR41="",$AT41="",$AX41="",$AW41=""),"CPT outcome, ",""))-2),"") -> Last Action | BI41: =IF($BB41="","",IFERROR(INDEX('Denial Codes'!$C:$C,MATCH(LEFT($BB41,FIND(" - ",$BB41&" - ")+2)&"*",'Denial Codes'!$A:$A,0)),"")) | BJ41: =IF($BA41="","",IFERROR(INDEX(Lists!$B:$B,MATCH(TRIM($BA41),Lists!$A:$A,0))&"","")) -> Get the other insurance and primary EOB, update COB with the payer and bill primary first.
A42: Denied | B42: Recon PIQ-92451492 - 93970 denial - Sent signed report showing bilateral compression/augmentation - Jess uploaded MR | C42: 548573158 | D42: 46156 | E42: HF537684538 | F42: 46051 | G42: United Healthcare | H42: United Healthcare | I42: No Payer | J42: 93970 x1 | K42: 46305 | L42: =IF($O42="","",$O42-TODAY()) -> -170 | M42: =IF(AND(TRIM($A42)="Finalized",$K42<>""),"",IF($D42="","",$D42+180-TODAY())) -> 25 | N42: =IF(AND(TRIM($A42)="Finalized",$K42<>""),"",IF($D42="","",$D42+365-TODAY())) -> 210 | O42: =IF(AND(TRIM($A42)="Finalized",$K42<>""),"",DATE(2026,4,29)) -> 46141 | P42: 90 days | Q42: UHC COMMERCIAL | R42: 180 days | S42: Processed date | T42: 365 days | U42: Processed date | V42: 2026-01 January | W42: US | AA42: 1 | AB42: =IF($F42="","",TODAY()-$F42) -> 260 | AC42: 93970 | AJ42: R600 | AK42: M79604 | AL42: M79605 | AO42: TURLEY, TODD | AP42: ASAP - DEER VALLEY | AQ42: 46058 | AX42: 93970 | AY42: Recon filed | AZ42: Uploaded MR | BA42: Medical necessity / frequency | BB42: CO_150 - Payer deems the information submitted does not support this level of service | BC42: PIQ-92451492 | BD42: 46336 | BF42: =IF(TRIM($A42)="Finalized","Closed",IF($BD42="","No review date set",IF($BD42<TODAY(),"OVERDUE",IF($BD42-TODAY()<=7,"Due within 7 days","Scheduled")))) -> Scheduled | BG42: =IF($K42="","",TODAY()-$K42) -> 6 | BH42: =IFERROR(LEFT(IF($B42="","Notes, ","")&IF($K42="","Latest Date Worked, ","")&IF($AY42="","Last Action, ","")&IF(AND(OR(TRIM($A42)="Denied",TRIM($A42)="Rejected"),$BA42=""),"Denial Reason, ","")&IF(AND(TRIM($A42)="Denied",$BB42="",TRIM($BA42)<>"NO DENIAL"),"Denial Code, ","")&IF(AND(TRIM($A42)<>"Finalized",$BD42=""),"Next Review Date, ","")&IF(AND(TRIM($A42)<>"Finalized",$BE42=""),"Next Step, ","")&IF(AND(TRIM($A42)="Finalized",$AV42="",$AR42="",$AT42="",$AX42="",$AW42=""),"CPT outcome, ",""),LEN(IF($B42="","Notes, ","")&IF($K42="","Latest Date Worked, ","")&IF($AY42="","Last Action, ","")&IF(AND(OR(TRIM($A42)="Denied",TRIM($A42)="Rejected"),$BA42=""),"Denial Reason, ","")&IF(AND(TRIM($A42)="Denied",$BB42="",TRIM($BA42)<>"NO DENIAL"),"Denial Code, ","")&IF(AND(TRIM($A42)<>"Finalized",$BD42=""),"Next Review Date, ","")&IF(AND(TRIM($A42)<>"Finalized",$BE42=""),"Next Step, ","")&IF(AND(TRIM($A42)="Finalized",$AV42="",$AR42="",$AT42="",$AX42="",$AW42=""),"CPT outcome, ",""))-2),"") -> Next Step | BI42: =IF($BB42="","",IFERROR(INDEX('Denial Codes'!$C:$C,MATCH(LEFT($BB42,FIND(" - ",$BB42&" - ")+2)&"*",'Denial Codes'!$A:$A,0)),"")) -> Medical necessity / frequency | BJ42: =IF($BA42="","",IFERROR(INDEX(Lists!$B:$B,MATCH(TRIM($BA42),Lists!$A:$A,0))&"","")) -> Appeal with medical records and a letter of medical necessity; check LCD/MUE limits.
A43: Denied | B43: Rep Briana - Jarrett Leathem is not contracted with member's Focus Network - Reference number 11216220 | C43: 548676737 | D43: 46098 | E43: HF499806568 | F43: 46056 | G43: Blue Cross Blue Shield of Arizona (BCBS AZ) | H43: Blue Cross Blue Shield of Arizona (BCBS AZ) | I43: No Payer | J43: 99494 x1; 99493 x1 | K43: 46183 | L43: =IF($O43="","",$O43-TODAY()) -> -165 | M43: =IF(AND(TRIM($A43)="Finalized",$K43<>""),"",IF($F43="","",$F43+90-TODAY())) -> -165 | N43: =IF(AND(TRIM($A43)="Finalized",$K43<>""),"",IF($D43="","",$D43+365-TODAY())) -> 152 | O43: =IF(AND(TRIM($A43)="Finalized",$K43<>""),"",DATE(2026,5,4)) -> 46146 | P43: 90 days | Q43: BCBS | R43: 90 days | S43: Date of service | T43: 365 days | U43: Processed date | V43: 2026-02 February | W43: BH | AA43: 1 | AB43: =IF($F43="","",TODAY()-$F43) -> 255 | AC43: 99494 | AD43: 99493 | AJ43: F4320 | AO43: LEATHEM, JARRETT | AP43: ASAP - Goodyear | AQ43: 46086 | AY43: Contacted payer | BA43: Credentialing / out of network | BC43: Call ref # 11216220 | BD43: 46213 | BF43: =IF(TRIM($A43)="Finalized","Closed",IF($BD43="","No review date set",IF($BD43<TODAY(),"OVERDUE",IF($BD43-TODAY()<=7,"Due within 7 days","Scheduled")))) -> OVERDUE | BG43: =IF($K43="","",TODAY()-$K43) -> 128 | BH43: =IFERROR(LEFT(IF($B43="","Notes, ","")&IF($K43="","Latest Date Worked, ","")&IF($AY43="","Last Action, ","")&IF(AND(OR(TRIM($A43)="Denied",TRIM($A43)="Rejected"),$BA43=""),"Denial Reason, ","")&IF(AND(TRIM($A43)="Denied",$BB43="",TRIM($BA43)<>"NO DENIAL"),"Denial Code, ","")&IF(AND(TRIM($A43)<>"Finalized",$BD43=""),"Next Review Date, ","")&IF(AND(TRIM($A43)<>"Finalized",$BE43=""),"Next Step, ","")&IF(AND(TRIM($A43)="Finalized",$AV43="",$AR43="",$AT43="",$AX43="",$AW43=""),"CPT outcome, ",""),LEN(IF($B43="","Notes, ","")&IF($K43="","Latest Date Worked, ","")&IF($AY43="","Last Action, ","")&IF(AND(OR(TRIM($A43)="Denied",TRIM($A43)="Rejected"),$BA43=""),"Denial Reason, ","")&IF(AND(TRIM($A43)="Denied",$BB43="",TRIM($BA43)<>"NO DENIAL"),"Denial Code, ","")&IF(AND(TRIM($A43)<>"Finalized",$BD43=""),"Next Review Date, ","")&IF(AND(TRIM($A43)<>"Finalized",$BE43=""),"Next Step, ","")&IF(AND(TRIM($A43)="Finalized",$AV43="",$AR43="",$AT43="",$AX43="",$AW43=""),"CPT outcome, ",""))-2),"") -> Denial Code, Next Step | BI43: =IF($BB43="","",IFERROR(INDEX('Denial Codes'!$C:$C,MATCH(LEFT($BB43,FIND(" - ",$BB43&" - ")+2)&"*",'Denial Codes'!$A:$A,0)),"")) | BJ43: =IF($BA43="","",IFERROR(INDEX(Lists!$B:$B,MATCH(TRIM($BA43),Lists!$A:$A,0))&"","")) -> Check provider enrollment, NPI/TIN and network status; appeal once credentialing is confirmed.
A44: Denied | B44: Deanne is reviewing this one - Rep Jessie - Claim contains a non anesthesia service, and rendering is listed as an anesthesiologist on ins end | C44: 555677002 | D44: 46147 | E44: HF540909294 | F44: 46059 | G44: Humana Gold Plus HMO | H44: Humana Gold Plus HMO | I44: No Payer | J44: 63048 x1; 63047 x1 | K44: 46247 | L44: =IF($O44="","",$O44-TODAY()) -> -162 | M44: =IF(AND(TRIM($A44)="Finalized",$K44<>""),"",IF($F44="","",$F44+90-TODAY())) -> -162 | N44: =IF(AND(TRIM($A44)="Finalized",$K44<>""),"",IF($D44="","",$D44+540-TODAY())) -> 376 | O44: =IF(AND(TRIM($A44)="Finalized",$K44<>""),"",DATE(2026,5,7)) -> 46149 | P44: 90 days | Q44: HUMANA MA | R44: 90 days | S44: Date of service | T44: 540 days | U44: Processed date | V44: 2026-02 February | W44: ORTHO | AA44: 1 | AB44: =IF($F44="","",TODAY()-$F44) -> 252 | AC44: 63048 | AD44: 63047 | AJ44: M48062 | AO44: O'NEIL, ROY | AP44: ASAP Surgery Centers North Valley LLC | AQ44: 46065 | AY44: Contacted payer | BA44: Credentialing / out of network | BD44: 46278 | BF44: =IF(TRIM($A44)="Finalized","Closed",IF($BD44="","No review date set",IF($BD44<TODAY(),"OVERDUE",IF($BD44-TODAY()<=7,"Due within 7 days","Scheduled")))) -> OVERDUE | BG44: =IF($K44="","",TODAY()-$K44) -> 64 | BH44: =IFERROR(LEFT(IF($B44="","Notes, ","")&IF($K44="","Latest Date Worked, ","")&IF($AY44="","Last Action, ","")&IF(AND(OR(TRIM($A44)="Denied",TRIM($A44)="Rejected"),$BA44=""),"Denial Reason, ","")&IF(AND(TRIM($A44)="Denied",$BB44="",TRIM($BA44)<>"NO DENIAL"),"Denial Code, ","")&IF(AND(TRIM($A44)<>"Finalized",$BD44=""),"Next Review Date, ","")&IF(AND(TRIM($A44)<>"Finalized",$BE44=""),"Next Step, ","")&IF(AND(TRIM($A44)="Finalized",$AV44="",$AR44="",$AT44="",$AX44="",$AW44=""),"CPT outcome, ",""),LEN(IF($B44="","Notes, ","")&IF($K44="","Latest Date Worked, ","")&IF($AY44="","Last Action, ","")&IF(AND(OR(TRIM($A44)="Denied",TRIM($A44)="Rejected"),$BA44=""),"Denial Reason, ","")&IF(AND(TRIM($A44)="Denied",$BB44="",TRIM($BA44)<>"NO DENIAL"),"Denial Code, ","")&IF(AND(TRIM($A44)<>"Finalized",$BD44=""),"Next Review Date, ","")&IF(AND(TRIM($A44)<>"Finalized",$BE44=""),"Next Step, ","")&IF(AND(TRIM($A44)="Finalized",$AV44="",$AR44="",$AT44="",$AX44="",$AW44=""),"CPT outcome, ",""))-2),"") -> Denial Code, Next Step | BI44: =IF($BB44="","",IFERROR(INDEX('Denial Codes'!$C:$C,MATCH(LEFT($BB44,FIND(" - ",$BB44&" - ")+2)&"*",'Denial Codes'!$A:$A,0)),"")) | BJ44: =IF($BA44="","",IFERROR(INDEX(Lists!$B:$B,MATCH(TRIM($BA44),Lists!$A:$A,0))&"","")) -> Check provider enrollment, NPI/TIN and network status; appeal once credentialing is confirmed.
A45: Denied | C45: 568966997 | D45: 46148 | E45: HF527306886 | F45: 46062 | G45: Optum Care Medical Network of Arizona, Utah, & Washington (LifePrint) | H45: Optum Care Medical Network of Arizona, Utah, & Washington (LifePrint) | I45: No Payer | J45: 99493 x1; 99494 x1 | K45: 46183 | L45: =IF($O45="","",$O45-TODAY()) -> -159 | M45: =IF(AND(TRIM($A45)="Finalized",$K45<>""),"",IF($D45="","",$D45+365-TODAY())) -> 202 | N45: =IF(AND(TRIM($A45)="Finalized",$K45<>""),"",IF($D45="","",$D45+365-TODAY())) -> 202 | O45: =IF(AND(TRIM($A45)="Finalized",$K45<>""),"",DATE(2026,5,10)) -> 46152 | P45: 90 days | Q45: OPTUM | R45: 365 days | S45: Processed date | T45: 365 days | U45: Processed date | V45: 2026-02 February | W45: BH | AA45: 1 | AB45: =IF($F45="","",TODAY()-$F45) -> 249 | AC45: 99493 | AD45: 99494 | AJ45: F4320 | AO45: KALLGREN, MARK | AP45: ASAP Peoria | AQ45: 46090 | BA45: Credentialing / out of network | BD45: 46213 | BF45: =IF(TRIM($A45)="Finalized","Closed",IF($BD45="","No review date set",IF($BD45<TODAY(),"OVERDUE",IF($BD45-TODAY()<=7,"Due within 7 days","Scheduled")))) -> OVERDUE | BG45: =IF($K45="","",TODAY()-$K45) -> 128 | BH45: =IFERROR(LEFT(IF($B45="","Notes, ","")&IF($K45="","Latest Date Worked, ","")&IF($AY45="","Last Action, ","")&IF(AND(OR(TRIM($A45)="Denied",TRIM($A45)="Rejected"),$BA45=""),"Denial Reason, ","")&IF(AND(TRIM($A45)="Denied",$BB45="",TRIM($BA45)<>"NO DENIAL"),"Denial Code, ","")&IF(AND(TRIM($A45)<>"Finalized",$BD45=""),"Next Review Date, ","")&IF(AND(TRIM($A45)<>"Finalized",$BE45=""),"Next Step, ","")&IF(AND(TRIM($A45)="Finalized",$AV45="",$AR45="",$AT45="",$AX45="",$AW45=""),"CPT outcome, ",""),LEN(IF($B45="","Notes, ","")&IF($K45="","Latest Date Worked, ","")&IF($AY45="","Last Action, ","")&IF(AND(OR(TRIM($A45)="Denied",TRIM($A45)="Rejected"),$BA45=""),"Denial Reason, ","")&IF(AND(TRIM($A45)="Denied",$BB45="",TRIM($BA45)<>"NO DENIAL"),"Denial Code, ","")&IF(AND(TRIM($A45)<>"Finalized",$BD45=""),"Next Review Date, ","")&IF(AND(TRIM($A45)<>"Finalized",$BE45=""),"Next Step, ","")&IF(AND(TRIM($A45)="Finalized",$AV45="",$AR45="",$AT45="",$AX45="",$AW45=""),"CPT outcome, ",""))-2),"") -> Notes, Last Action, Denial Code, Next Step | BI45: =IF($BB45="","",IFERROR(INDEX('Denial Codes'!$C:$C,MATCH(LEFT($BB45,FIND(" - ",$BB45&" - ")+2)&"*",'Denial Codes'!$A:$A,0)),"")) | BJ45: =IF($BA45="","",IFERROR(INDEX(Lists!$B:$B,MATCH(TRIM($BA45),Lists!$A:$A,0))&"","")) -> Check provider enrollment, NPI/TIN and network status; appeal once credentialing is confirmed.
A46: Pending | B46: secondary - Resubmitted to AmeTrust | C46: 549765437 | D46: 46119 | E46: HF359780591 | F46: 46065 | G46: TRIADA GAP BENEFITS | H46: Blue Cross Blue Shield of Arizona (BCBS AZ) | I46: TRIADA GAP BENEFITS | J46: 99493 x1; 99494 x1 | K46: 46305 | L46: =IF($O46="","",$O46-TODAY()) -> -156 | M46: =IF(AND(TRIM($A46)="Finalized",$K46<>""),"",IF($F46="","",$F46+90-TODAY())) -> -156 | N46: =IF(AND(TRIM($A46)="Finalized",$K46<>""),"",IF($D46="","",$D46+365-TODAY())) -> 173 | O46: =IF(AND(TRIM($A46)="Finalized",$K46<>""),"",DATE(2026,5,13)) -> 46155 | P46: 90 days | Q46: BCBS | R46: 90 days | S46: Date of service | T46: 365 days | U46: Processed date | V46: 2026-02 February | W46: BH | AA46: 1 | AB46: =IF($F46="","",TODAY()-$F46) -> 246 | AC46: 99493 | AD46: 99494 | AJ46: F411 | AN46: 558453526 | AO46: LEATHEM, JARRETT | AP46: ASAP - DEER VALLEY | AQ46: 46086 | AW46: 99493, 99494 | AX46: 99493, 99494 | AY46: Resubmitted | BB46: CO_45 - Charge exceeds fee schedule/maximum allowable or contracted/legislated fee arrangement | BD46: 46336 | BF46: =IF(TRIM($A46)="Finalized","Closed",IF($BD46="","No review date set",IF($BD46<TODAY(),"OVERDUE",IF($BD46-TODAY()<=7,"Due within 7 days","Scheduled")))) -> Scheduled | BG46: =IF($K46="","",TODAY()-$K46) -> 6 | BH46: =IFERROR(LEFT(IF($B46="","Notes, ","")&IF($K46="","Latest Date Worked, ","")&IF($AY46="","Last Action, ","")&IF(AND(OR(TRIM($A46)="Denied",TRIM($A46)="Rejected"),$BA46=""),"Denial Reason, ","")&IF(AND(TRIM($A46)="Denied",$BB46="",TRIM($BA46)<>"NO DENIAL"),"Denial Code, ","")&IF(AND(TRIM($A46)<>"Finalized",$BD46=""),"Next Review Date, ","")&IF(AND(TRIM($A46)<>"Finalized",$BE46=""),"Next Step, ","")&IF(AND(TRIM($A46)="Finalized",$AV46="",$AR46="",$AT46="",$AX46="",$AW46=""),"CPT outcome, ",""),LEN(IF($B46="","Notes, ","")&IF($K46="","Latest Date Worked, ","")&IF($AY46="","Last Action, ","")&IF(AND(OR(TRIM($A46)="Denied",TRIM($A46)="Rejected"),$BA46=""),"Denial Reason, ","")&IF(AND(TRIM($A46)="Denied",$BB46="",TRIM($BA46)<>"NO DENIAL"),"Denial Code, ","")&IF(AND(TRIM($A46)<>"Finalized",$BD46=""),"Next Review Date, ","")&IF(AND(TRIM($A46)<>"Finalized",$BE46=""),"Next Step, ","")&IF(AND(TRIM($A46)="Finalized",$AV46="",$AR46="",$AT46="",$AX46="",$AW46=""),"CPT outcome, ",""))-2),"") -> Next Step | BI46: =IF($BB46="","",IFERROR(INDEX('Denial Codes'!$C:$C,MATCH(LEFT($BB46,FIND(" - ",$BB46&" - ")+2)&"*",'Denial Codes'!$A:$A,0)),"")) -> Other | BJ46: =IF($BA46="","",IFERROR(INDEX(Lists!$B:$B,MATCH(TRIM($BA46),Lists!$A:$A,0))&"",""))
A47: Rejected | B47: Edited dx to G894, added auth #, and resubmitted - but VA doesn't cover BH - Rejected due to invalid dx - ASAP DEER VALLEY NPI missing - Resubmitted | C47: 574453982 | D47: 46098 | E47: HF342585384 | F47: 46036 | G47: TRIWEST VA CCN CLAIMS | H47: TRIWEST VA CCN CLAIMS | I47: No Payer | J47: 99494 x2; 99493 x1 | K47: 46305 | L47: =IF($O47="","",$O47-TODAY()) -> -155 | M47: =IF(AND(TRIM($A47)="Finalized",$K47<>""),"",IF($D47="","",$D47+365-TODAY())) -> 152 | N47: =IF(AND(TRIM($A47)="Finalized",$K47<>""),"",IF($D47="","",$D47+90-TODAY())) -> -123 | O47: =IF(AND(TRIM($A47)="Finalized",$K47<>""),"",DATE(2026,5,14)) -> 46156 | P47: 120 days | Q47: TRIWEST | R47: 365 days | S47: Processed date | T47: 90 days | U47: Processed date | V47: 2026-01 January | W47: BH | AA47: 2, 1 | AB47: =IF($F47="","",TODAY()-$F47) -> 275 | AC47: 99494 | AD47: 99493 | AJ47: G894 | AO47: TURLEY, TODD | AP47: ASAP - DEER VALLEY | AQ47: 46056 | AY47: Resubmitted | AZ47: Resubmitted | BA47: Diagnosis issue | BD47: 46336 | BF47: =IF(TRIM($A47)="Finalized","Closed",IF($BD47="","No review date set",IF($BD47<TODAY(),"OVERDUE",IF($BD47-TODAY()<=7,"Due within 7 days","Scheduled")))) -> Scheduled | BG47: =IF($K47="","",TODAY()-$K47) -> 6 | BH47: =IFERROR(LEFT(IF($B47="","Notes, ","")&IF($K47="","Latest Date Worked, ","")&IF($AY47="","Last Action, ","")&IF(AND(OR(TRIM($A47)="Denied",TRIM($A47)="Rejected"),$BA47=""),"Denial Reason, ","")&IF(AND(TRIM($A47)="Denied",$BB47="",TRIM($BA47)<>"NO DENIAL"),"Denial Code, ","")&IF(AND(TRIM($A47)<>"Finalized",$BD47=""),"Next Review Date, ","")&IF(AND(TRIM($A47)<>"Finalized",$BE47=""),"Next Step, ","")&IF(AND(TRIM($A47)="Finalized",$AV47="",$AR47="",$AT47="",$AX47="",$AW47=""),"CPT outcome, ",""),LEN(IF($B47="","Notes, ","")&IF($K47="","Latest Date Worked, ","")&IF($AY47="","Last Action, ","")&IF(AND(OR(TRIM($A47)="Denied",TRIM($A47)="Rejected"),$BA47=""),"Denial Reason, ","")&IF(AND(TRIM($A47)="Denied",$BB47="",TRIM($BA47)<>"NO DENIAL"),"Denial Code, ","")&IF(AND(TRIM($A47)<>"Finalized",$BD47=""),"Next Review Date, ","")&IF(AND(TRIM($A47)<>"Finalized",$BE47=""),"Next Step, ","")&IF(AND(TRIM($A47)="Finalized",$AV47="",$AR47="",$AT47="",$AX47="",$AW47=""),"CPT outcome, ",""))-2),"") -> Next Step | BI47: =IF($BB47="","",IFERROR(INDEX('Denial Codes'!$C:$C,MATCH(LEFT($BB47,FIND(" - ",$BB47&" - ")+2)&"*",'Denial Codes'!$A:$A,0)),"")) | BJ47: =IF($BA47="","",IFERROR(INDEX(Lists!$B:$B,MATCH(TRIM($BA47),Lists!$A:$A,0))&"","")) -> Review the diagnosis codes and pointers with the chart; correct and resubmit.
A48: Denied | B48: Added Date of Current Illness, claim note, and resubmitted | C48: 557794433 | D48: 46147 | E48: HF434792716 | F48: 46066 | G48: Optum Care Medical Network of Arizona, Utah, & Washington (LifePrint) | H48: Optum Care Medical Network of Arizona, Utah, & Washington (LifePrint) | I48: No Payer | J48: 99493 x1 | K48: 46142 | L48: =IF($O48="","",$O48-TODAY()) -> -155 | M48: =IF(AND(TRIM($A48)="Finalized",$K48<>""),"",IF($D48="","",$D48+365-TODAY())) -> 201 | N48: =IF(AND(TRIM($A48)="Finalized",$K48<>""),"",IF($D48="","",$D48+365-TODAY())) -> 201 | O48: =IF(AND(TRIM($A48)="Finalized",$K48<>""),"",DATE(2026,5,14)) -> 46156 | P48: 90 days | Q48: OPTUM | R48: 365 days | S48: Processed date | T48: 365 days | U48: Processed date | V48: 2026-02 February | W48: BH | AA48: 1 | AB48: =IF($F48="","",TODAY()-$F48) -> 245 | AC48: 99493 | AJ48: F1190 | AO48: LEATHEM, JARRETT | AP48: ASAP - Gilbert | AQ48: 46086 | AX48: 99493 | AY48: Resubmitted | BA48: Coding / billing error | BB48: OA_246 - This non-payable code is for required reporting only | BD48: 46172 | BF48: =IF(TRIM($A48)="Finalized","Closed",IF($BD48="","No review date set",IF($BD48<TODAY(),"OVERDUE",IF($BD48-TODAY()<=7,"Due within 7 days","Scheduled")))) -> OVERDUE | BG48: =IF($K48="","",TODAY()-$K48) -> 169 | BH48: =IFERROR(LEFT(IF($B48="","Notes, ","")&IF($K48="","Latest Date Worked, ","")&IF($AY48="","Last Action, ","")&IF(AND(OR(TRIM($A48)="Denied",TRIM($A48)="Rejected"),$BA48=""),"Denial Reason, ","")&IF(AND(TRIM($A48)="Denied",$BB48="",TRIM($BA48)<>"NO DENIAL"),"Denial Code, ","")&IF(AND(TRIM($A48)<>"Finalized",$BD48=""),"Next Review Date, ","")&IF(AND(TRIM($A48)<>"Finalized",$BE48=""),"Next Step, ","")&IF(AND(TRIM($A48)="Finalized",$AV48="",$AR48="",$AT48="",$AX48="",$AW48=""),"CPT outcome, ",""),LEN(IF($B48="","Notes, ","")&IF($K48="","Latest Date Worked, ","")&IF($AY48="","Last Action, ","")&IF(AND(OR(TRIM($A48)="Denied",TRIM($A48)="Rejected"),$BA48=""),"Denial Reason, ","")&IF(AND(TRIM($A48)="Denied",$BB48="",TRIM($BA48)<>"NO DENIAL"),"Denial Code, ","")&IF(AND(TRIM($A48)<>"Finalized",$BD48=""),"Next Review Date, ","")&IF(AND(TRIM($A48)<>"Finalized",$BE48=""),"Next Step, ","")&IF(AND(TRIM($A48)="Finalized",$AV48="",$AR48="",$AT48="",$AX48="",$AW48=""),"CPT outcome, ",""))-2),"") -> Next Step | BI48: =IF($BB48="","",IFERROR(INDEX('Denial Codes'!$C:$C,MATCH(LEFT($BB48,FIND(" - ",$BB48&" - ")+2)&"*",'Denial Codes'!$A:$A,0)),"")) -> Coding / billing error | BJ48: =IF($BA48="","",IFERROR(INDEX(Lists!$B:$B,MATCH(TRIM($BA48),Lists!$A:$A,0))&"","")) -> Fix the code, units, charge or other claim data and resubmit as a corrected claim.
A49: Denied | B49: Provider active, resubmitted | C49: 557784595 | D49: 46154 | E49: HF489558936 | F49: 46069 | G49: Blue Cross Blue Shield of Arizona (BCBS AZ) | H49: Blue Cross Blue Shield of Arizona (BCBS AZ) | I49: No Payer | J49: 36246+59+RT x1; 75710+XU+RT x1; 76937 x1; 75774+XU x4; 36248+59 x3; 37242 x1 | K49: 46142 | L49: =IF($O49="","",$O49-TODAY()) -> -152 | M49: =IF(AND(TRIM($A49)="Finalized",$K49<>""),"",IF($F49="","",$F49+90-TODAY())) -> -152 | N49: =IF(AND(TRIM($A49)="Finalized",$K49<>""),"",IF($D49="","",$D49+365-TODAY())) -> 208 | O49: =IF(AND(TRIM($A49)="Finalized",$K49<>""),"",DATE(2026,5,17)) -> 46159 | P49: 90 days | Q49: BCBS | R49: 90 days | S49: Date of service | T49: 365 days | U49: Processed date | V49: 2026-02 February | W49: GAE | X49: 59, XU | Y49: RT | AA49: 1, 4, 3 | AB49: =IF($F49="","",TODAY()-$F49) -> 242 | AC49: 36246 | AD49: 75710 | AE49: 76937 | AF49: 75774 | AG49: 36248 | AH49: 37242 | AJ49: M1711 | AK49: I798 | AL49: M25561 | AO49: HUNTER, DREW | AP49: ASAP - DEER VALLEY | AQ49: 46090 | AY49: Resubmitted | BA49: Credentialing / out of network | BD49: 46172 | BF49: =IF(TRIM($A49)="Finalized","Closed",IF($BD49="","No review date set",IF($BD49<TODAY(),"OVERDUE",IF($BD49-TODAY()<=7,"Due within 7 days","Scheduled")))) -> OVERDUE | BG49: =IF($K49="","",TODAY()-$K49) -> 169 | BH49: =IFERROR(LEFT(IF($B49="","Notes, ","")&IF($K49="","Latest Date Worked, ","")&IF($AY49="","Last Action, ","")&IF(AND(OR(TRIM($A49)="Denied",TRIM($A49)="Rejected"),$BA49=""),"Denial Reason, ","")&IF(AND(TRIM($A49)="Denied",$BB49="",TRIM($BA49)<>"NO DENIAL"),"Denial Code, ","")&IF(AND(TRIM($A49)<>"Finalized",$BD49=""),"Next Review Date, ","")&IF(AND(TRIM($A49)<>"Finalized",$BE49=""),"Next Step, ","")&IF(AND(TRIM($A49)="Finalized",$AV49="",$AR49="",$AT49="",$AX49="",$AW49=""),"CPT outcome, ",""),LEN(IF($B49="","Notes, ","")&IF($K49="","Latest Date Worked, ","")&IF($AY49="","Last Action, ","")&IF(AND(OR(TRIM($A49)="Denied",TRIM($A49)="Rejected"),$BA49=""),"Denial Reason, ","")&IF(AND(TRIM($A49)="Denied",$BB49="",TRIM($BA49)<>"NO DENIAL"),"Denial Code, ","")&IF(AND(TRIM($A49)<>"Finalized",$BD49=""),"Next Review Date, ","")&IF(AND(TRIM($A49)<>"Finalized",$BE49=""),"Next Step, ","")&IF(AND(TRIM($A49)="Finalized",$AV49="",$AR49="",$AT49="",$AX49="",$AW49=""),"CPT outcome, ",""))-2),"") -> Denial Code, Next Step | BI49: =IF($BB49="","",IFERROR(INDEX('Denial Codes'!$C:$C,MATCH(LEFT($BB49,FIND(" - ",$BB49&" - ")+2)&"*",'Denial Codes'!$A:$A,0)),"")) | BJ49: =IF($BA49="","",IFERROR(INDEX(Lists!$B:$B,MATCH(TRIM($BA49),Lists!$A:$A,0))&"","")) -> Check provider enrollment, NPI/TIN and network status; appeal once credentialing is confirmed.
A50: Under Review | B50: Auth issue - Bri resubmitted - Provider TAX ID/NPI Combination is not on file with BCBS AZ. | C50: 565140993 | D50: 46227 | E50: HF513477727 | F50: 46069 | G50: Blue Cross Blue Shield of Arizona (BCBS AZ) | H50: Blue Cross Blue Shield of Arizona (BCBS AZ) | I50: No Payer | J50: L0648+KX x1 | K50: 46196 | L50: =IF($O50="","",$O50-TODAY()) -> -152 | M50: =IF(AND(TRIM($A50)="Finalized",$K50<>""),"",IF($F50="","",$F50+90-TODAY())) -> -152 | N50: =IF(AND(TRIM($A50)="Finalized",$K50<>""),"",IF($D50="","",$D50+365-TODAY())) -> 281 | O50: =IF(AND(TRIM($A50)="Finalized",$K50<>""),"",DATE(2026,5,17)) -> 46159 | P50: 90 days | Q50: BCBS | R50: 90 days | S50: Date of service | T50: 365 days | U50: Processed date | V50: 2026-02 February | W50: DME | X50: KX | AA50: 1 | AB50: =IF($F50="","",TODAY()-$F50) -> 242 | AC50: L0648 | AJ50: M4316 | AK50: M51362 | AO50: MAYURAN, VIKRAM | AP50: ASAP - Mesa | AQ50: 46080 | AY50: Resubmitted | BA50: Other | BD50: 46226 | BF50: =IF(TRIM($A50)="Finalized","Closed",IF($BD50="","No review date set",IF($BD50<TODAY(),"OVERDUE",IF($BD50-TODAY()<=7,"Due within 7 days","Scheduled")))) -> OVERDUE | BG50: =IF($K50="","",TODAY()-$K50) -> 115 | BH50: =IFERROR(LEFT(IF($B50="","Notes, ","")&IF($K50="","Latest Date Worked, ","")&IF($AY50="","Last Action, ","")&IF(AND(OR(TRIM($A50)="Denied",TRIM($A50)="Rejected"),$BA50=""),"Denial Reason, ","")&IF(AND(TRIM($A50)="Denied",$BB50="",TRIM($BA50)<>"NO DENIAL"),"Denial Code, ","")&IF(AND(TRIM($A50)<>"Finalized",$BD50=""),"Next Review Date, ","")&IF(AND(TRIM($A50)<>"Finalized",$BE50=""),"Next Step, ","")&IF(AND(TRIM($A50)="Finalized",$AV50="",$AR50="",$AT50="",$AX50="",$AW50=""),"CPT outcome, ",""),LEN(IF($B50="","Notes, ","")&IF($K50="","Latest Date Worked, ","")&IF($AY50="","Last Action, ","")&IF(AND(OR(TRIM($A50)="Denied",TRIM($A50)="Rejected"),$BA50=""),"Denial Reason, ","")&IF(AND(TRIM($A50)="Denied",$BB50="",TRIM($BA50)<>"NO DENIAL"),"Denial Code, ","")&IF(AND(TRIM($A50)<>"Finalized",$BD50=""),"Next Review Date, ","")&IF(AND(TRIM($A50)<>"Finalized",$BE50=""),"Next Step, ","")&IF(AND(TRIM($A50)="Finalized",$AV50="",$AR50="",$AT50="",$AX50="",$AW50=""),"CPT outcome, ",""))-2),"") -> Next Step | BI50: =IF($BB50="","",IFERROR(INDEX('Denial Codes'!$C:$C,MATCH(LEFT($BB50,FIND(" - ",$BB50&" - ")+2)&"*",'Denial Codes'!$A:$A,0)),"")) | BJ50: =IF($BA50="","",IFERROR(INDEX(Lists!$B:$B,MATCH(TRIM($BA50),Lists!$A:$A,0))&"",""))
A51: Denied | B51: 99492 paid on DOS 01/27/2026 - Resubmitted - Awaiting resolution on claim #556349314 (DOS 01/27/2026) before reprocessing DND 99493 This non-payable code is for required reporting only - Added Date of Current Illness, claim note, and resubmitted | C51: 557794882 | D51: 46147 | E51: HF431164004 | F51: 46070 | G51: Optum Care Medical Network of Arizona, Utah, & Washington (LifePrint) | H51: Optum Care Medical Network of Arizona, Utah, & Washington (LifePrint) | I51: No Payer | J51: 99493 x1 | K51: 46309 | L51: =IF($O51="","",$O51-TODAY()) -> -151 | M51: =IF(AND(TRIM($A51)="Finalized",$K51<>""),"",IF($D51="","",$D51+365-TODAY())) -> 201 | N51: =IF(AND(TRIM($A51)="Finalized",$K51<>""),"",IF($D51="","",$D51+365-TODAY())) -> 201 | O51: =IF(AND(TRIM($A51)="Finalized",$K51<>""),"",DATE(2026,5,18)) -> 46160 | P51: 90 days | Q51: OPTUM | R51: 365 days | S51: Processed date | T51: 365 days | U51: Processed date | V51: 2026-02 February | W51: BH | AA51: 1 | AB51: =IF($F51="","",TODAY()-$F51) -> 241 | AC51: 99493 | AJ51: F331 | AK51: F411 | AO51: O'NEIL, ROY | AP51: ASAP - Goodyear | AQ51: 46086 | AX51: 99493, 99494 | AY51: Resubmitted | AZ51: Resubmitted | BA51: Coding / billing error | BB51: OA_246 - This non-payable code is for required reporting only | BD51: 46340 | BF51: =IF(TRIM($A51)="Finalized","Closed",IF($BD51="","No review date set",IF($BD51<TODAY(),"OVERDUE",IF($BD51-TODAY()<=7,"Due within 7 days","Scheduled")))) -> Scheduled | BG51: =IF($K51="","",TODAY()-$K51) -> 2 | BH51: =IFERROR(LEFT(IF($B51="","Notes, ","")&IF($K51="","Latest Date Worked, ","")&IF($AY51="","Last Action, ","")&IF(AND(OR(TRIM($A51)="Denied",TRIM($A51)="Rejected"),$BA51=""),"Denial Reason, ","")&IF(AND(TRIM($A51)="Denied",$BB51="",TRIM($BA51)<>"NO DENIAL"),"Denial Code, ","")&IF(AND(TRIM($A51)<>"Finalized",$BD51=""),"Next Review Date, ","")&IF(AND(TRIM($A51)<>"Finalized",$BE51=""),"Next Step, ","")&IF(AND(TRIM($A51)="Finalized",$AV51="",$AR51="",$AT51="",$AX51="",$AW51=""),"CPT outcome, ",""),LEN(IF($B51="","Notes, ","")&IF($K51="","Latest Date Worked, ","")&IF($AY51="","Last Action, ","")&IF(AND(OR(TRIM($A51)="Denied",TRIM($A51)="Rejected"),$BA51=""),"Denial Reason, ","")&IF(AND(TRIM($A51)="Denied",$BB51="",TRIM($BA51)<>"NO DENIAL"),"Denial Code, ","")&IF(AND(TRIM($A51)<>"Finalized",$BD51=""),"Next Review Date, ","")&IF(AND(TRIM($A51)<>"Finalized",$BE51=""),"Next Step, ","")&IF(AND(TRIM($A51)="Finalized",$AV51="",$AR51="",$AT51="",$AX51="",$AW51=""),"CPT outcome, ",""))-2),"") -> Next Step | BI51: =IF($BB51="","",IFERROR(INDEX('Denial Codes'!$C:$C,MATCH(LEFT($BB51,FIND(" - ",$BB51&" - ")+2)&"*",'Denial Codes'!$A:$A,0)),"")) -> Coding / billing error | BJ51: =IF($BA51="","",IFERROR(INDEX(Lists!$B:$B,MATCH(TRIM($BA51),Lists!$A:$A,0))&"","")) -> Fix the code, units, charge or other claim data and resubmit as a corrected claim.
A52: Denied | B52: Rep Muthamma | C52: 550288006 | D52: 46101 | E52: HF331718997 | F52: 46071 | G52: Blue Cross Blue Shield of Arizona (BCBS AZ) | H52: Blue Cross Blue Shield of Arizona (BCBS AZ) | I52: No Payer | J52: 99494 x2; 99492 x1 | K52: 46183 | L52: =IF($O52="","",$O52-TODAY()) -> -150 | M52: =IF(AND(TRIM($A52)="Finalized",$K52<>""),"",IF($F52="","",$F52+90-TODAY())) -> -150 | N52: =IF(AND(TRIM($A52)="Finalized",$K52<>""),"",IF($D52="","",$D52+365-TODAY())) -> 155 | O52: =IF(AND(TRIM($A52)="Finalized",$K52<>""),"",DATE(2026,5,19)) -> 46161 | P52: 90 days | Q52: BCBS | R52: 90 days | S52: Date of service | T52: 365 days | U52: Processed date | V52: 2026-02 February | W52: BH | AA52: 2, 1 | AB52: =IF($F52="","",TODAY()-$F52) -> 240 | AC52: 99494 | AD52: 99492 | AJ52: F4323 | AO52: SARKAR, AWNIK | AP52: ASAP - DEER VALLEY | AQ52: 46086 | AY52: Contacted payer | BC52: Call ref # 11253575 | BD52: 46213 | BF52: =IF(TRIM($A52)="Finalized","Closed",IF($BD52="","No review date set",IF($BD52<TODAY(),"OVERDUE",IF($BD52-TODAY()<=7,"Due within 7 days","Scheduled")))) -> OVERDUE | BG52: =IF($K52="","",TODAY()-$K52) -> 128 | BH52: =IFERROR(LEFT(IF($B52="","Notes, ","")&IF($K52="","Latest Date Worked, ","")&IF($AY52="","Last Action, ","")&IF(AND(OR(TRIM($A52)="Denied",TRIM($A52)="Rejected"),$BA52=""),"Denial Reason, ","")&IF(AND(TRIM($A52)="Denied",$BB52="",TRIM($BA52)<>"NO DENIAL"),"Denial Code, ","")&IF(AND(TRIM($A52)<>"Finalized",$BD52=""),"Next Review Date, ","")&IF(AND(TRIM($A52)<>"Finalized",$BE52=""),"Next Step, ","")&IF(AND(TRIM($A52)="Finalized",$AV52="",$AR52="",$AT52="",$AX52="",$AW52=""),"CPT outcome, ",""),LEN(IF($B52="","Notes, ","")&IF($K52="","Latest Date Worked, ","")&IF($AY52="","Last Action, ","")&IF(AND(OR(TRIM($A52)="Denied",TRIM($A52)="Rejected"),$BA52=""),"Denial Reason, ","")&IF(AND(TRIM($A52)="Denied",$BB52="",TRIM($BA52)<>"NO DENIAL"),"Denial Code, ","")&IF(AND(TRIM($A52)<>"Finalized",$BD52=""),"Next Review Date, ","")&IF(AND(TRIM($A52)<>"Finalized",$BE52=""),"Next Step, ","")&IF(AND(TRIM($A52)="Finalized",$AV52="",$AR52="",$AT52="",$AX52="",$AW52=""),"CPT outcome, ",""))-2),"") -> Denial Reason, Denial Code, Next Step | BI52: =IF($BB52="","",IFERROR(INDEX('Denial Codes'!$C:$C,MATCH(LEFT($BB52,FIND(" - ",$BB52&" - ")+2)&"*",'Denial Codes'!$A:$A,0)),"")) | BJ52: =IF($BA52="","",IFERROR(INDEX(Lists!$B:$B,MATCH(TRIM($BA52),Lists!$A:$A,0))&"",""))
A53: Finalized | B53: Adjusted balance - No authorization found or requested - Checking if we need auth on Curo portal # 19801266 - Review | C53: 550530483 | D53: 46106 | E53: HF544828362 | F53: 46072 | G53: UHC Group Medicare Advantage | H53: UHC Group Medicare Advantage | I53: No Payer | J53: A6010+A1 x20 | K53: 46197 | L53: =IF($O53="","",$O53-TODAY()) | M53: =IF(AND(TRIM($A53)="Finalized",$K53<>""),"",IF($D53="","",$D53+180-TODAY())) | N53: =IF(AND(TRIM($A53)="Finalized",$K53<>""),"",IF($D53="","",$D53+365-TODAY())) | O53: =IF(AND(TRIM($A53)="Finalized",$K53<>""),"",DATE(2026,5,20)) | P53: 90 days | Q53: UHC MA | R53: 180 days | S53: Processed date | T53: 365 days | U53: Processed date | V53: 2026-02 February | W53: DME | X53: A1 | AA53: 20 | AB53: =IF($F53="","",TODAY()-$F53) -> 239 | AC53: A6010 | AJ53: G894 | AK53: L97529 | AO53: MEARS, CHAD | AP53: ASAP Peoria | AQ53: 46077 | AT53: A6010 | AU53: CO_197 - Precertification/authorization/notification/pre-treatment absent | AY53: Adjusted balance | BA53: No authorization | BB53: CO_197 - Precertification/authorization/notification/pre-treatment absent | BC53: Curo # 19801266 | BF53: =IF(TRIM($A53)="Finalized","Closed",IF($BD53="","No review date set",IF($BD53<TODAY(),"OVERDUE",IF($BD53-TODAY()<=7,"Due within 7 days","Scheduled")))) -> Closed | BG53: =IF($K53="","",TODAY()-$K53) -> 114 | BH53: =IFERROR(LEFT(IF($B53="","Notes, ","")&IF($K53="","Latest Date Worked, ","")&IF($AY53="","Last Action, ","")&IF(AND(OR(TRIM($A53)="Denied",TRIM($A53)="Rejected"),$BA53=""),"Denial Reason, ","")&IF(AND(TRIM($A53)="Denied",$BB53="",TRIM($BA53)<>"NO DENIAL"),"Denial Code, ","")&IF(AND(TRIM($A53)<>"Finalized",$BD53=""),"Next Review Date, ","")&IF(AND(TRIM($A53)<>"Finalized",$BE53=""),"Next Step, ","")&IF(AND(TRIM($A53)="Finalized",$AV53="",$AR53="",$AT53="",$AX53="",$AW53=""),"CPT outcome, ",""),LEN(IF($B53="","Notes, ","")&IF($K53="","Latest Date Worked, ","")&IF($AY53="","Last Action, ","")&IF(AND(OR(TRIM($A53)="Denied",TRIM($A53)="Rejected"),$BA53=""),"Denial Reason, ","")&IF(AND(TRIM($A53)="Denied",$BB53="",TRIM($BA53)<>"NO DENIAL"),"Denial Code, ","")&IF(AND(TRIM($A53)<>"Finalized",$BD53=""),"Next Review Date, ","")&IF(AND(TRIM($A53)<>"Finalized",$BE53=""),"Next Step, ","")&IF(AND(TRIM($A53)="Finalized",$AV53="",$AR53="",$AT53="",$AX53="",$AW53=""),"CPT outcome, ",""))-2),"") | BI53: =IF($BB53="","",IFERROR(INDEX('Denial Codes'!$C:$C,MATCH(LEFT($BB53,FIND(" - ",$BB53&" - ")+2)&"*",'Denial Codes'!$A:$A,0)),"")) -> No authorization | BJ53: =IF($BA53="","",IFERROR(INDEX(Lists!$B:$B,MATCH(TRIM($BA53),Lists!$A:$A,0))&"","")) -> Check the portal for an auth; request a retro-auth or file an appeal with the auth number, then resubmit.
A54: Finalized | B54: PAID - Changed primary code - Used 99492, and resubmitted | C54: 557794229 | D54: 46147 | E54: HF460603685 | F54: 46073 | G54: Optum Care Medical Network of Arizona, Utah, & Washington (LifePrint) | H54: Optum Care Medical Network of Arizona, Utah, & Washington (LifePrint) | I54: No Payer | J54: 99493 x1 | K54: 46247 | L54: =IF($O54="","",$O54-TODAY()) | M54: =IF(AND(TRIM($A54)="Finalized",$K54<>""),"",IF($D54="","",$D54+365-TODAY())) | N54: =IF(AND(TRIM($A54)="Finalized",$K54<>""),"",IF($D54="","",$D54+365-TODAY())) | O54: =IF(AND(TRIM($A54)="Finalized",$K54<>""),"",DATE(2026,5,21)) | P54: 90 days | Q54: OPTUM | R54: 365 days | S54: Processed date | T54: 365 days | U54: Processed date | V54: 2026-02 February | W54: BH | AA54: 1 | AB54: =IF($F54="","",TODAY()-$F54) -> 238 | AC54: 99493 | AJ54: F1190 | AO54: KALLGREN, MARK | AP54: ASAP - Gilbert | AQ54: 46086 | AV54: 99492 | AX54: 99492, 99493 | AY54: Payment posted | AZ54: Resubmitted | BA54: Coding / billing error | BB54: OA_246 - This non-payable code is for required reporting only | BF54: =IF(TRIM($A54)="Finalized","Closed",IF($BD54="","No review date set",IF($BD54<TODAY(),"OVERDUE",IF($BD54-TODAY()<=7,"Due within 7 days","Scheduled")))) -> Closed | BG54: =IF($K54="","",TODAY()-$K54) -> 64 | BH54: =IFERROR(LEFT(IF($B54="","Notes, ","")&IF($K54="","Latest Date Worked, ","")&IF($AY54="","Last Action, ","")&IF(AND(OR(TRIM($A54)="Denied",TRIM($A54)="Rejected"),$BA54=""),"Denial Reason, ","")&IF(AND(TRIM($A54)="Denied",$BB54="",TRIM($BA54)<>"NO DENIAL"),"Denial Code, ","")&IF(AND(TRIM($A54)<>"Finalized",$BD54=""),"Next Review Date, ","")&IF(AND(TRIM($A54)<>"Finalized",$BE54=""),"Next Step, ","")&IF(AND(TRIM($A54)="Finalized",$AV54="",$AR54="",$AT54="",$AX54="",$AW54=""),"CPT outcome, ",""),LEN(IF($B54="","Notes, ","")&IF($K54="","Latest Date Worked, ","")&IF($AY54="","Last Action, ","")&IF(AND(OR(TRIM($A54)="Denied",TRIM($A54)="Rejected"),$BA54=""),"Denial Reason, ","")&IF(AND(TRIM($A54)="Denied",$BB54="",TRIM($BA54)<>"NO DENIAL"),"Denial Code, ","")&IF(AND(TRIM($A54)<>"Finalized",$BD54=""),"Next Review Date, ","")&IF(AND(TRIM($A54)<>"Finalized",$BE54=""),"Next Step, ","")&IF(AND(TRIM($A54)="Finalized",$AV54="",$AR54="",$AT54="",$AX54="",$AW54=""),"CPT outcome, ",""))-2),"") | BI54: =IF($BB54="","",IFERROR(INDEX('Denial Codes'!$C:$C,MATCH(LEFT($BB54,FIND(" - ",$BB54&" - ")+2)&"*",'Denial Codes'!$A:$A,0)),"")) -> Coding / billing error | BJ54: =IF($BA54="","",IFERROR(INDEX(Lists!$B:$B,MATCH(TRIM($BA54),Lists!$A:$A,0))&"","")) -> Fix the code, units, charge or other claim data and resubmit as a corrected claim.
A55: Finalized | B55: PAID - Edited service line 1 - Used cpt 99492, and resubmitted - The reconsideration option is unavailable on portal because the claim has already been adjusted - 99493 paid on claim 26A074466600, DOS 12/12/2025, under prior member ID 1718676 - current claim was billed with member ID 906162197 currently active - Added Date of Current Illness, claim note, and resubmitted | C55: 557793858 | D55: 46147 | E55: HF443112560 | F55: 46073 | G55: Optum Care Medical Network of Arizona, Utah, & Washington (LifePrint) | H55: Optum Care Medical Network of Arizona, Utah, & Washington (LifePrint) | I55: No Payer | J55: 99493 x1 | K55: 46266 | L55: =IF($O55="","",$O55-TODAY()) | M55: =IF(AND(TRIM($A55)="Finalized",$K55<>""),"",IF($D55="","",$D55+365-TODAY())) | N55: =IF(AND(TRIM($A55)="Finalized",$K55<>""),"",IF($D55="","",$D55+365-TODAY())) | O55: =IF(AND(TRIM($A55)="Finalized",$K55<>""),"",DATE(2026,5,21)) | P55: 90 days | Q55: OPTUM | R55: 365 days | S55: Processed date | T55: 365 days | U55: Processed date | V55: 2026-02 February | W55: BH | AA55: 1 | AB55: =IF($F55="","",TODAY()-$F55) -> 238 | AC55: 99493 | AJ55: F1190 | AO55: LEATHEM, JARRETT | AP55: ASAP - Gilbert | AQ55: 46086 | AV55: 99492 | AX55: 99493, 99492 | AY55: Payment posted | AZ55: Resubmitted | BA55: Coding / billing error | BB55: OA_246 - This non-payable code is for required reporting only | BF55: =IF(TRIM($A55)="Finalized","Closed",IF($BD55="","No review date set",IF($BD55<TODAY(),"OVERDUE",IF($BD55-TODAY()<=7,"Due within 7 days","Scheduled")))) -> Closed | BG55: =IF($K55="","",TODAY()-$K55) -> 45 | BH55: =IFERROR(LEFT(IF($B55="","Notes, ","")&IF($K55="","Latest Date Worked, ","")&IF($AY55="","Last Action, ","")&IF(AND(OR(TRIM($A55)="Denied",TRIM($A55)="Rejected"),$BA55=""),"Denial Reason, ","")&IF(AND(TRIM($A55)="Denied",$BB55="",TRIM($BA55)<>"NO DENIAL"),"Denial Code, ","")&IF(AND(TRIM($A55)<>"Finalized",$BD55=""),"Next Review Date, ","")&IF(AND(TRIM($A55)<>"Finalized",$BE55=""),"Next Step, ","")&IF(AND(TRIM($A55)="Finalized",$AV55="",$AR55="",$AT55="",$AX55="",$AW55=""),"CPT outcome, ",""),LEN(IF($B55="","Notes, ","")&IF($K55="","Latest Date Worked, ","")&IF($AY55="","Last Action, ","")&IF(AND(OR(TRIM($A55)="Denied",TRIM($A55)="Rejected"),$BA55=""),"Denial Reason, ","")&IF(AND(TRIM($A55)="Denied",$BB55="",TRIM($BA55)<>"NO DENIAL"),"Denial Code, ","")&IF(AND(TRIM($A55)<>"Finalized",$BD55=""),"Next Review Date, ","")&IF(AND(TRIM($A55)<>"Finalized",$BE55=""),"Next Step, ","")&IF(AND(TRIM($A55)="Finalized",$AV55="",$AR55="",$AT55="",$AX55="",$AW55=""),"CPT outcome, ",""))-2),"") | BI55: =IF($BB55="","",IFERROR(INDEX('Denial Codes'!$C:$C,MATCH(LEFT($BB55,FIND(" - ",$BB55&" - ")+2)&"*",'Denial Codes'!$A:$A,0)),"")) -> Coding / billing error | BJ55: =IF($BA55="","",IFERROR(INDEX(Lists!$B:$B,MATCH(TRIM($BA55),Lists!$A:$A,0))&"","")) -> Fix the code, units, charge or other claim data and resubmit as a corrected claim.
A56: Finalized | B56: Claim 568613230 was paid - Removed mod 58, and resubmitted - Added mod 58, and resubmitted | C56: 562083380 | D56: 46189 | E56: HF334213960 | F56: 46080 | G56: Optum Care Medical Network of Arizona, Utah, & Washington (LifePrint) | H56: Optum Care Medical Network of Arizona, Utah, & Washington (LifePrint) | I56: No Payer | J56: 63047+58 x1 | K56: 46247 | L56: =IF($O56="","",$O56-TODAY()) | M56: =IF(AND(TRIM($A56)="Finalized",$K56<>""),"",IF($D56="","",$D56+365-TODAY())) | N56: =IF(AND(TRIM($A56)="Finalized",$K56<>""),"",IF($D56="","",$D56+365-TODAY())) | O56: =IF(AND(TRIM($A56)="Finalized",$K56<>""),"",DATE(2026,5,28)) | P56: 90 days | Q56: OPTUM | R56: 365 days | S56: Processed date | T56: 365 days | U56: Processed date | V56: 2026-02 February | W56: ORTHO | X56: 58 | AA56: 1 | AB56: =IF($F56="","",TODAY()-$F56) -> 231 | AC56: 63047 | AJ56: M48062 | AO56: LEATHEM, JARRETT | AP56: Premier Endoscopy Center, LLC | AQ56: 46083 | AX56: 63047 | AY56: Payment posted | AZ56: Resubmitted | BA56: Modifier issue | BB56: CO_97 - The benefit for this service is included in the payment/allowance for another service/procedure already adjudicated | BF56: =IF(TRIM($A56)="Finalized","Closed",IF($BD56="","No review date set",IF($BD56<TODAY(),"OVERDUE",IF($BD56-TODAY()<=7,"Due within 7 days","Scheduled")))) -> Closed | BG56: =IF($K56="","",TODAY()-$K56) -> 64 | BH56: =IFERROR(LEFT(IF($B56="","Notes, ","")&IF($K56="","Latest Date Worked, ","")&IF($AY56="","Last Action, ","")&IF(AND(OR(TRIM($A56)="Denied",TRIM($A56)="Rejected"),$BA56=""),"Denial Reason, ","")&IF(AND(TRIM($A56)="Denied",$BB56="",TRIM($BA56)<>"NO DENIAL"),"Denial Code, ","")&IF(AND(TRIM($A56)<>"Finalized",$BD56=""),"Next Review Date, ","")&IF(AND(TRIM($A56)<>"Finalized",$BE56=""),"Next Step, ","")&IF(AND(TRIM($A56)="Finalized",$AV56="",$AR56="",$AT56="",$AX56="",$AW56=""),"CPT outcome, ",""),LEN(IF($B56="","Notes, ","")&IF($K56="","Latest Date Worked, ","")&IF($AY56="","Last Action, ","")&IF(AND(OR(TRIM($A56)="Denied",TRIM($A56)="Rejected"),$BA56=""),"Denial Reason, ","")&IF(AND(TRIM($A56)="Denied",$BB56="",TRIM($BA56)<>"NO DENIAL"),"Denial Code, ","")&IF(AND(TRIM($A56)<>"Finalized",$BD56=""),"Next Review Date, ","")&IF(AND(TRIM($A56)<>"Finalized",$BE56=""),"Next Step, ","")&IF(AND(TRIM($A56)="Finalized",$AV56="",$AR56="",$AT56="",$AX56="",$AW56=""),"CPT outcome, ",""))-2),"") | BI56: =IF($BB56="","",IFERROR(INDEX('Denial Codes'!$C:$C,MATCH(LEFT($BB56,FIND(" - ",$BB56&" - ")+2)&"*",'Denial Codes'!$A:$A,0)),"")) -> Bundled / NCCI edit | BJ56: =IF($BA56="","",IFERROR(INDEX(Lists!$B:$B,MATCH(TRIM($BA56),Lists!$A:$A,0))&"","")) -> Correct or add the modifier (e.g. NU/RR, KX, RT/LT, 25) and resubmit.
A57: Finalized | B57: PAID - Uploaded MR | C57: 555067836 | D57: 46217 | E57: HF333306186 | F57: 46083 | G57: UnitedHealthcare Community Plan / Arizona Long Term Care | H57: UnitedHealthcare Community Plan / Arizona Long Term Care | I57: UnitedHealthcare Community Plan / Arizona Long Term Care | J57: 75710+26+XU+RT x1; 36246+59+RT x1; 75774+26+XU x5 | K57: 46197 | L57: =IF($O57="","",$O57-TODAY()) | M57: =IF(AND(TRIM($A57)="Finalized",$K57<>""),"",IF($D57="","",$D57+180-TODAY())) | N57: =IF(AND(TRIM($A57)="Finalized",$K57<>""),"",IF($D57="","",$D57+365-TODAY())) | O57: =IF(AND(TRIM($A57)="Finalized",$K57<>""),"",DATE(2026,5,31)) | P57: 90 days | Q57: UHC COMMUNITY | R57: 180 days | S57: Processed date | T57: 365 days | U57: Processed date | V57: 2026-03 March | W57: GAE | X57: 26, 59 | Y57: XU, RT | Z57: RT | AA57: 1, 5 | AB57: =IF($F57="","",TODAY()-$F57) -> 228 | AC57: 75710 | AD57: 36246 | AE57: 75774 | AJ57: M1711 | AK57: I798 | AL57: M25561 | AO57: HUNTER, DREW | AP57: ASAP Surgery Centers North Valley LLC | AQ57: 46119 | AV57: 75710, 36246, 75774 | AX57: 75710, 36246, 75774 | AY57: Payment posted | AZ57: Uploaded MR | BA57: Medical records needed | BB57: CO_252 - An attachment/other documentation is required to adjudicate this claim/service | BC57: PIQ-86274627 | BF57: =IF(TRIM($A57)="Finalized","Closed",IF($BD57="","No review date set",IF($BD57<TODAY(),"OVERDUE",IF($BD57-TODAY()<=7,"Due within 7 days","Scheduled")))) -> Closed | BG57: =IF($K57="","",TODAY()-$K57) -> 114 | BH57: =IFERROR(LEFT(IF($B57="","Notes, ","")&IF($K57="","Latest Date Worked, ","")&IF($AY57="","Last Action, ","")&IF(AND(OR(TRIM($A57)="Denied",TRIM($A57)="Rejected"),$BA57=""),"Denial Reason, ","")&IF(AND(TRIM($A57)="Denied",$BB57="",TRIM($BA57)<>"NO DENIAL"),"Denial Code, ","")&IF(AND(TRIM($A57)<>"Finalized",$BD57=""),"Next Review Date, ","")&IF(AND(TRIM($A57)<>"Finalized",$BE57=""),"Next Step, ","")&IF(AND(TRIM($A57)="Finalized",$AV57="",$AR57="",$AT57="",$AX57="",$AW57=""),"CPT outcome, ",""),LEN(IF($B57="","Notes, ","")&IF($K57="","Latest Date Worked, ","")&IF($AY57="","Last Action, ","")&IF(AND(OR(TRIM($A57)="Denied",TRIM($A57)="Rejected"),$BA57=""),"Denial Reason, ","")&IF(AND(TRIM($A57)="Denied",$BB57="",TRIM($BA57)<>"NO DENIAL"),"Denial Code, ","")&IF(AND(TRIM($A57)<>"Finalized",$BD57=""),"Next Review Date, ","")&IF(AND(TRIM($A57)<>"Finalized",$BE57=""),"Next Step, ","")&IF(AND(TRIM($A57)="Finalized",$AV57="",$AR57="",$AT57="",$AX57="",$AW57=""),"CPT outcome, ",""))-2),"") | BI57: =IF($BB57="","",IFERROR(INDEX('Denial Codes'!$C:$C,MATCH(LEFT($BB57,FIND(" - ",$BB57&" - ")+2)&"*",'Denial Codes'!$A:$A,0)),"")) -> Medical records needed | BJ57: =IF($BA57="","",IFERROR(INDEX(Lists!$B:$B,MATCH(TRIM($BA57),Lists!$A:$A,0))&"","")) -> Upload the MR on the payer portal, note the PIQ/reference number and set a review date.
A58: Denied | B58: Edited dx order, and resubmitted | C58: 571606836 | D58: 46113 | E58: HF539049375 | F58: 46084 | G58: CIGNA HealthSprings | H58: CIGNA HealthSprings | I58: No Payer | J58: 93970 x1; 93923 x1 | K58: 46278 | L58: =IF($O58="","",$O58-TODAY()) -> -137 | M58: =IF(AND(TRIM($A58)="Finalized",$K58<>""),"",IF($F58="","",$F58+90-TODAY())) -> -137 | N58: =IF(AND(TRIM($A58)="Finalized",$K58<>""),"",IF($D58="","",$D58+180-TODAY())) -> -18 | O58: =IF(AND(TRIM($A58)="Finalized",$K58<>""),"",DATE(2026,6,1)) -> 46174 | P58: 90 days | Q58: CIGNA / CIGNA MEDICARE | R58: 90 days | S58: Date of service | T58: 180 days | U58: Processed date | V58: 2026-03 March | W58: US | AA58: 1 | AB58: =IF($F58="","",TODAY()-$F58) -> 227 | AC58: 93970 | AD58: 93923 | AJ58: M5416 | AK58: R600 | AL58: E139 | AM58: I10 | AO58: LEATHEM, JARRETT | AP58: ASAP - Gilbert | AQ58: 46106 | AV58: 93970 | AW58: 93923 | AX58: 93970, 93923 | AY58: Resubmitted | BA58: Diagnosis issue | BB58: CO_131 - Claim specific negotiated discount | BD58: 46308 | BF58: =IF(TRIM($A58)="Finalized","Closed",IF($BD58="","No review date set",IF($BD58<TODAY(),"OVERDUE",IF($BD58-TODAY()<=7,"Due within 7 days","Scheduled")))) -> OVERDUE | BG58: =IF($K58="","",TODAY()-$K58) -> 33 | BH58: =IFERROR(LEFT(IF($B58="","Notes, ","")&IF($K58="","Latest Date Worked, ","")&IF($AY58="","Last Action, ","")&IF(AND(OR(TRIM($A58)="Denied",TRIM($A58)="Rejected"),$BA58=""),"Denial Reason, ","")&IF(AND(TRIM($A58)="Denied",$BB58="",TRIM($BA58)<>"NO DENIAL"),"Denial Code, ","")&IF(AND(TRIM($A58)<>"Finalized",$BD58=""),"Next Review Date, ","")&IF(AND(TRIM($A58)<>"Finalized",$BE58=""),"Next Step, ","")&IF(AND(TRIM($A58)="Finalized",$AV58="",$AR58="",$AT58="",$AX58="",$AW58=""),"CPT outcome, ",""),LEN(IF($B58="","Notes, ","")&IF($K58="","Latest Date Worked, ","")&IF($AY58="","Last Action, ","")&IF(AND(OR(TRIM($A58)="Denied",TRIM($A58)="Rejected"),$BA58=""),"Denial Reason, ","")&IF(AND(TRIM($A58)="Denied",$BB58="",TRIM($BA58)<>"NO DENIAL"),"Denial Code, ","")&IF(AND(TRIM($A58)<>"Finalized",$BD58=""),"Next Review Date, ","")&IF(AND(TRIM($A58)<>"Finalized",$BE58=""),"Next Step, ","")&IF(AND(TRIM($A58)="Finalized",$AV58="",$AR58="",$AT58="",$AX58="",$AW58=""),"CPT outcome, ",""))-2),"") -> Next Step | BI58: =IF($BB58="","",IFERROR(INDEX('Denial Codes'!$C:$C,MATCH(LEFT($BB58,FIND(" - ",$BB58&" - ")+2)&"*",'Denial Codes'!$A:$A,0)),"")) -> Other | BJ58: =IF($BA58="","",IFERROR(INDEX(Lists!$B:$B,MATCH(TRIM($BA58),Lists!$A:$A,0))&"","")) -> Review the diagnosis codes and pointers with the chart; correct and resubmit.
A59: Denied | B59: Jess corrected rendering to TIMOTHY BAUGHER, and resubmitted - We had JARRETT LEATHEM | C59: 566722180 | D59: 46134 | E59: HF537685966 | F59: 46085 | G59: Blue Cross Blue Shield of Arizona (BCBS AZ) | H59: Blue Cross Blue Shield of Arizona (BCBS AZ) | I59: Medicare Part B Arizona * | J59: 99493 x1; 99494 x2 | K59: 46231 | L59: =IF($O59="","",$O59-TODAY()) -> -136 | M59: =IF(AND(TRIM($A59)="Finalized",$K59<>""),"",IF($F59="","",$F59+90-TODAY())) -> -136 | N59: =IF(AND(TRIM($A59)="Finalized",$K59<>""),"",IF($D59="","",$D59+365-TODAY())) -> 188 | O59: =IF(AND(TRIM($A59)="Finalized",$K59<>""),"",DATE(2026,6,2)) -> 46175 | P59: 90 days | Q59: BCBS | R59: 90 days | S59: Date of service | T59: 365 days | U59: Processed date | V59: 2026-03 March | W59: BH | AA59: 1, 2 | AB59: =IF($F59="","",TODAY()-$F59) -> 226 | AC59: 99493 | AD59: 99494 | AJ59: F330 | AO59: BAUGHER, TIMOTHY | AP59: ASAP - Gilbert | AQ59: 46119 | AY59: Resubmitted | BA59: Credentialing / out of network | BD59: 46262 | BF59: =IF(TRIM($A59)="Finalized","Closed",IF($BD59="","No review date set",IF($BD59<TODAY(),"OVERDUE",IF($BD59-TODAY()<=7,"Due within 7 days","Scheduled")))) -> OVERDUE | BG59: =IF($K59="","",TODAY()-$K59) -> 80 | BH59: =IFERROR(LEFT(IF($B59="","Notes, ","")&IF($K59="","Latest Date Worked, ","")&IF($AY59="","Last Action, ","")&IF(AND(OR(TRIM($A59)="Denied",TRIM($A59)="Rejected"),$BA59=""),"Denial Reason, ","")&IF(AND(TRIM($A59)="Denied",$BB59="",TRIM($BA59)<>"NO DENIAL"),"Denial Code, ","")&IF(AND(TRIM($A59)<>"Finalized",$BD59=""),"Next Review Date, ","")&IF(AND(TRIM($A59)<>"Finalized",$BE59=""),"Next Step, ","")&IF(AND(TRIM($A59)="Finalized",$AV59="",$AR59="",$AT59="",$AX59="",$AW59=""),"CPT outcome, ",""),LEN(IF($B59="","Notes, ","")&IF($K59="","Latest Date Worked, ","")&IF($AY59="","Last Action, ","")&IF(AND(OR(TRIM($A59)="Denied",TRIM($A59)="Rejected"),$BA59=""),"Denial Reason, ","")&IF(AND(TRIM($A59)="Denied",$BB59="",TRIM($BA59)<>"NO DENIAL"),"Denial Code, ","")&IF(AND(TRIM($A59)<>"Finalized",$BD59=""),"Next Review Date, ","")&IF(AND(TRIM($A59)<>"Finalized",$BE59=""),"Next Step, ","")&IF(AND(TRIM($A59)="Finalized",$AV59="",$AR59="",$AT59="",$AX59="",$AW59=""),"CPT outcome, ",""))-2),"") -> Denial Code, Next Step | BI59: =IF($BB59="","",IFERROR(INDEX('Denial Codes'!$C:$C,MATCH(LEFT($BB59,FIND(" - ",$BB59&" - ")+2)&"*",'Denial Codes'!$A:$A,0)),"")) | BJ59: =IF($BA59="","",IFERROR(INDEX(Lists!$B:$B,MATCH(TRIM($BA59),Lists!$A:$A,0))&"","")) -> Check provider enrollment, NPI/TIN and network status; appeal once credentialing is confirmed.
A60: Denied | B60: Recon sent to fax 615-401-4642 by Christian J | C60: 552284225 | D60: 46204 | E60: HF517981468 | F60: 46085 | G60: HealthSpring Medicare Advantage | H60: HealthSpring Medicare Advantage | I60: No Payer | J60: 63048 x1 | K60: 46282 | L60: =IF($O60="","",$O60-TODAY()) -> -136 | M60: =IF(AND(TRIM($A60)="Finalized",$K60<>""),"",IF($F60="","",$F60+90-TODAY())) -> -136 | N60: =IF(AND(TRIM($A60)="Finalized",$K60<>""),"",IF($D60="","",$D60+180-TODAY())) -> 73 | O60: =IF(AND(TRIM($A60)="Finalized",$K60<>""),"",DATE(2026,6,2)) -> 46175 | P60: 90 days | Q60: CIGNA / CIGNA MEDICARE | R60: 90 days | S60: Date of service | T60: 180 days | U60: Processed date | V60: 2026-03 March | W60: ORTHO | AA60: 1 | AB60: =IF($F60="","",TODAY()-$F60) -> 226 | AC60: 63048 | AJ60: M4316 | AK60: M4726 | AL60: M5416 | AM60: M4120 | AO60: MCCUNNIFF, PETER | AP60: ASAP Surgery Centers North Valley LLC | AQ60: 46197 | AX60: 63048 | AY60: Recon filed | BA60: Place of service | BB60: CO_5 - The procedure code/type of bill is inconsistent with the place of service | BD60: 46343 | BF60: =IF(TRIM($A60)="Finalized","Closed",IF($BD60="","No review date set",IF($BD60<TODAY(),"OVERDUE",IF($BD60-TODAY()<=7,"Due within 7 days","Scheduled")))) -> Scheduled | BG60: =IF($K60="","",TODAY()-$K60) -> 29 | BH60: =IFERROR(LEFT(IF($B60="","Notes, ","")&IF($K60="","Latest Date Worked, ","")&IF($AY60="","Last Action, ","")&IF(AND(OR(TRIM($A60)="Denied",TRIM($A60)="Rejected"),$BA60=""),"Denial Reason, ","")&IF(AND(TRIM($A60)="Denied",$BB60="",TRIM($BA60)<>"NO DENIAL"),"Denial Code, ","")&IF(AND(TRIM($A60)<>"Finalized",$BD60=""),"Next Review Date, ","")&IF(AND(TRIM($A60)<>"Finalized",$BE60=""),"Next Step, ","")&IF(AND(TRIM($A60)="Finalized",$AV60="",$AR60="",$AT60="",$AX60="",$AW60=""),"CPT outcome, ",""),LEN(IF($B60="","Notes, ","")&IF($K60="","Latest Date Worked, ","")&IF($AY60="","Last Action, ","")&IF(AND(OR(TRIM($A60)="Denied",TRIM($A60)="Rejected"),$BA60=""),"Denial Reason, ","")&IF(AND(TRIM($A60)="Denied",$BB60="",TRIM($BA60)<>"NO DENIAL"),"Denial Code, ","")&IF(AND(TRIM($A60)<>"Finalized",$BD60=""),"Next Review Date, ","")&IF(AND(TRIM($A60)<>"Finalized",$BE60=""),"Next Step, ","")&IF(AND(TRIM($A60)="Finalized",$AV60="",$AR60="",$AT60="",$AX60="",$AW60=""),"CPT outcome, ",""))-2),"") -> Next Step | BI60: =IF($BB60="","",IFERROR(INDEX('Denial Codes'!$C:$C,MATCH(LEFT($BB60,FIND(" - ",$BB60&" - ")+2)&"*",'Denial Codes'!$A:$A,0)),"")) -> Place of service | BJ60: =IF($BA60="","",IFERROR(INDEX(Lists!$B:$B,MATCH(TRIM($BA60),Lists!$A:$A,0))&"","")) -> Verify the place of service (inpatient/outpatient) and correct the claim.
A61: Finalized | B61: PAID - Optum has no record of 99492 - that code was billed to UHC, not Optum - Resubmitted with 99492 | C61: 551769931 | D61: 46141 | E61: HF372010397 | F61: 46086 | G61: Optum Care Medical Network of Arizona, Utah, & Washington (LifePrint) | H61: Optum Care Medical Network of Arizona, Utah, & Washington (LifePrint) | I61: No Payer | J61: 99493 x1; 99494 x1 | K61: 46265 | L61: =IF($O61="","",$O61-TODAY()) | M61: =IF(AND(TRIM($A61)="Finalized",$K61<>""),"",IF($D61="","",$D61+365-TODAY())) | N61: =IF(AND(TRIM($A61)="Finalized",$K61<>""),"",IF($D61="","",$D61+365-TODAY())) | O61: =IF(AND(TRIM($A61)="Finalized",$K61<>""),"",DATE(2026,6,3)) | P61: 90 days | Q61: OPTUM | R61: 365 days | S61: Processed date | T61: 365 days | U61: Processed date | V61: 2026-03 March | W61: BH | AA61: 1 | AB61: =IF($F61="","",TODAY()-$F61) -> 225 | AC61: 99493 | AD61: 99494 | AJ61: F1190 | AO61: LEATHEM, JARRETT | AP61: ASAP - DEER VALLEY | AQ61: 46119 | AV61: 99492, 99494 | AX61: 99492, 99493, 99494 | AY61: Payment posted | AZ61: Resubmitted | BA61: Coding / billing error | BB61: OA_246 - This non-payable code is for required reporting only | BF61: =IF(TRIM($A61)="Finalized","Closed",IF($BD61="","No review date set",IF($BD61<TODAY(),"OVERDUE",IF($BD61-TODAY()<=7,"Due within 7 days","Scheduled")))) -> Closed | BG61: =IF($K61="","",TODAY()-$K61) -> 46 | BH61: =IFERROR(LEFT(IF($B61="","Notes, ","")&IF($K61="","Latest Date Worked, ","")&IF($AY61="","Last Action, ","")&IF(AND(OR(TRIM($A61)="Denied",TRIM($A61)="Rejected"),$BA61=""),"Denial Reason, ","")&IF(AND(TRIM($A61)="Denied",$BB61="",TRIM($BA61)<>"NO DENIAL"),"Denial Code, ","")&IF(AND(TRIM($A61)<>"Finalized",$BD61=""),"Next Review Date, ","")&IF(AND(TRIM($A61)<>"Finalized",$BE61=""),"Next Step, ","")&IF(AND(TRIM($A61)="Finalized",$AV61="",$AR61="",$AT61="",$AX61="",$AW61=""),"CPT outcome, ",""),LEN(IF($B61="","Notes, ","")&IF($K61="","Latest Date Worked, ","")&IF($AY61="","Last Action, ","")&IF(AND(OR(TRIM($A61)="Denied",TRIM($A61)="Rejected"),$BA61=""),"Denial Reason, ","")&IF(AND(TRIM($A61)="Denied",$BB61="",TRIM($BA61)<>"NO DENIAL"),"Denial Code, ","")&IF(AND(TRIM($A61)<>"Finalized",$BD61=""),"Next Review Date, ","")&IF(AND(TRIM($A61)<>"Finalized",$BE61=""),"Next Step, ","")&IF(AND(TRIM($A61)="Finalized",$AV61="",$AR61="",$AT61="",$AX61="",$AW61=""),"CPT outcome, ",""))-2),"") | BI61: =IF($BB61="","",IFERROR(INDEX('Denial Codes'!$C:$C,MATCH(LEFT($BB61,FIND(" - ",$BB61&" - ")+2)&"*",'Denial Codes'!$A:$A,0)),"")) -> Coding / billing error | BJ61: =IF($BA61="","",IFERROR(INDEX(Lists!$B:$B,MATCH(TRIM($BA61),Lists!$A:$A,0))&"","")) -> Fix the code, units, charge or other claim data and resubmit as a corrected claim.
A62: Finalized | B62: PAID - Corrected rendering provider, and resubmitted | C62: 551874008 | D62: 46121 | E62: HF515864933 | F62: 46087 | G62: Optum Care Medical Network of Arizona, Utah, & Washington (LifePrint) | H62: Optum Care Medical Network of Arizona, Utah, & Washington (LifePrint) | I62: No Payer | J62: 99494 x1; 99492 x1 | K62: 46265 | L62: =IF($O62="","",$O62-TODAY()) | M62: =IF(AND(TRIM($A62)="Finalized",$K62<>""),"",IF($D62="","",$D62+365-TODAY())) | N62: =IF(AND(TRIM($A62)="Finalized",$K62<>""),"",IF($D62="","",$D62+365-TODAY())) | O62: =IF(AND(TRIM($A62)="Finalized",$K62<>""),"",DATE(2026,6,4)) | P62: 90 days | Q62: OPTUM | R62: 365 days | S62: Processed date | T62: 365 days | U62: Processed date | V62: 2026-03 March | W62: BH | AA62: 1 | AB62: =IF($F62="","",TODAY()-$F62) -> 224 | AC62: 99494 | AD62: 99492 | AJ62: F4320 | AO62: KRAUSE, JEFFREY | AP62: ASAP - DEER VALLEY | AQ62: 46119 | AV62: 99494, 99492 | AX62: 99494, 99492 | AY62: Payment posted | AZ62: Resubmitted | BA62: Credentialing / out of network | BB62: CO_B7 - This provider was not certified/eligible to be paid for this procedure/service on this date of service | BF62: =IF(TRIM($A62)="Finalized","Closed",IF($BD62="","No review date set",IF($BD62<TODAY(),"OVERDUE",IF($BD62-TODAY()<=7,"Due within 7 days","Scheduled")))) -> Closed | BG62: =IF($K62="","",TODAY()-$K62) -> 46 | BH62: =IFERROR(LEFT(IF($B62="","Notes, ","")&IF($K62="","Latest Date Worked, ","")&IF($AY62="","Last Action, ","")&IF(AND(OR(TRIM($A62)="Denied",TRIM($A62)="Rejected"),$BA62=""),"Denial Reason, ","")&IF(AND(TRIM($A62)="Denied",$BB62="",TRIM($BA62)<>"NO DENIAL"),"Denial Code, ","")&IF(AND(TRIM($A62)<>"Finalized",$BD62=""),"Next Review Date, ","")&IF(AND(TRIM($A62)<>"Finalized",$BE62=""),"Next Step, ","")&IF(AND(TRIM($A62)="Finalized",$AV62="",$AR62="",$AT62="",$AX62="",$AW62=""),"CPT outcome, ",""),LEN(IF($B62="","Notes, ","")&IF($K62="","Latest Date Worked, ","")&IF($AY62="","Last Action, ","")&IF(AND(OR(TRIM($A62)="Denied",TRIM($A62)="Rejected"),$BA62=""),"Denial Reason, ","")&IF(AND(TRIM($A62)="Denied",$BB62="",TRIM($BA62)<>"NO DENIAL"),"Denial Code, ","")&IF(AND(TRIM($A62)<>"Finalized",$BD62=""),"Next Review Date, ","")&IF(AND(TRIM($A62)<>"Finalized",$BE62=""),"Next Step, ","")&IF(AND(TRIM($A62)="Finalized",$AV62="",$AR62="",$AT62="",$AX62="",$AW62=""),"CPT outcome, ",""))-2),"") | BI62: =IF($BB62="","",IFERROR(INDEX('Denial Codes'!$C:$C,MATCH(LEFT($BB62,FIND(" - ",$BB62&" - ")+2)&"*",'Denial Codes'!$A:$A,0)),"")) -> Credentialing / out of network | BJ62: =IF($BA62="","",IFERROR(INDEX(Lists!$B:$B,MATCH(TRIM($BA62),Lists!$A:$A,0))&"","")) -> Check provider enrollment, NPI/TIN and network status; appeal once credentialing is confirmed.
A63: Pending | B63: secondary - Rep Gloria C - Ins started the refund request - Rep sent claim back to have it reprocessed - Ticket # SF20260903906271400 - TAT 30 bd - OP by secondary insurance | C63: 551830492 | D63: 46196 | E63: HF417864409 | F63: 46087 | G63: UnitedHealthcare Community Plan / Arizona Long Term Care | H63: United Healthcare | I63: UnitedHealthcare Community Plan / Arizona Long Term Care | J63: 99492 x1; 99494 x1 | K63: 46268 | L63: =IF($O63="","",$O63-TODAY()) -> -134 | M63: =IF(AND(TRIM($A63)="Finalized",$K63<>""),"",IF($D63="","",$D63+180-TODAY())) -> 65 | N63: =IF(AND(TRIM($A63)="Finalized",$K63<>""),"",IF($D63="","",$D63+365-TODAY())) -> 250 | O63: =IF(AND(TRIM($A63)="Finalized",$K63<>""),"",DATE(2026,6,4)) -> 46177 | P63: 90 days | Q63: UHC COMMERCIAL | R63: 180 days | S63: Processed date | T63: 365 days | U63: Processed date | V63: 2026-03 March | W63: BH | AA63: 1 | AB63: =IF($F63="","",TODAY()-$F63) -> 224 | AC63: 99492 | AD63: 99494 | AJ63: F39 | AN63: 560056768 | AO63: LEATHEM, JARRETT | AP63: ASAP - Gilbert | AQ63: 46119 | AV63: 99492, 99494 | AX63: 99492, 99494 | AY63: Contacted payer | BC63: Ticket # SF20260903906271400; Call ref # 188336955 | BD63: 46298 | BE63: Follow up on refund/reprocessing ticket SF20260903906271400 | BF63: =IF(TRIM($A63)="Finalized","Closed",IF($BD63="","No review date set",IF($BD63<TODAY(),"OVERDUE",IF($BD63-TODAY()<=7,"Due within 7 days","Scheduled")))) -> OVERDUE | BG63: =IF($K63="","",TODAY()-$K63) -> 43 | BH63: =IFERROR(LEFT(IF($B63="","Notes, ","")&IF($K63="","Latest Date Worked, ","")&IF($AY63="","Last Action, ","")&IF(AND(OR(TRIM($A63)="Denied",TRIM($A63)="Rejected"),$BA63=""),"Denial Reason, ","")&IF(AND(TRIM($A63)="Denied",$BB63="",TRIM($BA63)<>"NO DENIAL"),"Denial Code, ","")&IF(AND(TRIM($A63)<>"Finalized",$BD63=""),"Next Review Date, ","")&IF(AND(TRIM($A63)<>"Finalized",$BE63=""),"Next Step, ","")&IF(AND(TRIM($A63)="Finalized",$AV63="",$AR63="",$AT63="",$AX63="",$AW63=""),"CPT outcome, ",""),LEN(IF($B63="","Notes, ","")&IF($K63="","Latest Date Worked, ","")&IF($AY63="","Last Action, ","")&IF(AND(OR(TRIM($A63)="Denied",TRIM($A63)="Rejected"),$BA63=""),"Denial Reason, ","")&IF(AND(TRIM($A63)="Denied",$BB63="",TRIM($BA63)<>"NO DENIAL"),"Denial Code, ","")&IF(AND(TRIM($A63)<>"Finalized",$BD63=""),"Next Review Date, ","")&IF(AND(TRIM($A63)<>"Finalized",$BE63=""),"Next Step, ","")&IF(AND(TRIM($A63)="Finalized",$AV63="",$AR63="",$AT63="",$AX63="",$AW63=""),"CPT outcome, ",""))-2),"") | BI63: =IF($BB63="","",IFERROR(INDEX('Denial Codes'!$C:$C,MATCH(LEFT($BB63,FIND(" - ",$BB63&" - ")+2)&"*",'Denial Codes'!$A:$A,0)),"")) | BJ63: =IF($BA63="","",IFERROR(INDEX(Lists!$B:$B,MATCH(TRIM($BA63),Lists!$A:$A,0))&"",""))
A64: Finalized | B64: Adjusted balance - Auth only included 62330 | C64: 551964467 | D64: 46097 | E64: HF490461961 | F64: 46087 | G64: Humana Gold Plus HMO | H64: Humana Gold Plus HMO | I64: No Payer | J64: 63047 x1 | K64: 46279 | L64: =IF($O64="","",$O64-TODAY()) | M64: =IF(AND(TRIM($A64)="Finalized",$K64<>""),"",IF($F64="","",$F64+90-TODAY())) | N64: =IF(AND(TRIM($A64)="Finalized",$K64<>""),"",IF($D64="","",$D64+540-TODAY())) | O64: =IF(AND(TRIM($A64)="Finalized",$K64<>""),"",DATE(2026,6,4)) | P64: 90 days | Q64: HUMANA MA | R64: 90 days | S64: Date of service | T64: 540 days | U64: Processed date | V64: 2026-03 March | W64: ORTHO | AA64: 1 | AB64: =IF($F64="","",TODAY()-$F64) -> 224 | AC64: 63047 | AJ64: M48062 | AO64: MORALES, DAVID | AP64: ASAP Surgery Centers North Valley LLC | AQ64: 46091 | AT64: 63047 | AU64: CO_39 - Services denied at the time authorization/pre-certification was requested | AY64: Adjusted balance | BA64: No authorization | BB64: CO_39 - Services denied at the time authorization/pre-certification was requested | BF64: =IF(TRIM($A64)="Finalized","Closed",IF($BD64="","No review date set",IF($BD64<TODAY(),"OVERDUE",IF($BD64-TODAY()<=7,"Due within 7 days","Scheduled")))) -> Closed | BG64: =IF($K64="","",TODAY()-$K64) -> 32 | BH64: =IFERROR(LEFT(IF($B64="","Notes, ","")&IF($K64="","Latest Date Worked, ","")&IF($AY64="","Last Action, ","")&IF(AND(OR(TRIM($A64)="Denied",TRIM($A64)="Rejected"),$BA64=""),"Denial Reason, ","")&IF(AND(TRIM($A64)="Denied",$BB64="",TRIM($BA64)<>"NO DENIAL"),"Denial Code, ","")&IF(AND(TRIM($A64)<>"Finalized",$BD64=""),"Next Review Date, ","")&IF(AND(TRIM($A64)<>"Finalized",$BE64=""),"Next Step, ","")&IF(AND(TRIM($A64)="Finalized",$AV64="",$AR64="",$AT64="",$AX64="",$AW64=""),"CPT outcome, ",""),LEN(IF($B64="","Notes, ","")&IF($K64="","Latest Date Worked, ","")&IF($AY64="","Last Action, ","")&IF(AND(OR(TRIM($A64)="Denied",TRIM($A64)="Rejected"),$BA64=""),"Denial Reason, ","")&IF(AND(TRIM($A64)="Denied",$BB64="",TRIM($BA64)<>"NO DENIAL"),"Denial Code, ","")&IF(AND(TRIM($A64)<>"Finalized",$BD64=""),"Next Review Date, ","")&IF(AND(TRIM($A64)<>"Finalized",$BE64=""),"Next Step, ","")&IF(AND(TRIM($A64)="Finalized",$AV64="",$AR64="",$AT64="",$AX64="",$AW64=""),"CPT outcome, ",""))-2),"") | BI64: =IF($BB64="","",IFERROR(INDEX('Denial Codes'!$C:$C,MATCH(LEFT($BB64,FIND(" - ",$BB64&" - ")+2)&"*",'Denial Codes'!$A:$A,0)),"")) -> No authorization | BJ64: =IF($BA64="","",IFERROR(INDEX(Lists!$B:$B,MATCH(TRIM($BA64),Lists!$A:$A,0))&"","")) -> Check the portal for an auth; request a retro-auth or file an appeal with the auth number, then resubmit.
A65: Denied | B65: Filed appeal # Z264AZW09999 on portal - Basis: add-on to auth'd/paid 63047, intraop findings. Op note attached - Add-on 63048 requires auth according to medicaid auth tool - Auth # OP4987640976 didn't include 63048 | C65: 564578362 | D65: 46218 | E65: HF496014369 | F65: 46057 | G65: Arizona Complete Health (Centene) | H65: Arizona Complete Health (Centene) | I65: No Payer | J65: 63048 x1 | K65: 46285 | L65: =IF($O65="","",$O65-TODAY()) -> -134 | M65: =IF(AND(TRIM($A65)="Finalized",$K65<>""),"",IF($F65="","",$F65+365-TODAY())) -> 111 | N65: =IF(AND(TRIM($A65)="Finalized",$K65<>""),"",IF($F65="","",$F65+365-TODAY())) -> 111 | O65: =IF(AND(TRIM($A65)="Finalized",$K65<>""),"",DATE(2026,6,4)) -> 46177 | P65: 120 days | Q65: AZ COMPLETE | R65: 365 days | S65: Date of service | T65: 365 days | U65: Date of service | V65: 2026-02 February | W65: ORTHO | AA65: 1 | AB65: =IF($F65="","",TODAY()-$F65) -> 254 | AC65: 63048 | AJ65: M48062 | AK65: M51370 | AO65: MCCUNNIFF, PETER | AP65: ASAP Surgery Centers North Valley LLC | AQ65: 46077 | AX65: 63048 | AY65: Appeal filed | BA65: No authorization | BC65: Appeal # Z264AZW09999; Auth # OP4987640976 | BD65: 46315 | BF65: =IF(TRIM($A65)="Finalized","Closed",IF($BD65="","No review date set",IF($BD65<TODAY(),"OVERDUE",IF($BD65-TODAY()<=7,"Due within 7 days","Scheduled")))) -> Due within 7 days | BG65: =IF($K65="","",TODAY()-$K65) -> 26 | BH65: =IFERROR(LEFT(IF($B65="","Notes, ","")&IF($K65="","Latest Date Worked, ","")&IF($AY65="","Last Action, ","")&IF(AND(OR(TRIM($A65)="Denied",TRIM($A65)="Rejected"),$BA65=""),"Denial Reason, ","")&IF(AND(TRIM($A65)="Denied",$BB65="",TRIM($BA65)<>"NO DENIAL"),"Denial Code, ","")&IF(AND(TRIM($A65)<>"Finalized",$BD65=""),"Next Review Date, ","")&IF(AND(TRIM($A65)<>"Finalized",$BE65=""),"Next Step, ","")&IF(AND(TRIM($A65)="Finalized",$AV65="",$AR65="",$AT65="",$AX65="",$AW65=""),"CPT outcome, ",""),LEN(IF($B65="","Notes, ","")&IF($K65="","Latest Date Worked, ","")&IF($AY65="","Last Action, ","")&IF(AND(OR(TRIM($A65)="Denied",TRIM($A65)="Rejected"),$BA65=""),"Denial Reason, ","")&IF(AND(TRIM($A65)="Denied",$BB65="",TRIM($BA65)<>"NO DENIAL"),"Denial Code, ","")&IF(AND(TRIM($A65)<>"Finalized",$BD65=""),"Next Review Date, ","")&IF(AND(TRIM($A65)<>"Finalized",$BE65=""),"Next Step, ","")&IF(AND(TRIM($A65)="Finalized",$AV65="",$AR65="",$AT65="",$AX65="",$AW65=""),"CPT outcome, ",""))-2),"") -> Denial Code, Next Step | BI65: =IF($BB65="","",IFERROR(INDEX('Denial Codes'!$C:$C,MATCH(LEFT($BB65,FIND(" - ",$BB65&" - ")+2)&"*",'Denial Codes'!$A:$A,0)),"")) | BJ65: =IF($BA65="","",IFERROR(INDEX(Lists!$B:$B,MATCH(TRIM($BA65),Lists!$A:$A,0))&"","")) -> Check the portal for an auth; request a retro-auth or file an appeal with the auth number, then resubmit.
A66: PAID | C66: 553643849 | D66: 46203 | E66: HF537038069 | F66: 46087 | G66: Blue Cross Blue Shield of Arizona (BCBS AZ) | H66: Blue Cross Blue Shield of Arizona (BCBS AZ) | I66: No Payer | J66: 22853 x1; 22551 x1; 22845+59 x1 | L66: =IF($O66="","",$O66-TODAY()) -> -134 | M66: =IF(AND(TRIM($A66)="Finalized",$K66<>""),"",IF($F66="","",$F66+90-TODAY())) -> -134 | N66: =IF(AND(TRIM($A66)="Finalized",$K66<>""),"",IF($D66="","",$D66+365-TODAY())) -> 257 | O66: =IF(AND(TRIM($A66)="Finalized",$K66<>""),"",DATE(2026,6,4)) -> 46177 | P66: 90 days | Q66: BCBS | R66: 90 days | S66: Date of service | T66: 365 days | U66: Processed date | V66: 2026-03 March | W66: ORTHO | X66: 59 | AA66: 1 | AB66: =IF($F66="","",TODAY()-$F66) -> 224 | AC66: 22853 | AD66: 22551 | AE66: 22845 | AJ66: M4802 | AK66: M50021 | AO66: MAYURAN, VIKRAM | AP66: Banner Desert Medical Center | AQ66: 46197 | AY66: Waiting on payer | BE66: Confirm payment is posted | BF66: =IF(TRIM($A66)="Finalized","Closed",IF($BD66="","No review date set",IF($BD66<TODAY(),"OVERDUE",IF($BD66-TODAY()<=7,"Due within 7 days","Scheduled")))) -> No review date set | BG66: =IF($K66="","",TODAY()-$K66) | BH66: =IFERROR(LEFT(IF($B66="","Notes, ","")&IF($K66="","Latest Date Worked, ","")&IF($AY66="","Last Action, ","")&IF(AND(OR(TRIM($A66)="Denied",TRIM($A66)="Rejected"),$BA66=""),"Denial Reason, ","")&IF(AND(TRIM($A66)="Denied",$BB66="",TRIM($BA66)<>"NO DENIAL"),"Denial Code, ","")&IF(AND(TRIM($A66)<>"Finalized",$BD66=""),"Next Review Date, ","")&IF(AND(TRIM($A66)<>"Finalized",$BE66=""),"Next Step, ","")&IF(AND(TRIM($A66)="Finalized",$AV66="",$AR66="",$AT66="",$AX66="",$AW66=""),"CPT outcome, ",""),LEN(IF($B66="","Notes, ","")&IF($K66="","Latest Date Worked, ","")&IF($AY66="","Last Action, ","")&IF(AND(OR(TRIM($A66)="Denied",TRIM($A66)="Rejected"),$BA66=""),"Denial Reason, ","")&IF(AND(TRIM($A66)="Denied",$BB66="",TRIM($BA66)<>"NO DENIAL"),"Denial Code, ","")&IF(AND(TRIM($A66)<>"Finalized",$BD66=""),"Next Review Date, ","")&IF(AND(TRIM($A66)<>"Finalized",$BE66=""),"Next Step, ","")&IF(AND(TRIM($A66)="Finalized",$AV66="",$AR66="",$AT66="",$AX66="",$AW66=""),"CPT outcome, ",""))-2),"") -> Notes, Latest Date Worked, Next Review Date | BI66: =IF($BB66="","",IFERROR(INDEX('Denial Codes'!$C:$C,MATCH(LEFT($BB66,FIND(" - ",$BB66&" - ")+2)&"*",'Denial Codes'!$A:$A,0)),"")) | BJ66: =IF($BA66="","",IFERROR(INDEX(Lists!$B:$B,MATCH(TRIM($BA66),Lists!$A:$A,0))&"",""))
A67: Denied | B67: Resubmitted to Alignment active on DOS | C67: 569488863 | D67: 46268 | E67: HF509386349 | F67: 46092 | G67: Alignment Health Care | H67: Alignment Health Care | I67: No Payer | J67: 99492 x1; 99494 x1 | K67: 46257 | L67: =IF($O67="","",$O67-TODAY()) | Q67: Not on reference list | V67: 2026-03 March | W67: BH | AA67: 1 | AB67: =IF($F67="","",TODAY()-$F67) -> 219 | AC67: 99492 | AD67: 99494 | AJ67: F1190 | AO67: O'NEIL, ROY | AP67: ASAP - DEER VALLEY | AQ67: 46119 | AY67: Resubmitted | BA67: Eligibility / member ID | BD67: 46288 | BF67: =IF(TRIM($A67)="Finalized","Closed",IF($BD67="","No review date set",IF($BD67<TODAY(),"OVERDUE",IF($BD67-TODAY()<=7,"Due within 7 days","Scheduled")))) -> OVERDUE | BG67: =IF($K67="","",TODAY()-$K67) -> 54 | BH67: =IFERROR(LEFT(IF($B67="","Notes, ","")&IF($K67="","Latest Date Worked, ","")&IF($AY67="","Last Action, ","")&IF(AND(OR(TRIM($A67)="Denied",TRIM($A67)="Rejected"),$BA67=""),"Denial Reason, ","")&IF(AND(TRIM($A67)="Denied",$BB67="",TRIM($BA67)<>"NO DENIAL"),"Denial Code, ","")&IF(AND(TRIM($A67)<>"Finalized",$BD67=""),"Next Review Date, ","")&IF(AND(TRIM($A67)<>"Finalized",$BE67=""),"Next Step, ","")&IF(AND(TRIM($A67)="Finalized",$AV67="",$AR67="",$AT67="",$AX67="",$AW67=""),"CPT outcome, ",""),LEN(IF($B67="","Notes, ","")&IF($K67="","Latest Date Worked, ","")&IF($AY67="","Last Action, ","")&IF(AND(OR(TRIM($A67)="Denied",TRIM($A67)="Rejected"),$BA67=""),"Denial Reason, ","")&IF(AND(TRIM($A67)="Denied",$BB67="",TRIM($BA67)<>"NO DENIAL"),"Denial Code, ","")&IF(AND(TRIM($A67)<>"Finalized",$BD67=""),"Next Review Date, ","")&IF(AND(TRIM($A67)<>"Finalized",$BE67=""),"Next Step, ","")&IF(AND(TRIM($A67)="Finalized",$AV67="",$AR67="",$AT67="",$AX67="",$AW67=""),"CPT outcome, ",""))-2),"") -> Denial Code, Next Step | BI67: =IF($BB67="","",IFERROR(INDEX('Denial Codes'!$C:$C,MATCH(LEFT($BB67,FIND(" - ",$BB67&" - ")+2)&"*",'Denial Codes'!$A:$A,0)),"")) | BJ67: =IF($BA67="","",IFERROR(INDEX(Lists!$B:$B,MATCH(TRIM($BA67),Lists!$A:$A,0))&"","")) -> Verify eligibility; correct the member ID/MBI, name or DOB and resubmit.
A68: Denied | B68: Jess resubmitted claim on 08/31/2026 | C68: 570400502 | D68: 46108 | E68: HF495165589 | F68: 46093 | G68: Humana Gold Plus HMO | H68: Humana Gold Plus HMO | I68: No Payer | J68: 22853 x1; 22845+59 x1; 22551 x1 | K68: 46265 | L68: =IF($O68="","",$O68-TODAY()) -> -128 | M68: =IF(AND(TRIM($A68)="Finalized",$K68<>""),"",IF($F68="","",$F68+90-TODAY())) -> -128 | N68: =IF(AND(TRIM($A68)="Finalized",$K68<>""),"",IF($D68="","",$D68+540-TODAY())) -> 337 | O68: =IF(AND(TRIM($A68)="Finalized",$K68<>""),"",DATE(2026,6,10)) -> 46183 | P68: 90 days | Q68: HUMANA MA | R68: 90 days | S68: Date of service | T68: 540 days | U68: Processed date | V68: 2026-03 March | W68: ORTHO | X68: 59 | AA68: 1 | AB68: =IF($F68="","",TODAY()-$F68) -> 218 | AC68: 22853 | AD68: 22845 | AE68: 22551 | AJ68: M5416 | AK68: M4317 | AO68: Adv Spine and Ortho Partners LLC | AP68: Banner Desert Medical Center | AQ68: 46105 | AV68: 22845, 22551 | AX68: 22853, 22845, 22551 | AY68: Resubmitted | BD68: 46295 | BF68: =IF(TRIM($A68)="Finalized","Closed",IF($BD68="","No review date set",IF($BD68<TODAY(),"OVERDUE",IF($BD68-TODAY()<=7,"Due within 7 days","Scheduled")))) -> OVERDUE | BG68: =IF($K68="","",TODAY()-$K68) -> 46 | BH68: =IFERROR(LEFT(IF($B68="","Notes, ","")&IF($K68="","Latest Date Worked, ","")&IF($AY68="","Last Action, ","")&IF(AND(OR(TRIM($A68)="Denied",TRIM($A68)="Rejected"),$BA68=""),"Denial Reason, ","")&IF(AND(TRIM($A68)="Denied",$BB68="",TRIM($BA68)<>"NO DENIAL"),"Denial Code, ","")&IF(AND(TRIM($A68)<>"Finalized",$BD68=""),"Next Review Date, ","")&IF(AND(TRIM($A68)<>"Finalized",$BE68=""),"Next Step, ","")&IF(AND(TRIM($A68)="Finalized",$AV68="",$AR68="",$AT68="",$AX68="",$AW68=""),"CPT outcome, ",""),LEN(IF($B68="","Notes, ","")&IF($K68="","Latest Date Worked, ","")&IF($AY68="","Last Action, ","")&IF(AND(OR(TRIM($A68)="Denied",TRIM($A68)="Rejected"),$BA68=""),"Denial Reason, ","")&IF(AND(TRIM($A68)="Denied",$BB68="",TRIM($BA68)<>"NO DENIAL"),"Denial Code, ","")&IF(AND(TRIM($A68)<>"Finalized",$BD68=""),"Next Review Date, ","")&IF(AND(TRIM($A68)<>"Finalized",$BE68=""),"Next Step, ","")&IF(AND(TRIM($A68)="Finalized",$AV68="",$AR68="",$AT68="",$AX68="",$AW68=""),"CPT outcome, ",""))-2),"") -> Denial Reason, Denial Code, Next Step | BI68: =IF($BB68="","",IFERROR(INDEX('Denial Codes'!$C:$C,MATCH(LEFT($BB68,FIND(" - ",$BB68&" - ")+2)&"*",'Denial Codes'!$A:$A,0)),"")) | BJ68: =IF($BA68="","",IFERROR(INDEX(Lists!$B:$B,MATCH(TRIM($BA68),Lists!$A:$A,0))&"",""))
A69: Denied | B69: Uploaded op notes from 03/12/2026 to 03/15/2026 - Jess uploaded MR | C69: 553656838 | D69: 46220 | E69: HF536440270 | F69: 46093 | G69: Humana Gold Plus HMO | H69: Humana Gold Plus HMO | I69: No Payer | J69: 22853 x1; 22612 x1 | K69: 46279 | L69: =IF($O69="","",$O69-TODAY()) -> -128 | M69: =IF(AND(TRIM($A69)="Finalized",$K69<>""),"",IF($F69="","",$F69+90-TODAY())) -> -128 | N69: =IF(AND(TRIM($A69)="Finalized",$K69<>""),"",IF($D69="","",$D69+540-TODAY())) -> 449 | O69: =IF(AND(TRIM($A69)="Finalized",$K69<>""),"",DATE(2026,6,10)) -> 46183 | P69: 90 days | Q69: HUMANA MA | R69: 90 days | S69: Date of service | T69: 540 days | U69: Processed date | V69: 2026-03 March | W69: ORTHO | AA69: 1 | AB69: =IF($F69="","",TODAY()-$F69) -> 218 | AC69: 22853 | AD69: 22612 | AJ69: M5416 | AK69: M48061 | AO69: MAYURAN, VIKRAM | AP69: Banner Desert Medical Center | AQ69: 46105 | AY69: Uploaded MR | AZ69: Uploaded MR | BA69: Medical records needed | BB69: CO_252 - An attachment/other documentation is required to adjudicate this claim/service | BC69: Request ID 35165602 | BD69: 46309 | BF69: =IF(TRIM($A69)="Finalized","Closed",IF($BD69="","No review date set",IF($BD69<TODAY(),"OVERDUE",IF($BD69-TODAY()<=7,"Due within 7 days","Scheduled")))) -> OVERDUE | BG69: =IF($K69="","",TODAY()-$K69) -> 32 | BH69: =IFERROR(LEFT(IF($B69="","Notes, ","")&IF($K69="","Latest Date Worked, ","")&IF($AY69="","Last Action, ","")&IF(AND(OR(TRIM($A69)="Denied",TRIM($A69)="Rejected"),$BA69=""),"Denial Reason, ","")&IF(AND(TRIM($A69)="Denied",$BB69="",TRIM($BA69)<>"NO DENIAL"),"Denial Code, ","")&IF(AND(TRIM($A69)<>"Finalized",$BD69=""),"Next Review Date, ","")&IF(AND(TRIM($A69)<>"Finalized",$BE69=""),"Next Step, ","")&IF(AND(TRIM($A69)="Finalized",$AV69="",$AR69="",$AT69="",$AX69="",$AW69=""),"CPT outcome, ",""),LEN(IF($B69="","Notes, ","")&IF($K69="","Latest Date Worked, ","")&IF($AY69="","Last Action, ","")&IF(AND(OR(TRIM($A69)="Denied",TRIM($A69)="Rejected"),$BA69=""),"Denial Reason, ","")&IF(AND(TRIM($A69)="Denied",$BB69="",TRIM($BA69)<>"NO DENIAL"),"Denial Code, ","")&IF(AND(TRIM($A69)<>"Finalized",$BD69=""),"Next Review Date, ","")&IF(AND(TRIM($A69)<>"Finalized",$BE69=""),"Next Step, ","")&IF(AND(TRIM($A69)="Finalized",$AV69="",$AR69="",$AT69="",$AX69="",$AW69=""),"CPT outcome, ",""))-2),"") -> Next Step | BI69: =IF($BB69="","",IFERROR(INDEX('Denial Codes'!$C:$C,MATCH(LEFT($BB69,FIND(" - ",$BB69&" - ")+2)&"*",'Denial Codes'!$A:$A,0)),"")) -> Medical records needed | BJ69: =IF($BA69="","",IFERROR(INDEX(Lists!$B:$B,MATCH(TRIM($BA69),Lists!$A:$A,0))&"","")) -> Upload the MR on the payer portal, note the PIQ/reference number and set a review date.
A70: Denied | B70: Uploaded MR | C70: 555351211 | D70: 46127 | E70: HF404885397 | F70: 46093 | G70: UnitedHealthcare Community Plan / Arizona Long Term Care | H70: UnitedHealthcare Community Plan / Arizona Long Term Care | I70: No Payer | J70: 63655 x1; 63685 x1 | K70: 46279 | L70: =IF($O70="","",$O70-TODAY()) -> -128 | M70: =IF(AND(TRIM($A70)="Finalized",$K70<>""),"",IF($D70="","",$D70+180-TODAY())) -> -4 | N70: =IF(AND(TRIM($A70)="Finalized",$K70<>""),"",IF($D70="","",$D70+365-TODAY())) -> 181 | O70: =IF(AND(TRIM($A70)="Finalized",$K70<>""),"",DATE(2026,6,10)) -> 46183 | P70: 90 days | Q70: UHC COMMUNITY | R70: 180 days | S70: Processed date | T70: 365 days | U70: Processed date | V70: 2026-03 March | W70: ORTHO | AA70: 1 | AB70: =IF($F70="","",TODAY()-$F70) -> 218 | AC70: 63655 | AD70: 63685 | AJ70: M961 | AK70: M5416 | AO70: LUKE, TIMOTHY | AP70: ASAP Surgery Centers North Valley LLC | AQ70: 46120 | AY70: Uploaded MR | BA70: Medical records needed | BB70: CO_252 - An attachment/other documentation is required to adjudicate this claim/service | BC70: PIQ-90849065 | BD70: 46309 | BF70: =IF(TRIM($A70)="Finalized","Closed",IF($BD70="","No review date set",IF($BD70<TODAY(),"OVERDUE",IF($BD70-TODAY()<=7,"Due within 7 days","Scheduled")))) -> OVERDUE | BG70: =IF($K70="","",TODAY()-$K70) -> 32 | BH70: =IFERROR(LEFT(IF($B70="","Notes, ","")&IF($K70="","Latest Date Worked, ","")&IF($AY70="","Last Action, ","")&IF(AND(OR(TRIM($A70)="Denied",TRIM($A70)="Rejected"),$BA70=""),"Denial Reason, ","")&IF(AND(TRIM($A70)="Denied",$BB70="",TRIM($BA70)<>"NO DENIAL"),"Denial Code, ","")&IF(AND(TRIM($A70)<>"Finalized",$BD70=""),"Next Review Date, ","")&IF(AND(TRIM($A70)<>"Finalized",$BE70=""),"Next Step, ","")&IF(AND(TRIM($A70)="Finalized",$AV70="",$AR70="",$AT70="",$AX70="",$AW70=""),"CPT outcome, ",""),LEN(IF($B70="","Notes, ","")&IF($K70="","Latest Date Worked, ","")&IF($AY70="","Last Action, ","")&IF(AND(OR(TRIM($A70)="Denied",TRIM($A70)="Rejected"),$BA70=""),"Denial Reason, ","")&IF(AND(TRIM($A70)="Denied",$BB70="",TRIM($BA70)<>"NO DENIAL"),"Denial Code, ","")&IF(AND(TRIM($A70)<>"Finalized",$BD70=""),"Next Review Date, ","")&IF(AND(TRIM($A70)<>"Finalized",$BE70=""),"Next Step, ","")&IF(AND(TRIM($A70)="Finalized",$AV70="",$AR70="",$AT70="",$AX70="",$AW70=""),"CPT outcome, ",""))-2),"") -> Next Step | BI70: =IF($BB70="","",IFERROR(INDEX('Denial Codes'!$C:$C,MATCH(LEFT($BB70,FIND(" - ",$BB70&" - ")+2)&"*",'Denial Codes'!$A:$A,0)),"")) -> Medical records needed | BJ70: =IF($BA70="","",IFERROR(INDEX(Lists!$B:$B,MATCH(TRIM($BA70),Lists!$A:$A,0))&"","")) -> Upload the MR on the payer portal, note the PIQ/reference number and set a review date.
A71: Denied | B71: Edited insured's info, and resubmitted | C71: 570820956 | D71: 46274 | E71: HF492208813 | F71: 46097 | G71: Blue Cross Blue Shield of Arizona (BCBS AZ) | H71: Blue Cross Blue Shield of Arizona (BCBS AZ) | I71: No Payer | J71: 99494 x1; 99492 x1 | K71: 46268 | L71: =IF($O71="","",$O71-TODAY()) -> -124 | M71: =IF(AND(TRIM($A71)="Finalized",$K71<>""),"",IF($F71="","",$F71+90-TODAY())) -> -124 | N71: =IF(AND(TRIM($A71)="Finalized",$K71<>""),"",IF($D71="","",$D71+365-TODAY())) -> 328 | O71: =IF(AND(TRIM($A71)="Finalized",$K71<>""),"",DATE(2026,6,14)) -> 46187 | P71: 90 days | Q71: BCBS | R71: 90 days | S71: Date of service | T71: 365 days | U71: Processed date | V71: 2026-03 March | W71: BH | AA71: 1 | AB71: =IF($F71="","",TODAY()-$F71) -> 214 | AC71: 99494 | AD71: 99492 | AJ71: F1190 | AK71: F411 | AO71: MEARS, CHAD | AP71: ASAP Peoria | AQ71: 46119 | AY71: Resubmitted | BA71: Eligibility / member ID | BD71: 46298 | BF71: =IF(TRIM($A71)="Finalized","Closed",IF($BD71="","No review date set",IF($BD71<TODAY(),"OVERDUE",IF($BD71-TODAY()<=7,"Due within 7 days","Scheduled")))) -> OVERDUE | BG71: =IF($K71="","",TODAY()-$K71) -> 43 | BH71: =IFERROR(LEFT(IF($B71="","Notes, ","")&IF($K71="","Latest Date Worked, ","")&IF($AY71="","Last Action, ","")&IF(AND(OR(TRIM($A71)="Denied",TRIM($A71)="Rejected"),$BA71=""),"Denial Reason, ","")&IF(AND(TRIM($A71)="Denied",$BB71="",TRIM($BA71)<>"NO DENIAL"),"Denial Code, ","")&IF(AND(TRIM($A71)<>"Finalized",$BD71=""),"Next Review Date, ","")&IF(AND(TRIM($A71)<>"Finalized",$BE71=""),"Next Step, ","")&IF(AND(TRIM($A71)="Finalized",$AV71="",$AR71="",$AT71="",$AX71="",$AW71=""),"CPT outcome, ",""),LEN(IF($B71="","Notes, ","")&IF($K71="","Latest Date Worked, ","")&IF($AY71="","Last Action, ","")&IF(AND(OR(TRIM($A71)="Denied",TRIM($A71)="Rejected"),$BA71=""),"Denial Reason, ","")&IF(AND(TRIM($A71)="Denied",$BB71="",TRIM($BA71)<>"NO DENIAL"),"Denial Code, ","")&IF(AND(TRIM($A71)<>"Finalized",$BD71=""),"Next Review Date, ","")&IF(AND(TRIM($A71)<>"Finalized",$BE71=""),"Next Step, ","")&IF(AND(TRIM($A71)="Finalized",$AV71="",$AR71="",$AT71="",$AX71="",$AW71=""),"CPT outcome, ",""))-2),"") -> Denial Code, Next Step | BI71: =IF($BB71="","",IFERROR(INDEX('Denial Codes'!$C:$C,MATCH(LEFT($BB71,FIND(" - ",$BB71&" - ")+2)&"*",'Denial Codes'!$A:$A,0)),"")) | BJ71: =IF($BA71="","",IFERROR(INDEX(Lists!$B:$B,MATCH(TRIM($BA71),Lists!$A:$A,0))&"","")) -> Verify eligibility; correct the member ID/MBI, name or DOB and resubmit.
A72: Denied | B72: Resubmitted to UHC as primary | C72: 571607238 | D72: 46135 | E72: HF470511781 | F72: 46098 | G72: United Healthcare | H72: United Healthcare | I72: Blue Cross Blue Shield of Arizona (BCBS AZ) | J72: 93970 x1 | K72: 46278 | L72: =IF($O72="","",$O72-TODAY()) -> -123 | M72: =IF(AND(TRIM($A72)="Finalized",$K72<>""),"",IF($D72="","",$D72+180-TODAY())) -> 4 | N72: =IF(AND(TRIM($A72)="Finalized",$K72<>""),"",IF($D72="","",$D72+365-TODAY())) -> 189 | O72: =IF(AND(TRIM($A72)="Finalized",$K72<>""),"",DATE(2026,6,15)) -> 46188 | P72: 90 days | Q72: UHC COMMERCIAL | R72: 180 days | S72: Processed date | T72: 365 days | U72: Processed date | V72: 2026-03 March | W72: US | AA72: 1 | AB72: =IF($F72="","",TODAY()-$F72) -> 213 | AC72: 93970 | AJ72: M5412 | AK72: R609 | AO72: LEATHEM, JARRETT | AP72: ASAP - Gilbert | AQ72: 46119 | AY72: Resubmitted | BA72: Wrong payer / vendor | BD72: 46308 | BF72: =IF(TRIM($A72)="Finalized","Closed",IF($BD72="","No review date set",IF($BD72<TODAY(),"OVERDUE",IF($BD72-TODAY()<=7,"Due within 7 days","Scheduled")))) -> OVERDUE | BG72: =IF($K72="","",TODAY()-$K72) -> 33 | BH72: =IFERROR(LEFT(IF($B72="","Notes, ","")&IF($K72="","Latest Date Worked, ","")&IF($AY72="","Last Action, ","")&IF(AND(OR(TRIM($A72)="Denied",TRIM($A72)="Rejected"),$BA72=""),"Denial Reason, ","")&IF(AND(TRIM($A72)="Denied",$BB72="",TRIM($BA72)<>"NO DENIAL"),"Denial Code, ","")&IF(AND(TRIM($A72)<>"Finalized",$BD72=""),"Next Review Date, ","")&IF(AND(TRIM($A72)<>"Finalized",$BE72=""),"Next Step, ","")&IF(AND(TRIM($A72)="Finalized",$AV72="",$AR72="",$AT72="",$AX72="",$AW72=""),"CPT outcome, ",""),LEN(IF($B72="","Notes, ","")&IF($K72="","Latest Date Worked, ","")&IF($AY72="","Last Action, ","")&IF(AND(OR(TRIM($A72)="Denied",TRIM($A72)="Rejected"),$BA72=""),"Denial Reason, ","")&IF(AND(TRIM($A72)="Denied",$BB72="",TRIM($BA72)<>"NO DENIAL"),"Denial Code, ","")&IF(AND(TRIM($A72)<>"Finalized",$BD72=""),"Next Review Date, ","")&IF(AND(TRIM($A72)<>"Finalized",$BE72=""),"Next Step, ","")&IF(AND(TRIM($A72)="Finalized",$AV72="",$AR72="",$AT72="",$AX72="",$AW72=""),"CPT outcome, ",""))-2),"") -> Denial Code, Next Step | BI72: =IF($BB72="","",IFERROR(INDEX('Denial Codes'!$C:$C,MATCH(LEFT($BB72,FIND(" - ",$BB72&" - ")+2)&"*",'Denial Codes'!$A:$A,0)),"")) | BJ72: =IF($BA72="","",IFERROR(INDEX(Lists!$B:$B,MATCH(TRIM($BA72),Lists!$A:$A,0))&"","")) -> Bill the correct payer, delegated vendor or capitated group/IPA (e.g. Optum Behavioral, Preferred Homecare).
A73: Denied | B73: Corrected cpt codes, added code 7, and resubmitted | C73: 571612561 | D73: 46146 | E73: HF505830380 | F73: 46098 | G73: AARP MedicareComplete (SecureHorizons & Oxford Network) | H73: AARP MedicareComplete (SecureHorizons & Oxford Network) | I73: No Payer | J73: 93970 x1; 93923 x1; 93925 x1 | K73: 46278 | L73: =IF($O73="","",$O73-TODAY()) -> -123 | M73: =IF(AND(TRIM($A73)="Finalized",$K73<>""),"",IF($D73="","",$D73+365-TODAY())) -> 200 | N73: =IF(AND(TRIM($A73)="Finalized",$K73<>""),"",IF($D73="","",$D73+365-TODAY())) -> 200 | O73: =IF(AND(TRIM($A73)="Finalized",$K73<>""),"",DATE(2026,6,15)) -> 46188 | P73: 90 days | Q73: AARP MA CHOICE / MEDICARE COMPLETE | R73: 365 days | S73: Processed date | T73: 365 days | U73: Processed date | V73: 2026-03 March | W73: US | AA73: 1 | AB73: =IF($F73="","",TODAY()-$F73) -> 213 | AC73: 93970 | AD73: 93923 | AE73: 93925 | AJ73: M79604 | AK73: M79605 | AL73: R600 | AO73: LEATHEM, JARRETT | AP73: ASAP - Gilbert | AQ73: 46106 | AX73: 93970, 93923, 93925 | AY73: Resubmitted | BA73: Timely filing | BB73: CO_29 - The time limit for filing has expired | BD73: 46308 | BF73: =IF(TRIM($A73)="Finalized","Closed",IF($BD73="","No review date set",IF($BD73<TODAY(),"OVERDUE",IF($BD73-TODAY()<=7,"Due within 7 days","Scheduled")))) -> OVERDUE | BG73: =IF($K73="","",TODAY()-$K73) -> 33 | BH73: =IFERROR(LEFT(IF($B73="","Notes, ","")&IF($K73="","Latest Date Worked, ","")&IF($AY73="","Last Action, ","")&IF(AND(OR(TRIM($A73)="Denied",TRIM($A73)="Rejected"),$BA73=""),"Denial Reason, ","")&IF(AND(TRIM($A73)="Denied",$BB73="",TRIM($BA73)<>"NO DENIAL"),"Denial Code, ","")&IF(AND(TRIM($A73)<>"Finalized",$BD73=""),"Next Review Date, ","")&IF(AND(TRIM($A73)<>"Finalized",$BE73=""),"Next Step, ","")&IF(AND(TRIM($A73)="Finalized",$AV73="",$AR73="",$AT73="",$AX73="",$AW73=""),"CPT outcome, ",""),LEN(IF($B73="","Notes, ","")&IF($K73="","Latest Date Worked, ","")&IF($AY73="","Last Action, ","")&IF(AND(OR(TRIM($A73)="Denied",TRIM($A73)="Rejected"),$BA73=""),"Denial Reason, ","")&IF(AND(TRIM($A73)="Denied",$BB73="",TRIM($BA73)<>"NO DENIAL"),"Denial Code, ","")&IF(AND(TRIM($A73)<>"Finalized",$BD73=""),"Next Review Date, ","")&IF(AND(TRIM($A73)<>"Finalized",$BE73=""),"Next Step, ","")&IF(AND(TRIM($A73)="Finalized",$AV73="",$AR73="",$AT73="",$AX73="",$AW73=""),"CPT outcome, ",""))-2),"") -> Next Step | BI73: =IF($BB73="","",IFERROR(INDEX('Denial Codes'!$C:$C,MATCH(LEFT($BB73,FIND(" - ",$BB73&" - ")+2)&"*",'Denial Codes'!$A:$A,0)),"")) -> Timely filing | BJ73: =IF($BA73="","",IFERROR(INDEX(Lists!$B:$B,MATCH(TRIM($BA73),Lists!$A:$A,0))&"","")) -> Find proof of timely filing (clearinghouse acceptance or earlier submission) and appeal with it; if none, adjust the balance.
A74: Denied | B74: Added Date of Current Illness, claim note, and resubmitted | C74: 570350220 | D74: 46268 | E74: HF341023592 | F74: 46099 | G74: Optum Care Medical Network of Arizona, Utah, & Washington (LifePrint) | H74: Optum Care Medical Network of Arizona, Utah, & Washington (LifePrint) | I74: No Payer | J74: 99493 x1; 99494 x1 | K74: 46265 | L74: =IF($O74="","",$O74-TODAY()) -> -122 | M74: =IF(AND(TRIM($A74)="Finalized",$K74<>""),"",IF($D74="","",$D74+365-TODAY())) -> 322 | N74: =IF(AND(TRIM($A74)="Finalized",$K74<>""),"",IF($D74="","",$D74+365-TODAY())) -> 322 | O74: =IF(AND(TRIM($A74)="Finalized",$K74<>""),"",DATE(2026,6,16)) -> 46189 | P74: 90 days | Q74: OPTUM | R74: 365 days | S74: Processed date | T74: 365 days | U74: Processed date | V74: 2026-03 March | W74: BH | AA74: 1 | AB74: =IF($F74="","",TODAY()-$F74) -> 212 | AC74: 99493 | AD74: 99494 | AJ74: F331 | AK74: F411 | AO74: TURLEY, TODD | AP74: ASAP - Gilbert | AQ74: 46153 | AV74: 99493 | AX74: 99493, 99494 | AY74: Resubmitted | BA74: Coding / billing error | BB74: OA_246 - This non-payable code is for required reporting only | BD74: 46295 | BF74: =IF(TRIM($A74)="Finalized","Closed",IF($BD74="","No review date set",IF($BD74<TODAY(),"OVERDUE",IF($BD74-TODAY()<=7,"Due within 7 days","Scheduled")))) -> OVERDUE | BG74: =IF($K74="","",TODAY()-$K74) -> 46 | BH74: =IFERROR(LEFT(IF($B74="","Notes, ","")&IF($K74="","Latest Date Worked, ","")&IF($AY74="","Last Action, ","")&IF(AND(OR(TRIM($A74)="Denied",TRIM($A74)="Rejected"),$BA74=""),"Denial Reason, ","")&IF(AND(TRIM($A74)="Denied",$BB74="",TRIM($BA74)<>"NO DENIAL"),"Denial Code, ","")&IF(AND(TRIM($A74)<>"Finalized",$BD74=""),"Next Review Date, ","")&IF(AND(TRIM($A74)<>"Finalized",$BE74=""),"Next Step, ","")&IF(AND(TRIM($A74)="Finalized",$AV74="",$AR74="",$AT74="",$AX74="",$AW74=""),"CPT outcome, ",""),LEN(IF($B74="","Notes, ","")&IF($K74="","Latest Date Worked, ","")&IF($AY74="","Last Action, ","")&IF(AND(OR(TRIM($A74)="Denied",TRIM($A74)="Rejected"),$BA74=""),"Denial Reason, ","")&IF(AND(TRIM($A74)="Denied",$BB74="",TRIM($BA74)<>"NO DENIAL"),"Denial Code, ","")&IF(AND(TRIM($A74)<>"Finalized",$BD74=""),"Next Review Date, ","")&IF(AND(TRIM($A74)<>"Finalized",$BE74=""),"Next Step, ","")&IF(AND(TRIM($A74)="Finalized",$AV74="",$AR74="",$AT74="",$AX74="",$AW74=""),"CPT outcome, ",""))-2),"") -> Next Step | BI74: =IF($BB74="","",IFERROR(INDEX('Denial Codes'!$C:$C,MATCH(LEFT($BB74,FIND(" - ",$BB74&" - ")+2)&"*",'Denial Codes'!$A:$A,0)),"")) -> Coding / billing error | BJ74: =IF($BA74="","",IFERROR(INDEX(Lists!$B:$B,MATCH(TRIM($BA74),Lists!$A:$A,0))&"","")) -> Fix the code, units, charge or other claim data and resubmit as a corrected claim.
A75: Denied | B75: Filed reconsideration with the 02/27/2026 order notes for BHE prior to SCS trial + March 2026 Monthly Review Summary - Jess uploaded MR | C75: 553133483 | D75: 46161 | E75: HF542079660 | F75: 46099 | G75: United Healthcare | H75: United Healthcare | I75: No Payer | J75: 99492 x1; 99494 x1 | K75: 46268 | L75: =IF($O75="","",$O75-TODAY()) -> -122 | M75: =IF(AND(TRIM($A75)="Finalized",$K75<>""),"",IF($D75="","",$D75+180-TODAY())) -> 30 | N75: =IF(AND(TRIM($A75)="Finalized",$K75<>""),"",IF($D75="","",$D75+365-TODAY())) -> 215 | O75: =IF(AND(TRIM($A75)="Finalized",$K75<>""),"",DATE(2026,6,16)) -> 46189 | P75: 90 days | Q75: UHC COMMERCIAL | R75: 180 days | S75: Processed date | T75: 365 days | U75: Processed date | V75: 2026-03 March | W75: BH | AA75: 1 | AB75: =IF($F75="","",TODAY()-$F75) -> 212 | AC75: 99492 | AD75: 99494 | AJ75: F39 | AO75: O'NEIL, ROY | AP75: ASAP - Gilbert | AQ75: 46119 | AY75: Recon filed | AZ75: Uploaded MR | BA75: Medical necessity / frequency | BC75: PIQ-90338069 | BD75: 46298 | BF75: =IF(TRIM($A75)="Finalized","Closed",IF($BD75="","No review date set",IF($BD75<TODAY(),"OVERDUE",IF($BD75-TODAY()<=7,"Due within 7 days","Scheduled")))) -> OVERDUE | BG75: =IF($K75="","",TODAY()-$K75) -> 43 | BH75: =IFERROR(LEFT(IF($B75="","Notes, ","")&IF($K75="","Latest Date Worked, ","")&IF($AY75="","Last Action, ","")&IF(AND(OR(TRIM($A75)="Denied",TRIM($A75)="Rejected"),$BA75=""),"Denial Reason, ","")&IF(AND(TRIM($A75)="Denied",$BB75="",TRIM($BA75)<>"NO DENIAL"),"Denial Code, ","")&IF(AND(TRIM($A75)<>"Finalized",$BD75=""),"Next Review Date, ","")&IF(AND(TRIM($A75)<>"Finalized",$BE75=""),"Next Step, ","")&IF(AND(TRIM($A75)="Finalized",$AV75="",$AR75="",$AT75="",$AX75="",$AW75=""),"CPT outcome, ",""),LEN(IF($B75="","Notes, ","")&IF($K75="","Latest Date Worked, ","")&IF($AY75="","Last Action, ","")&IF(AND(OR(TRIM($A75)="Denied",TRIM($A75)="Rejected"),$BA75=""),"Denial Reason, ","")&IF(AND(TRIM($A75)="Denied",$BB75="",TRIM($BA75)<>"NO DENIAL"),"Denial Code, ","")&IF(AND(TRIM($A75)<>"Finalized",$BD75=""),"Next Review Date, ","")&IF(AND(TRIM($A75)<>"Finalized",$BE75=""),"Next Step, ","")&IF(AND(TRIM($A75)="Finalized",$AV75="",$AR75="",$AT75="",$AX75="",$AW75=""),"CPT outcome, ",""))-2),"") -> Denial Code, Next Step | BI75: =IF($BB75="","",IFERROR(INDEX('Denial Codes'!$C:$C,MATCH(LEFT($BB75,FIND(" - ",$BB75&" - ")+2)&"*",'Denial Codes'!$A:$A,0)),"")) | BJ75: =IF($BA75="","",IFERROR(INDEX(Lists!$B:$B,MATCH(TRIM($BA75),Lists!$A:$A,0))&"","")) -> Appeal with medical records and a letter of medical necessity; check LCD/MUE limits.
